Workbook

Sheet Securities
B1: FUND INFO | U1: CATEGORY METRICS | AC1: PEER GROUP METRICS | AJ1: RETURNS | AQ1: CATEGORY RETURNS | AX1: CATEGORY RETURN RANK | BE1: CATEGORY SIZE | BL1: PEER GROUP RETURNS | BS1: PEER GROUP RETURN RANK | BZ1: PEER GROUP SIZE
B2: security_id | C2: security_name | D2: detailed_security_type | E2: investment_strategy | F2: fund_family | G2: fund_company_name | H2: broad_category_group | I2: broad_asset_class | J2: category_name | K2: category_index | L2: peer_group_name | M2: ycharts_benchmark_category | N2: inception_date_generic | O2: assets_under_management | P2: expense_ratio_generic | Q2: expense_ratio_rank | R2: expense_ratio_peer_group_rank | S2: max_manager_tenure | T2: discount_or_premium_to_nav | U2: alpha_rank | V2: information_ratio_rank | W2: sharpe_rank | X2: alpha_3y_vs_category | Y2: information_ratio_3y_vs_category | Z2: historical_sharpe_3y | AA2: rsquared_3y_vs_category | AB2: upside_downside_5y_vs_category | AC2: alpha_peer_group_rank | AD2: information_ratio_peer_group_rank | AE2: sharpe_peer_group_rank | AF2: market_alpha_3y_vs_pg | AG2: information_ratio_3y_vs_pg | AH2: rsquared_3y_vs_pg | AI2: upside_downside_5y_vs_pg | AJ2: one_month_total_return_nav | AK2: three_month_total_return_nav | AL2: ytd_total_return_nav | AM2: one_year_total_return_nav | AN2: annualized_three_year_total_return_nav | AO2: annualized_five_year_total_return_nav | AP2: annualized_ten_year_total_return_nav | AQ2: category_one_month_total_return | AR2: category_three_month_total_return | AS2: category_ytd_total_return | AT2: category_one_year_total_return | AU2: category_three_year_total_return | AV2: category_five_year_total_return | AW2: category_ten_year_total_return | AX2: one_month_total_return_rank_nav | AY2: three_month_total_return_rank_nav | AZ2: ytd_total_return_rank_nav | BA2: one_year_total_return_rank_nav | BB2: three_year_total_return_rank_nav | BC2: five_year_total_return_rank_nav | BD2: ten_year_total_return_rank_nav | BE2: one_month_total_return_rank_category_size_nav | BF2: three_month_total_return_rank_category_size_nav | BG2: ytd_total_return_rank_category_size_nav | BH2: one_year_total_return_rank_category_size_nav | BI2: three_year_total_return_rank_category_size_nav | BJ2: five_year_total_return_rank_category_size_nav | BK2: ten_year_total_return_rank_category_size_nav | BL2: peer_group_one_month_total_return | BM2: peer_group_three_month_total_return | BN2: peer_group_ytd_total_return | BO2: peer_group_one_year_total_return | BP2: peer_group_three_year_total_return | BQ2: peer_group_five_year_total_return | BR2: peer_group_ten_year_total_return | BS2: one_month_total_return_peer_group_rank_nav | BT2: three_month_total_return_peer_group_rank_nav | BU2: ytd_total_return_peer_group_rank_nav | BV2: one_year_total_return_peer_group_rank_nav | BW2: three_year_total_return_peer_group_rank_nav | BX2: five_year_total_return_peer_group_rank_nav | BY2: ten_year_total_return_peer_group_rank_nav | BZ2: one_month_total_return_peer_group_size_nav | CA2: three_month_total_return_peer_group_size_nav | CB2: ytd_total_return_peer_group_size_nav | CC2: one_year_total_return_peer_group_size_nav | CD2: three_year_total_return_peer_group_size_nav | CE2: five_year_total_return_peer_group_size_nav | CF2: ten_year_total_return_peer_group_size_nav
B3: M:APDFX | C3: {=_xll.YCI($B3,C$2)} -> Artisan High Income Fund Advisor | D3: {=_xll.YCI($B3,D$2)} -> mutual_fund | E3: {=_xll.YCI($B3,E$2)} -> The investment seeks to provide total return through a combination of current income and capital appreciation. Under normal circumstances, the fund will invest primarily in instruments that are rated, at the time of purchase, below investment grade (below BBB- by Standard & Poor's Rating Services ("S&P") or Fitch, Inc. ("Fitch") or below Baa3 by Moody's Investors Service, Inc. ("Moody's")), or comparably rated by another nationally recognized statistical rating organization ("NRSRO"), or unrated but determined by Artisan Partners to be of comparable quality. | F3: {=_xll.YCI($B3,F$2)} -> Artisan Partners Funds | G3: {=_xll.YCI($B3,G$2)} -> Artisan Partners Limited Partnership | H3: {=_xll.YCI($B3,H$2)} -> Fixed Income | I3: {=_xll.YCI($B3,I$2)} -> Taxable Bond | J3: {=_xll.YCI($B3,J$2)} -> High Yield Bond | ... N3: {=_xll.YCI($B3,N$2)} -> 2014-03-19 | O3: {=_xll.YCP($B3,O$2)} -> 4009299912 | P3: {=_xll.YCP($B3,P$2)} -> 0.008 | Q3: {=_xll.YCP($B3,Q$2)} -> 54 | R3: {=_xll.YCP($B3,R$2)} -> 56 | S3: {=_xll.YCP($B3,S$2)} -> 12.38 | T3: {=_xll.YCP($B3,T$2)} -> ERR: INVALID CALC | U3: {=_xll.YCP($B3,U$2)} -> 20 | V3: {=_xll.YCP($B3,V$2)} -> 38 | ... CF3: {=_xll.YCP($B3,CF$2)} -> 467
B4: AVDE | C4: {=_xll.YCI($B4,C$2)} -> Avantis International Equity ETF | D4: {=_xll.YCI($B4,D$2)} -> etf | E4: {=_xll.YCI($B4,E$2)} -> The investment seeks long-term capital appreciation. The fund invests primarily in a diverse group of non-U.S. companies across countries, market sectors and industry groups. It may invest in companies of all market capitalizations. Under normal market conditions, the fund will invest at least 80% of its assets in equity securities. It also may invest in derivative instruments such as futures contracts, currency forwards, and swap agreements. | F4: {=_xll.YCI($B4,F$2)} -> Avantis Investors | G4: {=_xll.YCI($B4,G$2)} -> American Century Investment Management Inc | H4: {=_xll.YCI($B4,H$2)} -> Equity | I4: {=_xll.YCI($B4,I$2)} -> International Equity | J4: {=_xll.YCI($B4,J$2)} -> Foreign Large Blend | ... N4: {=_xll.YCI($B4,N$2)} -> 2019-09-24 | O4: {=_xll.YCP($B4,O$2)} -> 18843246896 | P4: {=_xll.YCP($B4,P$2)} -> 0.0023 | Q4: {=_xll.YCP($B4,Q$2)} -> 14 | R4: {=_xll.YCP($B4,R$2)} -> 13 | S4: {=_xll.YCP($B4,S$2)} -> 6.86 | T4: {=_xll.YCP($B4,T$2)} -> 0.00176092 | U4: {=_xll.YCP($B4,U$2)} -> 14 | V4: {=_xll.YCP($B4,V$2)} -> 16 | ... CF4: {=_xll.YCP($B4,CF$2)} -> 164
B5: M:AVERX | C5: {=_xll.YCI($B5,C$2)} -> Ave Maria Value Focused Fund | D5: {=_xll.YCI($B5,D$2)} -> mutual_fund | E5: {=_xll.YCI($B5,E$2)} -> The investment seeks long-term capital appreciation. The fund invests at least 80% of its net assets, including the amount of any borrowings for investment purposes, in equity securities (which include common stocks, preferred stocks and securities convertible into common stocks). It may invest in the securities of companies of any size, regardless of market capitalization. The fund may also invest in exchange-traded funds ("ETFs") if the Adviser believes it is advisable to expose the fund to the broad market or to broad market sectors or to hedge against market risk without purchasing a large number of individual securities. The fund is non-diversified. | F5: {=_xll.YCI($B5,F$2)} -> Ave Maria Mutual Funds | G5: {=_xll.YCI($B5,G$2)} -> Schwartz Investment Counsel Inc | H5: {=_xll.YCI($B5,H$2)} -> Equity | I5: {=_xll.YCI($B5,I$2)} -> US Equity | J5: {=_xll.YCI($B5,J$2)} -> Mid-Cap Blend | ... N5: {=_xll.YCI($B5,N$2)} -> 1993-07-20 | O5: {=_xll.YCP($B5,O$2)} -> 132962126 | P5: {=_xll.YCP($B5,P$2)} -> 0.0113 | Q5: {=_xll.YCP($B5,Q$2)} -> 77 | R5: {=_xll.YCP($B5,R$2)} -> 71 | S5: {=_xll.YCP($B5,S$2)} -> 42.62 | T5: {=_xll.YCP($B5,T$2)} -> ERR: INVALID CALC | U5: {=_xll.YCP($B5,U$2)} -> 1 | V5: {=_xll.YCP($B5,V$2)} -> 5 | ... CF5: {=_xll.YCP($B5,CF$2)} -> 277
B6: AVIG | C6: {=_xll.YCI($B6,C$2)} -> Avantis Core Fixed Income ETF | D6: {=_xll.YCI($B6,D$2)} -> etf | E6: {=_xll.YCI($B6,E$2)} -> The investment seeks to maximize total return. The fund invests primarily in investment grade quality debt obligations from a diverse group of U.S. and non-U.S. issuers. Under normal market conditions, it will invest at least 80% of its net assets, plus any borrowings for investment purposes, in fixed income securities. The fund seeks to maintain a weighted average duration within 2 years of the weighted average duration of its benchmark, the Bloomberg U.S. Aggregate Bond index, as calculated by the manager. | F6: {=_xll.YCI($B6,F$2)} -> Avantis Investors | G6: {=_xll.YCI($B6,G$2)} -> American Century Investment Management Inc | H6: {=_xll.YCI($B6,H$2)} -> Fixed Income | I6: {=_xll.YCI($B6,I$2)} -> Taxable Bond | J6: {=_xll.YCI($B6,J$2)} -> Intermediate Core Bond | ... N6: {=_xll.YCI($B6,N$2)} -> 2020-10-13 | O6: {=_xll.YCP($B6,O$2)} -> 1980075978 | P6: {=_xll.YCP($B6,P$2)} -> 0.0015 | Q6: {=_xll.YCP($B6,Q$2)} -> 13 | R6: {=_xll.YCP($B6,R$2)} -> 8 | S6: {=_xll.YCP($B6,S$2)} -> 5.8 | T6: {=_xll.YCP($B6,T$2)} -> -5.645e-05 | U6: {=_xll.YCP($B6,U$2)} -> 20 | V6: {=_xll.YCP($B6,V$2)} -> 11 | ... CF6: {=_xll.YCP($B6,CF$2)} -> 24
B7: M:BIMIX | C7: {=_xll.YCI($B7,C$2)} -> Baird Intermediate Bond Fund Institutional | D7: {=_xll.YCI($B7,D$2)} -> mutual_fund | E7: {=_xll.YCI($B7,E$2)} -> The investment seeks an annual rate of total return, before fund expenses, greater than the annual rate of total return of the Bloomberg Intermediate U.S. government/Credit Index. The fund normally invests at least 80% of its net assets in the following types of U.S. dollar-denominated debt obligations: U.S. government and other public-sector agencies, asset-backed and mortgage-backed obligations of U.S. and foreign issuers and corporate debt of U.S. and foreign issuers. | F7: {=_xll.YCI($B7,F$2)} -> Baird | G7: {=_xll.YCI($B7,G$2)} -> Robert W. Baird & Co. Incorporated | H7: {=_xll.YCI($B7,H$2)} -> Fixed Income | I7: {=_xll.YCI($B7,I$2)} -> Taxable Bond | J7: {=_xll.YCI($B7,J$2)} -> Intermediate Core Bond | ... N7: {=_xll.YCI($B7,N$2)} -> 2000-09-29 | O7: {=_xll.YCP($B7,O$2)} -> 13133244822 | P7: {=_xll.YCP($B7,P$2)} -> 0.003 | Q7: {=_xll.YCP($B7,Q$2)} -> 33 | R7: {=_xll.YCP($B7,R$2)} -> 21 | S7: {=_xll.YCP($B7,S$2)} -> 25.85 | T7: {=_xll.YCP($B7,T$2)} -> ERR: INVALID CALC | U7: {=_xll.YCP($B7,U$2)} -> 13 | V7: {=_xll.YCP($B7,V$2)} -> 31 | ... CF7: {=_xll.YCP($B7,CF$2)} -> 154
B8: BIV | C8: {=_xll.YCI($B8,C$2)} -> Vanguard Intermediate-Term Bond Index Fund ETF | D8: {=_xll.YCI($B8,D$2)} -> etf | E8: {=_xll.YCI($B8,E$2)} -> The investment seeks to track the performance of the Bloomberg U.S. 5-10 Year Government/Credit Float Adjusted Index. This index includes all medium and larger issues of U.S. government, investment-grade corporate and investment-grade international dollar-denominated bonds that have maturities between 5 and 10 years and are publicly issued. All of the fund's investments will be selected through the sampling process, and at least 80% of its assets will be invested in bonds held in the index. | F8: {=_xll.YCI($B8,F$2)} -> Vanguard | G8: {=_xll.YCI($B8,G$2)} -> Vanguard Group, Inc. (via Vanguard Capital Mgmt) | H8: {=_xll.YCI($B8,H$2)} -> Fixed Income | I8: {=_xll.YCI($B8,I$2)} -> Taxable Bond | J8: {=_xll.YCI($B8,J$2)} -> Intermediate Core Bond | ... N8: {=_xll.YCI($B8,N$2)} -> 2007-04-03 | O8: {=_xll.YCP($B8,O$2)} -> 28797391268 | P8: {=_xll.YCP($B8,P$2)} -> 0.0003 | Q8: {=_xll.YCP($B8,Q$2)} -> 7 | R8: {=_xll.YCP($B8,R$2)} -> 4 | S8: {=_xll.YCP($B8,S$2)} -> 18.28 | T8: {=_xll.YCP($B8,T$2)} -> 0 | U8: {=_xll.YCP($B8,U$2)} -> 18 | V8: {=_xll.YCP($B8,V$2)} -> 16 | ... CF8: {=_xll.YCP($B8,CF$2)} -> 488
B9: M:BRXIX | C9: {=_xll.YCI($B9,C$2)} -> MFS Blended Research International Equity Fund I | D9: {=_xll.YCI($B9,D$2)} -> mutual_fund | E9: {=_xll.YCI($B9,E$2)} -> The investment seeks capital appreciation. The fund normally invests at least 80% of the fund's net assets in equity securities. Equity securities include common stocks and other securities that represent an ownership interest (or right to acquire an ownership interest) in a company or other issuer. MFS primarily invests in securities of companies with large capitalizations. MFS normally invests the fund's assets across different industries, sectors, countries, and regions, but MFS may invest a significant percentage of the fund's assets in issuers in a single industry, sector, country, or region. | F9: {=_xll.YCI($B9,F$2)} -> MFS | G9: {=_xll.YCI($B9,G$2)} -> Massachusetts Financial Services Company | H9: {=_xll.YCI($B9,H$2)} -> Equity | I9: {=_xll.YCI($B9,I$2)} -> International Equity | J9: {=_xll.YCI($B9,J$2)} -> Foreign Large Blend | ... N9: {=_xll.YCI($B9,N$2)} -> 2015-09-15 | O9: {=_xll.YCP($B9,O$2)} -> 4055533673 | P9: {=_xll.YCP($B9,P$2)} -> 0.0052 | Q9: {=_xll.YCP($B9,Q$2)} -> 37 | R9: {=_xll.YCP($B9,R$2)} -> 14 | S9: {=_xll.YCP($B9,S$2)} -> 10.88 | T9: {=_xll.YCP($B9,T$2)} -> ERR: INVALID CALC | U9: {=_xll.YCP($B9,U$2)} -> 2 | V9: {=_xll.YCP($B9,V$2)} -> 1 | ... CF9: {=_xll.YCP($B9,CF$2)} -> 129
B10: DFCF | C10: {=_xll.YCI($B10,C$2)} -> DFA Dimensional Core Fixed Income ETF | D10: {=_xll.YCI($B10,D$2)} -> etf | E10: {=_xll.YCI($B10,E$2)} -> The investment seeks to maximize total returns from the universe of eligible investments; Total return is comprised of income and capital appreciation. Under normal circumstances, at least 80% of the Portfolio’s net assets will be invested in fixed income securities considered to be investment grade quality. The Portfolio primarily invests in securities that mature within twenty years from the date of settlement. The Portfolio will generally maintain a weighted average duration of no more than one quarter year greater than, and no less than one year below, the weighted average duration of the Portfolio’s benchmark, the Bloomberg U.S. Aggregate Bond Index. | F10: {=_xll.YCI($B10,F$2)} -> Dimensional Fund Advisors | G10: {=_xll.YCI($B10,G$2)} -> Dimensional Fund Advisors LP | H10: {=_xll.YCI($B10,H$2)} -> Fixed Income | I10: {=_xll.YCI($B10,I$2)} -> Taxable Bond | J10: {=_xll.YCI($B10,J$2)} -> Intermediate Core Bond | ... N10: {=_xll.YCI($B10,N$2)} -> 2021-11-15 | O10: {=_xll.YCP($B10,O$2)} -> 10915181278 | P10: {=_xll.YCP($B10,P$2)} -> 0.0017 | Q10: {=_xll.YCP($B10,Q$2)} -> 14 | R10: {=_xll.YCP($B10,R$2)} -> 18 | S10: {=_xll.YCP($B10,S$2)} -> 4.71 | T10: {=_xll.YCP($B10,T$2)} -> 0.00048216 | U10: {=_xll.YCP($B10,U$2)} -> 12 | V10: {=_xll.YCP($B10,V$2)} -> 8 | ... CF10: {=_xll.YCP($B10,CF$2)} -> 210
B11: M:DHRIX | C11: {=_xll.YCI($B11,C$2)} -> Diamond Hill Core Bond Fund I | D11: {=_xll.YCI($B11,D$2)} -> mutual_fund | E11: {=_xll.YCI($B11,E$2)} -> The investment seeks to maximize total return consistent with the preservation of capital. The Advisor intends to provide total return by investing at least 80% of its net assets at the time of purchase in a diversified portfolio of investment grade, fixed income securities, including bonds, debt securities and other similar U.S. dollar-denominated instruments issued by various U.S. public- or private-sector entities, by non-U.S. corporations or U.S. affiliates of non-U.S. corporations, including those in emerging markets. | F11: {=_xll.YCI($B11,F$2)} -> Diamond Hill Funds | G11: {=_xll.YCI($B11,G$2)} -> Diamond Hill Capital Management, LLC | H11: {=_xll.YCI($B11,H$2)} -> Fixed Income | I11: {=_xll.YCI($B11,I$2)} -> Taxable Bond | J11: {=_xll.YCI($B11,J$2)} -> Intermediate Core Bond | ... N11: {=_xll.YCI($B11,N$2)} -> 2016-07-05 | O11: {=_xll.YCP($B11,O$2)} -> 2477684562 | P11: {=_xll.YCP($B11,P$2)} -> 0.0048 | Q11: {=_xll.YCP($B11,Q$2)} -> 59 | R11: {=_xll.YCP($B11,R$2)} -> 48 | S11: {=_xll.YCP($B11,S$2)} -> 10.08 | T11: {=_xll.YCP($B11,T$2)} -> ERR: INVALID CALC | U11: {=_xll.YCP($B11,U$2)} -> 9 | V11: {=_xll.YCP($B11,V$2)} -> 5 | ... CF11: {=_xll.YCP($B11,CF$2)} -> 488
B12: M:EICOX | C12: {=_xll.YCI($B12,C$2)} -> Eaton Vance Emerging and Frontier Countries Eq I | D12: {=_xll.YCI($B12,D$2)} -> mutual_fund | E12: {=_xll.YCI($B12,E$2)} -> The investment seeks total return. The fund seeks its investment objective by investing at least 80% of its net assets (plus the amount of any borrowings for investment purposes) in equity investments in emerging and frontier market countries. Emerging market countries are countries represented in the MSCI Emerging Markets Index. Equity investments include common stocks, preferred stocks, private equity securities and other instruments that provide exposure to equity securities or markets. The fund is non-diversified. | F12: {=_xll.YCI($B12,F$2)} -> Eaton Vance | G12: {=_xll.YCI($B12,G$2)} -> Boston Management and Research | H12: {=_xll.YCI($B12,H$2)} -> Equity | I12: {=_xll.YCI($B12,I$2)} -> International Equity | J12: {=_xll.YCI($B12,J$2)} -> Diversified Emerging Mkts | ... N12: {=_xll.YCI($B12,N$2)} -> 2013-11-01 | O12: {=_xll.YCP($B12,O$2)} -> 3971296779 | P12: {=_xll.YCP($B12,P$2)} -> 0.0115 | Q12: {=_xll.YCP($B12,Q$2)} -> 67 | R12: {=_xll.YCP($B12,R$2)} -> 36 | S12: {=_xll.YCP($B12,S$2)} -> 3.34 | T12: {=_xll.YCP($B12,T$2)} -> ERR: INVALID CALC | U12: {=_xll.YCP($B12,U$2)} -> 13 | V12: {=_xll.YCP($B12,V$2)} -> 14 | ... CF12: {=_xll.YCP($B12,CF$2)} -> 12
B13: EMMF | C13: {=_xll.YCI($B13,C$2)} -> WisdomTree Emerging Markets Multifactor Fund | D13: {=_xll.YCI($B13,D$2)} -> etf | E13: {=_xll.YCI($B13,E$2)} -> The investment seeks capital appreciation. The fund invests, under normal circumstances, at least 80% of its net assets, plus any borrowings for investment purposes, in securities of emerging markets issuers and/or investments that have economic characteristics that are substantially similar to the economic characteristics of such securities. The fund manager generally expects to invest in large- and mid-capitalization companies, but the fund may also invest in small-capitalization companies. It is non-diversified. | F13: {=_xll.YCI($B13,F$2)} -> WisdomTree | G13: {=_xll.YCI($B13,G$2)} -> WisdomTree Asset Management Inc | H13: {=_xll.YCI($B13,H$2)} -> Equity | I13: {=_xll.YCI($B13,I$2)} -> International Equity | J13: {=_xll.YCI($B13,J$2)} -> Diversified Emerging Mkts | ... N13: {=_xll.YCI($B13,N$2)} -> 2018-08-10 | O13: {=_xll.YCP($B13,O$2)} -> 181517157 | P13: {=_xll.YCP($B13,P$2)} -> 0.0048 | Q13: {=_xll.YCP($B13,Q$2)} -> 22 | R13: {=_xll.YCP($B13,R$2)} -> 14 | S13: {=_xll.YCP($B13,S$2)} -> 5.77 | T13: {=_xll.YCP($B13,T$2)} -> -0.00900941 | U13: {=_xll.YCP($B13,U$2)} -> 31 | V13: {=_xll.YCP($B13,V$2)} -> 58 | ... CF13: {=_xll.YCP($B13,CF$2)} -> 597
B14: EYLD | C14: {=_xll.YCI($B14,C$2)} -> Cambria Emerging Shareholder Yield ETF | D14: {=_xll.YCI($B14,D$2)} -> etf | E14: {=_xll.YCI($B14,E$2)} -> The investment seeks income and capital appreciation. The fund is actively managed and seeks to achieve its investment objective by investing, under normal market conditions, at least 80% of its total assets in equity securities, including common stock and depositary receipts, issued by publicly listed companies in emerging foreign markets that provide high "shareholder yield." Its investment adviser, Cambria Investment Management, L.P. ("Cambria" or the "Adviser"), defines "shareholder yield" as the totality of returns realized by an investor from a company’s cash payments for dividends, buybacks and debt paydowns. | F14: {=_xll.YCI($B14,F$2)} -> Cambria | G14: {=_xll.YCI($B14,G$2)} -> Cambria Investment Management, L.P. | H14: {=_xll.YCI($B14,H$2)} -> Equity | I14: {=_xll.YCI($B14,I$2)} -> International Equity | J14: {=_xll.YCI($B14,J$2)} -> Diversified Emerging Mkts | ... N14: {=_xll.YCI($B14,N$2)} -> 2016-07-14 | O14: {=_xll.YCP($B14,O$2)} -> 893585101 | P14: {=_xll.YCP($B14,P$2)} -> 0.0063 | Q14: {=_xll.YCP($B14,Q$2)} -> 25 | R14: {=_xll.YCP($B14,R$2)} -> 18 | S14: {=_xll.YCP($B14,S$2)} -> 10.06 | T14: {=_xll.YCP($B14,T$2)} -> -0.00513506 | U14: {=_xll.YCP($B14,U$2)} -> 11 | V14: {=_xll.YCP($B14,V$2)} -> 17 | ... CF14: {=_xll.YCP($B14,CF$2)} -> 597
... B44: XSMO | C44: {=_xll.YCI($B44,C$2)} -> Invesco S&P SmallCap Momentum ETF | D44: {=_xll.YCI($B44,D$2)} -> etf | E44: {=_xll.YCI($B44,E$2)} -> The investment seeks to track the investment results (before fees and expenses) of the S&P SmallCap 600 Momentum Index (the "underlying index"). The fund generally will invest at least 90% of its total assets in securities that comprise the underlying index. Strictly in accordance with its guidelines and mandated procedures, the index provider compiles, maintains and calculates the underlying index, which is composed of constituents of the S&P SmallCap 600® Index that have the highest "momentum score." | F44: {=_xll.YCI($B44,F$2)} -> Invesco | G44: {=_xll.YCI($B44,G$2)} -> Invesco Capital Management LLC | H44: {=_xll.YCI($B44,H$2)} -> Equity | I44: {=_xll.YCI($B44,I$2)} -> US Equity | J44: {=_xll.YCI($B44,J$2)} -> Small Blend | ... N44: {=_xll.YCI($B44,N$2)} -> 2005-03-03 | O44: {=_xll.YCP($B44,O$2)} -> 3084880065 | P44: {=_xll.YCP($B44,P$2)} -> 0.0035 | Q44: {=_xll.YCP($B44,Q$2)} -> 17 | R44: {=_xll.YCP($B44,R$2)} -> 11 | S44: {=_xll.YCP($B44,S$2)} -> 19.18 | T44: {=_xll.YCP($B44,T$2)} -> 0.00057006 | U44: {=_xll.YCP($B44,U$2)} -> 4 | V44: {=_xll.YCP($B44,V$2)} -> 3 | ... CF44: {=_xll.YCP($B44,CF$2)} -> 997
C45: {=_xll.YCI($B45,C$2)} | D45: {=_xll.YCI($B45,D$2)} | E45: {=_xll.YCI($B45,E$2)} | F45: {=_xll.YCI($B45,F$2)} | G45: {=_xll.YCI($B45,G$2)} | H45: {=_xll.YCI($B45,H$2)} | I45: {=_xll.YCI($B45,I$2)} | J45: {=_xll.YCI($B45,J$2)} | ... N45: {=_xll.YCI($B45,N$2)} | O45: {=_xll.YCP($B45,O$2)} | P45: {=_xll.YCP($B45,P$2)} | Q45: {=_xll.YCP($B45,Q$2)} | R45: {=_xll.YCP($B45,R$2)} | S45: {=_xll.YCP($B45,S$2)} | T45: {=_xll.YCP($B45,T$2)} | U45: {=_xll.YCP($B45,U$2)} | W45: {=_xll.YCP($B45,W$2)} | AA45: {=_xll.YCP($B45,AA$2)} | AB45: {=_xll.YCP($B45,AB$2)} | AC45: {=_xll.YCP($B45,AC$2)} | AE45: {=_xll.YCP($B45,AE$2)} | AH45: {=_xll.YCP($B45,AH$2)} | AI45: {=_xll.YCP($B45,AI$2)} | AJ45: {=_xll.YCP($B45,AJ$2)} | AK45: {=_xll.YCP($B45,AK$2)} | AL45: {=_xll.YCP($B45,AL$2)} | AM45: {=_xll.YCP($B45,AM$2)} | AN45: {=_xll.YCP($B45,AN$2)} | AO45: {=_xll.YCP($B45,AO$2)} | ... CF45: {=_xll.YCP($B45,CF$2)}
C46: {=_xll.YCI($B46,C$2)} | D46: {=_xll.YCI($B46,D$2)} | E46: {=_xll.YCI($B46,E$2)} | F46: {=_xll.YCI($B46,F$2)} | G46: {=_xll.YCI($B46,G$2)} | H46: {=_xll.YCI($B46,H$2)} | I46: {=_xll.YCI($B46,I$2)} | J46: {=_xll.YCI($B46,J$2)} | ... N46: {=_xll.YCI($B46,N$2)} | O46: {=_xll.YCP($B46,O$2)} | P46: {=_xll.YCP($B46,P$2)} | Q46: {=_xll.YCP($B46,Q$2)} | R46: {=_xll.YCP($B46,R$2)} | S46: {=_xll.YCP($B46,S$2)} | T46: {=_xll.YCP($B46,T$2)} | U46: {=_xll.YCP($B46,U$2)} | W46: {=_xll.YCP($B46,W$2)} | AA46: {=_xll.YCP($B46,AA$2)} | AB46: {=_xll.YCP($B46,AB$2)} | AC46: {=_xll.YCP($B46,AC$2)} | AE46: {=_xll.YCP($B46,AE$2)} | AH46: {=_xll.YCP($B46,AH$2)} | AI46: {=_xll.YCP($B46,AI$2)} | AJ46: {=_xll.YCP($B46,AJ$2)} | AK46: {=_xll.YCP($B46,AK$2)} | AL46: {=_xll.YCP($B46,AL$2)} | AM46: {=_xll.YCP($B46,AM$2)} | AN46: {=_xll.YCP($B46,AN$2)} | AO46: {=_xll.YCP($B46,AO$2)} | ... CF46: {=_xll.YCP($B46,CF$2)}
C47: {=_xll.YCI($B47,C$2)} | D47: {=_xll.YCI($B47,D$2)} | E47: {=_xll.YCI($B47,E$2)} | F47: {=_xll.YCI($B47,F$2)} | G47: {=_xll.YCI($B47,G$2)} | H47: {=_xll.YCI($B47,H$2)} | I47: {=_xll.YCI($B47,I$2)} | J47: {=_xll.YCI($B47,J$2)} | ... N47: {=_xll.YCI($B47,N$2)} | O47: {=_xll.YCP($B47,O$2)} | P47: {=_xll.YCP($B47,P$2)} | Q47: {=_xll.YCP($B47,Q$2)} | R47: {=_xll.YCP($B47,R$2)} | S47: {=_xll.YCP($B47,S$2)} | T47: {=_xll.YCP($B47,T$2)} | U47: {=_xll.YCP($B47,U$2)} | W47: {=_xll.YCP($B47,W$2)} | AA47: {=_xll.YCP($B47,AA$2)} | AB47: {=_xll.YCP($B47,AB$2)} | AC47: {=_xll.YCP($B47,AC$2)} | AE47: {=_xll.YCP($B47,AE$2)} | AH47: {=_xll.YCP($B47,AH$2)} | AI47: {=_xll.YCP($B47,AI$2)} | AJ47: {=_xll.YCP($B47,AJ$2)} | AK47: {=_xll.YCP($B47,AK$2)} | AL47: {=_xll.YCP($B47,AL$2)} | AM47: {=_xll.YCP($B47,AM$2)} | AN47: {=_xll.YCP($B47,AN$2)} | AO47: {=_xll.YCP($B47,AO$2)} | ... BR47: {=_xll.YCP($B47,BR$2)} | BT47: {=_xll.YCP($B47,BT$2)} | BU47: {=_xll.YCP($B47,BU$2)} | BV47: {=_xll.YCP($B47,BV$2)} | BW47: {=_xll.YCP($B47,BW$2)} | BX47: {=_xll.YCP($B47,BX$2)} | BY47: {=_xll.YCP($B47,BY$2)} | BZ47: {=_xll.YCP($B47,BZ$2)} | CA47: {=_xll.YCP($B47,CA$2)} | ... CF47: {=_xll.YCP($B47,CF$2)}
C48: {=_xll.YCI($B48,C$2)} | D48: {=_xll.YCI($B48,D$2)} | E48: {=_xll.YCI($B48,E$2)} | F48: {=_xll.YCI($B48,F$2)} | G48: {=_xll.YCI($B48,G$2)} | H48: {=_xll.YCI($B48,H$2)} | I48: {=_xll.YCI($B48,I$2)} | J48: {=_xll.YCI($B48,J$2)} | ... N48: {=_xll.YCI($B48,N$2)} | O48: {=_xll.YCP($B48,O$2)} | P48: {=_xll.YCP($B48,P$2)} | Q48: {=_xll.YCP($B48,Q$2)} | R48: {=_xll.YCP($B48,R$2)} | S48: {=_xll.YCP($B48,S$2)} | T48: {=_xll.YCP($B48,T$2)} | U48: {=_xll.YCP($B48,U$2)} | W48: {=_xll.YCP($B48,W$2)} | AA48: {=_xll.YCP($B48,AA$2)} | AB48: {=_xll.YCP($B48,AB$2)} | AC48: {=_xll.YCP($B48,AC$2)} | AE48: {=_xll.YCP($B48,AE$2)} | AH48: {=_xll.YCP($B48,AH$2)} | AI48: {=_xll.YCP($B48,AI$2)} | AJ48: {=_xll.YCP($B48,AJ$2)} | AK48: {=_xll.YCP($B48,AK$2)} | AL48: {=_xll.YCP($B48,AL$2)} | AM48: {=_xll.YCP($B48,AM$2)} | AN48: {=_xll.YCP($B48,AN$2)} | AO48: {=_xll.YCP($B48,AO$2)} | ... BR48: {=_xll.YCP($B48,BR$2)} | BT48: {=_xll.YCP($B48,BT$2)} | BU48: {=_xll.YCP($B48,BU$2)} | BV48: {=_xll.YCP($B48,BV$2)} | BW48: {=_xll.YCP($B48,BW$2)} | BX48: {=_xll.YCP($B48,BX$2)} | BY48: {=_xll.YCP($B48,BY$2)} | BZ48: {=_xll.YCP($B48,BZ$2)} | CA48: {=_xll.YCP($B48,CA$2)} | ... CF48: {=_xll.YCP($B48,CF$2)}
C49: {=_xll.YCI($B49,C$2)} | D49: {=_xll.YCI($B49,D$2)} | E49: {=_xll.YCI($B49,E$2)} | F49: {=_xll.YCI($B49,F$2)} | G49: {=_xll.YCI($B49,G$2)} | H49: {=_xll.YCI($B49,H$2)} | I49: {=_xll.YCI($B49,I$2)} | J49: {=_xll.YCI($B49,J$2)} | ... N49: {=_xll.YCI($B49,N$2)} | O49: {=_xll.YCP($B49,O$2)} | P49: {=_xll.YCP($B49,P$2)} | Q49: {=_xll.YCP($B49,Q$2)} | R49: {=_xll.YCP($B49,R$2)} | S49: {=_xll.YCP($B49,S$2)} | T49: {=_xll.YCP($B49,T$2)} | U49: {=_xll.YCP($B49,U$2)} | W49: {=_xll.YCP($B49,W$2)} | AA49: {=_xll.YCP($B49,AA$2)} | AB49: {=_xll.YCP($B49,AB$2)} | AC49: {=_xll.YCP($B49,AC$2)} | AE49: {=_xll.YCP($B49,AE$2)} | AH49: {=_xll.YCP($B49,AH$2)} | AI49: {=_xll.YCP($B49,AI$2)} | AJ49: {=_xll.YCP($B49,AJ$2)} | AK49: {=_xll.YCP($B49,AK$2)} | AL49: {=_xll.YCP($B49,AL$2)} | AM49: {=_xll.YCP($B49,AM$2)} | AN49: {=_xll.YCP($B49,AN$2)} | AO49: {=_xll.YCP($B49,AO$2)} | ... BR49: {=_xll.YCP($B49,BR$2)} | BT49: {=_xll.YCP($B49,BT$2)} | BU49: {=_xll.YCP($B49,BU$2)} | BV49: {=_xll.YCP($B49,BV$2)} | BW49: {=_xll.YCP($B49,BW$2)} | BX49: {=_xll.YCP($B49,BX$2)} | BY49: {=_xll.YCP($B49,BY$2)} | BZ49: {=_xll.YCP($B49,BZ$2)} | CA49: {=_xll.YCP($B49,CA$2)} | ... CF49: {=_xll.YCP($B49,CF$2)}
C50: {=_xll.YCI($B50,C$2)} | D50: {=_xll.YCI($B50,D$2)} | E50: {=_xll.YCI($B50,E$2)} | F50: {=_xll.YCI($B50,F$2)} | G50: {=_xll.YCI($B50,G$2)} | H50: {=_xll.YCI($B50,H$2)} | I50: {=_xll.YCI($B50,I$2)} | J50: {=_xll.YCI($B50,J$2)} | ... N50: {=_xll.YCI($B50,N$2)} | O50: {=_xll.YCP($B50,O$2)} | P50: {=_xll.YCP($B50,P$2)} | Q50: {=_xll.YCP($B50,Q$2)} | R50: {=_xll.YCP($B50,R$2)} | S50: {=_xll.YCP($B50,S$2)} | T50: {=_xll.YCP($B50,T$2)} | U50: {=_xll.YCP($B50,U$2)} | W50: {=_xll.YCP($B50,W$2)} | AA50: {=_xll.YCP($B50,AA$2)} | AB50: {=_xll.YCP($B50,AB$2)} | AC50: {=_xll.YCP($B50,AC$2)} | AE50: {=_xll.YCP($B50,AE$2)} | AH50: {=_xll.YCP($B50,AH$2)} | AI50: {=_xll.YCP($B50,AI$2)} | AJ50: {=_xll.YCP($B50,AJ$2)} | AK50: {=_xll.YCP($B50,AK$2)} | AL50: {=_xll.YCP($B50,AL$2)} | AM50: {=_xll.YCP($B50,AM$2)} | AN50: {=_xll.YCP($B50,AN$2)} | AO50: {=_xll.YCP($B50,AO$2)} | ... BR50: {=_xll.YCP($B50,BR$2)} | BT50: {=_xll.YCP($B50,BT$2)} | BU50: {=_xll.YCP($B50,BU$2)} | BV50: {=_xll.YCP($B50,BV$2)} | BW50: {=_xll.YCP($B50,BW$2)} | BX50: {=_xll.YCP($B50,BX$2)} | BY50: {=_xll.YCP($B50,BY$2)} | BZ50: {=_xll.YCP($B50,BZ$2)} | CA50: {=_xll.YCP($B50,CA$2)} | ... CF50: {=_xll.YCP($B50,CF$2)}
C51: {=_xll.YCI($B51,C$2)} | D51: {=_xll.YCI($B51,D$2)} | E51: {=_xll.YCI($B51,E$2)} | F51: {=_xll.YCI($B51,F$2)} | G51: {=_xll.YCI($B51,G$2)} | H51: {=_xll.YCI($B51,H$2)} | I51: {=_xll.YCI($B51,I$2)} | J51: {=_xll.YCI($B51,J$2)} | ... N51: {=_xll.YCI($B51,N$2)} | O51: {=_xll.YCP($B51,O$2)} | P51: {=_xll.YCP($B51,P$2)} | Q51: {=_xll.YCP($B51,Q$2)} | R51: {=_xll.YCP($B51,R$2)} | S51: {=_xll.YCP($B51,S$2)} | T51: {=_xll.YCP($B51,T$2)} | U51: {=_xll.YCP($B51,U$2)} | W51: {=_xll.YCP($B51,W$2)} | AA51: {=_xll.YCP($B51,AA$2)} | AB51: {=_xll.YCP($B51,AB$2)} | AC51: {=_xll.YCP($B51,AC$2)} | AE51: {=_xll.YCP($B51,AE$2)} | AH51: {=_xll.YCP($B51,AH$2)} | AI51: {=_xll.YCP($B51,AI$2)} | AJ51: {=_xll.YCP($B51,AJ$2)} | AK51: {=_xll.YCP($B51,AK$2)} | AL51: {=_xll.YCP($B51,AL$2)} | AM51: {=_xll.YCP($B51,AM$2)} | AN51: {=_xll.YCP($B51,AN$2)} | AO51: {=_xll.YCP($B51,AO$2)} | ... BR51: {=_xll.YCP($B51,BR$2)} | BT51: {=_xll.YCP($B51,BT$2)} | BU51: {=_xll.YCP($B51,BU$2)} | BV51: {=_xll.YCP($B51,BV$2)} | BW51: {=_xll.YCP($B51,BW$2)} | BX51: {=_xll.YCP($B51,BX$2)} | BY51: {=_xll.YCP($B51,BY$2)} | BZ51: {=_xll.YCP($B51,BZ$2)} | CA51: {=_xll.YCP($B51,CA$2)} | ... CF51: {=_xll.YCP($B51,CF$2)}
C52: {=_xll.YCI($B52,C$2)} | D52: {=_xll.YCI($B52,D$2)} | E52: {=_xll.YCI($B52,E$2)} | F52: {=_xll.YCI($B52,F$2)} | G52: {=_xll.YCI($B52,G$2)} | H52: {=_xll.YCI($B52,H$2)} | I52: {=_xll.YCI($B52,I$2)} | J52: {=_xll.YCI($B52,J$2)} | ... N52: {=_xll.YCI($B52,N$2)} | O52: {=_xll.YCP($B52,O$2)} | P52: {=_xll.YCP($B52,P$2)} | Q52: {=_xll.YCP($B52,Q$2)} | R52: {=_xll.YCP($B52,R$2)} | S52: {=_xll.YCP($B52,S$2)} | T52: {=_xll.YCP($B52,T$2)} | U52: {=_xll.YCP($B52,U$2)} | W52: {=_xll.YCP($B52,W$2)} | AA52: {=_xll.YCP($B52,AA$2)} | AB52: {=_xll.YCP($B52,AB$2)} | AC52: {=_xll.YCP($B52,AC$2)} | AE52: {=_xll.YCP($B52,AE$2)} | AH52: {=_xll.YCP($B52,AH$2)} | AI52: {=_xll.YCP($B52,AI$2)} | AJ52: {=_xll.YCP($B52,AJ$2)} | AK52: {=_xll.YCP($B52,AK$2)} | AL52: {=_xll.YCP($B52,AL$2)} | AM52: {=_xll.YCP($B52,AM$2)} | AN52: {=_xll.YCP($B52,AN$2)} | AO52: {=_xll.YCP($B52,AO$2)} | ... BR52: {=_xll.YCP($B52,BR$2)} | BT52: {=_xll.YCP($B52,BT$2)} | BU52: {=_xll.YCP($B52,BU$2)} | BV52: {=_xll.YCP($B52,BV$2)} | BW52: {=_xll.YCP($B52,BW$2)} | BX52: {=_xll.YCP($B52,BX$2)} | BY52: {=_xll.YCP($B52,BY$2)} | BZ52: {=_xll.YCP($B52,BZ$2)} | CA52: {=_xll.YCP($B52,CA$2)} | ... CF52: {=_xll.YCP($B52,CF$2)}
C53: {=_xll.YCI($B53,C$2)} | D53: {=_xll.YCI($B53,D$2)} | E53: {=_xll.YCI($B53,E$2)} | F53: {=_xll.YCI($B53,F$2)} | G53: {=_xll.YCI($B53,G$2)} | H53: {=_xll.YCI($B53,H$2)} | I53: {=_xll.YCI($B53,I$2)} | J53: {=_xll.YCI($B53,J$2)} | ... N53: {=_xll.YCI($B53,N$2)} | O53: {=_xll.YCP($B53,O$2)} | P53: {=_xll.YCP($B53,P$2)} | Q53: {=_xll.YCP($B53,Q$2)} | R53: {=_xll.YCP($B53,R$2)} | S53: {=_xll.YCP($B53,S$2)} | T53: {=_xll.YCP($B53,T$2)} | U53: {=_xll.YCP($B53,U$2)} | W53: {=_xll.YCP($B53,W$2)} | AA53: {=_xll.YCP($B53,AA$2)} | AB53: {=_xll.YCP($B53,AB$2)} | AC53: {=_xll.YCP($B53,AC$2)} | AE53: {=_xll.YCP($B53,AE$2)} | AH53: {=_xll.YCP($B53,AH$2)} | AI53: {=_xll.YCP($B53,AI$2)} | AJ53: {=_xll.YCP($B53,AJ$2)} | AK53: {=_xll.YCP($B53,AK$2)} | AL53: {=_xll.YCP($B53,AL$2)} | AM53: {=_xll.YCP($B53,AM$2)} | AN53: {=_xll.YCP($B53,AN$2)} | AO53: {=_xll.YCP($B53,AO$2)} | ... BR53: {=_xll.YCP($B53,BR$2)} | BT53: {=_xll.YCP($B53,BT$2)} | BU53: {=_xll.YCP($B53,BU$2)} | BV53: {=_xll.YCP($B53,BV$2)} | BW53: {=_xll.YCP($B53,BW$2)} | BX53: {=_xll.YCP($B53,BX$2)} | BY53: {=_xll.YCP($B53,BY$2)} | BZ53: {=_xll.YCP($B53,BZ$2)} | CA53: {=_xll.YCP($B53,CA$2)} | ... CF53: {=_xll.YCP($B53,CF$2)}
C54: {=_xll.YCI($B54,C$2)} | D54: {=_xll.YCI($B54,D$2)} | E54: {=_xll.YCI($B54,E$2)} | F54: {=_xll.YCI($B54,F$2)} | G54: {=_xll.YCI($B54,G$2)} | H54: {=_xll.YCI($B54,H$2)} | I54: {=_xll.YCI($B54,I$2)} | J54: {=_xll.YCI($B54,J$2)} | ... N54: {=_xll.YCI($B54,N$2)} | O54: {=_xll.YCP($B54,O$2)} | P54: {=_xll.YCP($B54,P$2)} | Q54: {=_xll.YCP($B54,Q$2)} | R54: {=_xll.YCP($B54,R$2)} | S54: {=_xll.YCP($B54,S$2)} | T54: {=_xll.YCP($B54,T$2)} | U54: {=_xll.YCP($B54,U$2)} | W54: {=_xll.YCP($B54,W$2)} | AA54: {=_xll.YCP($B54,AA$2)} | AB54: {=_xll.YCP($B54,AB$2)} | AC54: {=_xll.YCP($B54,AC$2)} | AE54: {=_xll.YCP($B54,AE$2)} | AH54: {=_xll.YCP($B54,AH$2)} | AI54: {=_xll.YCP($B54,AI$2)} | AJ54: {=_xll.YCP($B54,AJ$2)} | AK54: {=_xll.YCP($B54,AK$2)} | AL54: {=_xll.YCP($B54,AL$2)} | AM54: {=_xll.YCP($B54,AM$2)} | AN54: {=_xll.YCP($B54,AN$2)} | AO54: {=_xll.YCP($B54,AO$2)} | ... BR54: {=_xll.YCP($B54,BR$2)} | BT54: {=_xll.YCP($B54,BT$2)} | BU54: {=_xll.YCP($B54,BU$2)} | BV54: {=_xll.YCP($B54,BV$2)} | BW54: {=_xll.YCP($B54,BW$2)} | BX54: {=_xll.YCP($B54,BX$2)} | BY54: {=_xll.YCP($B54,BY$2)} | BZ54: {=_xll.YCP($B54,BZ$2)} | CA54: {=_xll.YCP($B54,CA$2)} | ... CF54: {=_xll.YCP($B54,CF$2)}
C55: {=_xll.YCI($B55,C$2)} | D55: {=_xll.YCI($B55,D$2)} | E55: {=_xll.YCI($B55,E$2)} | F55: {=_xll.YCI($B55,F$2)} | G55: {=_xll.YCI($B55,G$2)} | H55: {=_xll.YCI($B55,H$2)} | I55: {=_xll.YCI($B55,I$2)} | J55: {=_xll.YCI($B55,J$2)} | ... N55: {=_xll.YCI($B55,N$2)} | O55: {=_xll.YCP($B55,O$2)} | P55: {=_xll.YCP($B55,P$2)} | Q55: {=_xll.YCP($B55,Q$2)} | R55: {=_xll.YCP($B55,R$2)} | S55: {=_xll.YCP($B55,S$2)} | T55: {=_xll.YCP($B55,T$2)} | U55: {=_xll.YCP($B55,U$2)} | W55: {=_xll.YCP($B55,W$2)} | AA55: {=_xll.YCP($B55,AA$2)} | AB55: {=_xll.YCP($B55,AB$2)} | AC55: {=_xll.YCP($B55,AC$2)} | AE55: {=_xll.YCP($B55,AE$2)} | AH55: {=_xll.YCP($B55,AH$2)} | AI55: {=_xll.YCP($B55,AI$2)} | AJ55: {=_xll.YCP($B55,AJ$2)} | AK55: {=_xll.YCP($B55,AK$2)} | AL55: {=_xll.YCP($B55,AL$2)} | AM55: {=_xll.YCP($B55,AM$2)} | AN55: {=_xll.YCP($B55,AN$2)} | AO55: {=_xll.YCP($B55,AO$2)} | ... BR55: {=_xll.YCP($B55,BR$2)} | BT55: {=_xll.YCP($B55,BT$2)} | BU55: {=_xll.YCP($B55,BU$2)} | BV55: {=_xll.YCP($B55,BV$2)} | BW55: {=_xll.YCP($B55,BW$2)} | BX55: {=_xll.YCP($B55,BX$2)} | BY55: {=_xll.YCP($B55,BY$2)} | BZ55: {=_xll.YCP($B55,BZ$2)} | CA55: {=_xll.YCP($B55,CA$2)} | ... CF55: {=_xll.YCP($B55,CF$2)}
C56: {=_xll.YCI($B56,C$2)} | D56: {=_xll.YCI($B56,D$2)} | E56: {=_xll.YCI($B56,E$2)} | F56: {=_xll.YCI($B56,F$2)} | G56: {=_xll.YCI($B56,G$2)} | H56: {=_xll.YCI($B56,H$2)} | I56: {=_xll.YCI($B56,I$2)} | J56: {=_xll.YCI($B56,J$2)} | ... N56: {=_xll.YCI($B56,N$2)} | O56: {=_xll.YCP($B56,O$2)} | P56: {=_xll.YCP($B56,P$2)} | Q56: {=_xll.YCP($B56,Q$2)} | R56: {=_xll.YCP($B56,R$2)} | S56: {=_xll.YCP($B56,S$2)} | T56: {=_xll.YCP($B56,T$2)} | U56: {=_xll.YCP($B56,U$2)} | W56: {=_xll.YCP($B56,W$2)} | AA56: {=_xll.YCP($B56,AA$2)} | AB56: {=_xll.YCP($B56,AB$2)} | AC56: {=_xll.YCP($B56,AC$2)} | AE56: {=_xll.YCP($B56,AE$2)} | AH56: {=_xll.YCP($B56,AH$2)} | AI56: {=_xll.YCP($B56,AI$2)} | AJ56: {=_xll.YCP($B56,AJ$2)} | AK56: {=_xll.YCP($B56,AK$2)} | AL56: {=_xll.YCP($B56,AL$2)} | AM56: {=_xll.YCP($B56,AM$2)} | AN56: {=_xll.YCP($B56,AN$2)} | AO56: {=_xll.YCP($B56,AO$2)} | ... CF56: {=_xll.YCP($B56,CF$2)}
C57: {=_xll.YCI($B57,C$2)} | D57: {=_xll.YCI($B57,D$2)} | E57: {=_xll.YCI($B57,E$2)} | F57: {=_xll.YCI($B57,F$2)} | G57: {=_xll.YCI($B57,G$2)} | H57: {=_xll.YCI($B57,H$2)} | I57: {=_xll.YCI($B57,I$2)} | J57: {=_xll.YCI($B57,J$2)} | ... N57: {=_xll.YCI($B57,N$2)} | O57: {=_xll.YCP($B57,O$2)} | P57: {=_xll.YCP($B57,P$2)} | Q57: {=_xll.YCP($B57,Q$2)} | R57: {=_xll.YCP($B57,R$2)} | S57: {=_xll.YCP($B57,S$2)} | T57: {=_xll.YCP($B57,T$2)} | U57: {=_xll.YCP($B57,U$2)} | W57: {=_xll.YCP($B57,W$2)} | AA57: {=_xll.YCP($B57,AA$2)} | AB57: {=_xll.YCP($B57,AB$2)} | AC57: {=_xll.YCP($B57,AC$2)} | AE57: {=_xll.YCP($B57,AE$2)} | AH57: {=_xll.YCP($B57,AH$2)} | AI57: {=_xll.YCP($B57,AI$2)} | AJ57: {=_xll.YCP($B57,AJ$2)} | AK57: {=_xll.YCP($B57,AK$2)} | AL57: {=_xll.YCP($B57,AL$2)} | AM57: {=_xll.YCP($B57,AM$2)} | AN57: {=_xll.YCP($B57,AN$2)} | AO57: {=_xll.YCP($B57,AO$2)} | ... CF57: {=_xll.YCP($B57,CF$2)}
C58: {=_xll.YCI($B58,C$2)} | D58: {=_xll.YCI($B58,D$2)} | E58: {=_xll.YCI($B58,E$2)} | F58: {=_xll.YCI($B58,F$2)} | G58: {=_xll.YCI($B58,G$2)} | H58: {=_xll.YCI($B58,H$2)} | I58: {=_xll.YCI($B58,I$2)} | J58: {=_xll.YCI($B58,J$2)} | ... N58: {=_xll.YCI($B58,N$2)} | O58: {=_xll.YCP($B58,O$2)} | P58: {=_xll.YCP($B58,P$2)} | Q58: {=_xll.YCP($B58,Q$2)} | R58: {=_xll.YCP($B58,R$2)} | S58: {=_xll.YCP($B58,S$2)} | T58: {=_xll.YCP($B58,T$2)} | U58: {=_xll.YCP($B58,U$2)} | W58: {=_xll.YCP($B58,W$2)} | AA58: {=_xll.YCP($B58,AA$2)} | AB58: {=_xll.YCP($B58,AB$2)} | AC58: {=_xll.YCP($B58,AC$2)} | AE58: {=_xll.YCP($B58,AE$2)} | AH58: {=_xll.YCP($B58,AH$2)} | AI58: {=_xll.YCP($B58,AI$2)} | AJ58: {=_xll.YCP($B58,AJ$2)} | AK58: {=_xll.YCP($B58,AK$2)} | AL58: {=_xll.YCP($B58,AL$2)} | AM58: {=_xll.YCP($B58,AM$2)} | AN58: {=_xll.YCP($B58,AN$2)} | AO58: {=_xll.YCP($B58,AO$2)} | ... CF58: {=_xll.YCP($B58,CF$2)}
C59: {=_xll.YCI($B59,C$2)} | D59: {=_xll.YCI($B59,D$2)} | E59: {=_xll.YCI($B59,E$2)} | F59: {=_xll.YCI($B59,F$2)} | G59: {=_xll.YCI($B59,G$2)} | H59: {=_xll.YCI($B59,H$2)} | I59: {=_xll.YCI($B59,I$2)} | J59: {=_xll.YCI($B59,J$2)} | ... N59: {=_xll.YCI($B59,N$2)} | O59: {=_xll.YCP($B59,O$2)} | P59: {=_xll.YCP($B59,P$2)} | Q59: {=_xll.YCP($B59,Q$2)} | R59: {=_xll.YCP($B59,R$2)} | S59: {=_xll.YCP($B59,S$2)} | T59: {=_xll.YCP($B59,T$2)} | U59: {=_xll.YCP($B59,U$2)} | W59: {=_xll.YCP($B59,W$2)} | AA59: {=_xll.YCP($B59,AA$2)} | AB59: {=_xll.YCP($B59,AB$2)} | AC59: {=_xll.YCP($B59,AC$2)} | AE59: {=_xll.YCP($B59,AE$2)} | AH59: {=_xll.YCP($B59,AH$2)} | AI59: {=_xll.YCP($B59,AI$2)} | AJ59: {=_xll.YCP($B59,AJ$2)} | AK59: {=_xll.YCP($B59,AK$2)} | AL59: {=_xll.YCP($B59,AL$2)} | AM59: {=_xll.YCP($B59,AM$2)} | AN59: {=_xll.YCP($B59,AN$2)} | AO59: {=_xll.YCP($B59,AO$2)} | ... CF59: {=_xll.YCP($B59,CF$2)}
C60: {=_xll.YCI($B60,C$2)} | D60: {=_xll.YCI($B60,D$2)} | E60: {=_xll.YCI($B60,E$2)} | F60: {=_xll.YCI($B60,F$2)} | G60: {=_xll.YCI($B60,G$2)} | H60: {=_xll.YCI($B60,H$2)} | I60: {=_xll.YCI($B60,I$2)} | J60: {=_xll.YCI($B60,J$2)} | ... N60: {=_xll.YCI($B60,N$2)} | O60: {=_xll.YCP($B60,O$2)} | P60: {=_xll.YCP($B60,P$2)} | Q60: {=_xll.YCP($B60,Q$2)} | R60: {=_xll.YCP($B60,R$2)} | S60: {=_xll.YCP($B60,S$2)} | T60: {=_xll.YCP($B60,T$2)} | U60: {=_xll.YCP($B60,U$2)} | W60: {=_xll.YCP($B60,W$2)} | AA60: {=_xll.YCP($B60,AA$2)} | AB60: {=_xll.YCP($B60,AB$2)} | AC60: {=_xll.YCP($B60,AC$2)} | AE60: {=_xll.YCP($B60,AE$2)} | AH60: {=_xll.YCP($B60,AH$2)} | AI60: {=_xll.YCP($B60,AI$2)} | AJ60: {=_xll.YCP($B60,AJ$2)} | AK60: {=_xll.YCP($B60,AK$2)} | AL60: {=_xll.YCP($B60,AL$2)} | AM60: {=_xll.YCP($B60,AM$2)} | AN60: {=_xll.YCP($B60,AN$2)} | AO60: {=_xll.YCP($B60,AO$2)} | ... CF60: {=_xll.YCP($B60,CF$2)}
C61: {=_xll.YCI($B61,C$2)} | D61: {=_xll.YCI($B61,D$2)} | E61: {=_xll.YCI($B61,E$2)} | F61: {=_xll.YCI($B61,F$2)} | G61: {=_xll.YCI($B61,G$2)} | H61: {=_xll.YCI($B61,H$2)} | I61: {=_xll.YCI($B61,I$2)} | J61: {=_xll.YCI($B61,J$2)} | ... N61: {=_xll.YCI($B61,N$2)} | O61: {=_xll.YCP($B61,O$2)} | P61: {=_xll.YCP($B61,P$2)} | Q61: {=_xll.YCP($B61,Q$2)} | R61: {=_xll.YCP($B61,R$2)} | S61: {=_xll.YCP($B61,S$2)} | T61: {=_xll.YCP($B61,T$2)} | U61: {=_xll.YCP($B61,U$2)} | W61: {=_xll.YCP($B61,W$2)} | AA61: {=_xll.YCP($B61,AA$2)} | AB61: {=_xll.YCP($B61,AB$2)} | AC61: {=_xll.YCP($B61,AC$2)} | AE61: {=_xll.YCP($B61,AE$2)} | AH61: {=_xll.YCP($B61,AH$2)} | AI61: {=_xll.YCP($B61,AI$2)} | AJ61: {=_xll.YCP($B61,AJ$2)} | AK61: {=_xll.YCP($B61,AK$2)} | AL61: {=_xll.YCP($B61,AL$2)} | AM61: {=_xll.YCP($B61,AM$2)} | AN61: {=_xll.YCP($B61,AN$2)} | AO61: {=_xll.YCP($B61,AO$2)} | ... CF61: {=_xll.YCP($B61,CF$2)}
C62: {=_xll.YCI($B62,C$2)} | D62: {=_xll.YCI($B62,D$2)} | E62: {=_xll.YCI($B62,E$2)} | F62: {=_xll.YCI($B62,F$2)} | G62: {=_xll.YCI($B62,G$2)} | H62: {=_xll.YCI($B62,H$2)} | I62: {=_xll.YCI($B62,I$2)} | J62: {=_xll.YCI($B62,J$2)} | ... N62: {=_xll.YCI($B62,N$2)} | O62: {=_xll.YCP($B62,O$2)} | P62: {=_xll.YCP($B62,P$2)} | Q62: {=_xll.YCP($B62,Q$2)} | R62: {=_xll.YCP($B62,R$2)} | S62: {=_xll.YCP($B62,S$2)} | T62: {=_xll.YCP($B62,T$2)} | U62: {=_xll.YCP($B62,U$2)} | W62: {=_xll.YCP($B62,W$2)} | AA62: {=_xll.YCP($B62,AA$2)} | AB62: {=_xll.YCP($B62,AB$2)} | AC62: {=_xll.YCP($B62,AC$2)} | AE62: {=_xll.YCP($B62,AE$2)} | AH62: {=_xll.YCP($B62,AH$2)} | AI62: {=_xll.YCP($B62,AI$2)} | AJ62: {=_xll.YCP($B62,AJ$2)} | AK62: {=_xll.YCP($B62,AK$2)} | AL62: {=_xll.YCP($B62,AL$2)} | AM62: {=_xll.YCP($B62,AM$2)} | AN62: {=_xll.YCP($B62,AN$2)} | AO62: {=_xll.YCP($B62,AO$2)} | ... CF62: {=_xll.YCP($B62,CF$2)}
C63: {=_xll.YCI($B63,C$2)} | D63: {=_xll.YCI($B63,D$2)} | E63: {=_xll.YCI($B63,E$2)} | F63: {=_xll.YCI($B63,F$2)} | G63: {=_xll.YCI($B63,G$2)} | H63: {=_xll.YCI($B63,H$2)} | I63: {=_xll.YCI($B63,I$2)} | J63: {=_xll.YCI($B63,J$2)} | ... N63: {=_xll.YCI($B63,N$2)} | O63: {=_xll.YCP($B63,O$2)} | P63: {=_xll.YCP($B63,P$2)} | Q63: {=_xll.YCP($B63,Q$2)} | R63: {=_xll.YCP($B63,R$2)} | S63: {=_xll.YCP($B63,S$2)} | T63: {=_xll.YCP($B63,T$2)} | U63: {=_xll.YCP($B63,U$2)} | W63: {=_xll.YCP($B63,W$2)} | AA63: {=_xll.YCP($B63,AA$2)} | AB63: {=_xll.YCP($B63,AB$2)} | AC63: {=_xll.YCP($B63,AC$2)} | AE63: {=_xll.YCP($B63,AE$2)} | AH63: {=_xll.YCP($B63,AH$2)} | AI63: {=_xll.YCP($B63,AI$2)} | AJ63: {=_xll.YCP($B63,AJ$2)} | AK63: {=_xll.YCP($B63,AK$2)} | AL63: {=_xll.YCP($B63,AL$2)} | AM63: {=_xll.YCP($B63,AM$2)} | AN63: {=_xll.YCP($B63,AN$2)} | AO63: {=_xll.YCP($B63,AO$2)} | ... CF63: {=_xll.YCP($B63,CF$2)}
C64: {=_xll.YCI($B64,C$2)} | D64: {=_xll.YCI($B64,D$2)} | E64: {=_xll.YCI($B64,E$2)} | F64: {=_xll.YCI($B64,F$2)} | G64: {=_xll.YCI($B64,G$2)} | H64: {=_xll.YCI($B64,H$2)} | I64: {=_xll.YCI($B64,I$2)} | J64: {=_xll.YCI($B64,J$2)} | ... N64: {=_xll.YCI($B64,N$2)} | O64: {=_xll.YCP($B64,O$2)} | P64: {=_xll.YCP($B64,P$2)} | Q64: {=_xll.YCP($B64,Q$2)} | R64: {=_xll.YCP($B64,R$2)} | S64: {=_xll.YCP($B64,S$2)} | T64: {=_xll.YCP($B64,T$2)} | U64: {=_xll.YCP($B64,U$2)} | W64: {=_xll.YCP($B64,W$2)} | AA64: {=_xll.YCP($B64,AA$2)} | AB64: {=_xll.YCP($B64,AB$2)} | AC64: {=_xll.YCP($B64,AC$2)} | AE64: {=_xll.YCP($B64,AE$2)} | AH64: {=_xll.YCP($B64,AH$2)} | AI64: {=_xll.YCP($B64,AI$2)} | AJ64: {=_xll.YCP($B64,AJ$2)} | AK64: {=_xll.YCP($B64,AK$2)} | AL64: {=_xll.YCP($B64,AL$2)} | AM64: {=_xll.YCP($B64,AM$2)} | AN64: {=_xll.YCP($B64,AN$2)} | AO64: {=_xll.YCP($B64,AO$2)} | ... CF64: {=_xll.YCP($B64,CF$2)}
C65: {=_xll.YCI($B65,C$2)} | D65: {=_xll.YCI($B65,D$2)} | E65: {=_xll.YCI($B65,E$2)} | F65: {=_xll.YCI($B65,F$2)} | G65: {=_xll.YCI($B65,G$2)} | H65: {=_xll.YCI($B65,H$2)} | I65: {=_xll.YCI($B65,I$2)} | J65: {=_xll.YCI($B65,J$2)} | ... N65: {=_xll.YCI($B65,N$2)} | O65: {=_xll.YCP($B65,O$2)} | P65: {=_xll.YCP($B65,P$2)} | Q65: {=_xll.YCP($B65,Q$2)} | R65: {=_xll.YCP($B65,R$2)} | S65: {=_xll.YCP($B65,S$2)} | T65: {=_xll.YCP($B65,T$2)} | U65: {=_xll.YCP($B65,U$2)} | W65: {=_xll.YCP($B65,W$2)} | AA65: {=_xll.YCP($B65,AA$2)} | AB65: {=_xll.YCP($B65,AB$2)} | AC65: {=_xll.YCP($B65,AC$2)} | AE65: {=_xll.YCP($B65,AE$2)} | AH65: {=_xll.YCP($B65,AH$2)} | AI65: {=_xll.YCP($B65,AI$2)} | AJ65: {=_xll.YCP($B65,AJ$2)} | AK65: {=_xll.YCP($B65,AK$2)} | AL65: {=_xll.YCP($B65,AL$2)} | AM65: {=_xll.YCP($B65,AM$2)} | AN65: {=_xll.YCP($B65,AN$2)} | AO65: {=_xll.YCP($B65,AO$2)} | ... CF65: {=_xll.YCP($B65,CF$2)}
C66: {=_xll.YCI($B66,C$2)} | D66: {=_xll.YCI($B66,D$2)} | E66: {=_xll.YCI($B66,E$2)} | F66: {=_xll.YCI($B66,F$2)} | G66: {=_xll.YCI($B66,G$2)} | H66: {=_xll.YCI($B66,H$2)} | I66: {=_xll.YCI($B66,I$2)} | J66: {=_xll.YCI($B66,J$2)} | ... N66: {=_xll.YCI($B66,N$2)} | O66: {=_xll.YCP($B66,O$2)} | P66: {=_xll.YCP($B66,P$2)} | Q66: {=_xll.YCP($B66,Q$2)} | R66: {=_xll.YCP($B66,R$2)} | S66: {=_xll.YCP($B66,S$2)} | T66: {=_xll.YCP($B66,T$2)} | U66: {=_xll.YCP($B66,U$2)} | W66: {=_xll.YCP($B66,W$2)} | AA66: {=_xll.YCP($B66,AA$2)} | AB66: {=_xll.YCP($B66,AB$2)} | AC66: {=_xll.YCP($B66,AC$2)} | AE66: {=_xll.YCP($B66,AE$2)} | AH66: {=_xll.YCP($B66,AH$2)} | AI66: {=_xll.YCP($B66,AI$2)} | AJ66: {=_xll.YCP($B66,AJ$2)} | AK66: {=_xll.YCP($B66,AK$2)} | AL66: {=_xll.YCP($B66,AL$2)} | AM66: {=_xll.YCP($B66,AM$2)} | AN66: {=_xll.YCP($B66,AN$2)} | AO66: {=_xll.YCP($B66,AO$2)} | ... CF66: {=_xll.YCP($B66,CF$2)}
C67: {=_xll.YCI($B67,C$2)} | D67: {=_xll.YCI($B67,D$2)} | E67: {=_xll.YCI($B67,E$2)} | F67: {=_xll.YCI($B67,F$2)} | G67: {=_xll.YCI($B67,G$2)} | H67: {=_xll.YCI($B67,H$2)} | I67: {=_xll.YCI($B67,I$2)} | J67: {=_xll.YCI($B67,J$2)} | ... N67: {=_xll.YCI($B67,N$2)} | O67: {=_xll.YCP($B67,O$2)} | P67: {=_xll.YCP($B67,P$2)} | Q67: {=_xll.YCP($B67,Q$2)} | R67: {=_xll.YCP($B67,R$2)} | S67: {=_xll.YCP($B67,S$2)} | T67: {=_xll.YCP($B67,T$2)} | U67: {=_xll.YCP($B67,U$2)} | W67: {=_xll.YCP($B67,W$2)} | AA67: {=_xll.YCP($B67,AA$2)} | AB67: {=_xll.YCP($B67,AB$2)} | AC67: {=_xll.YCP($B67,AC$2)} | AE67: {=_xll.YCP($B67,AE$2)} | AH67: {=_xll.YCP($B67,AH$2)} | AI67: {=_xll.YCP($B67,AI$2)} | AJ67: {=_xll.YCP($B67,AJ$2)} | AK67: {=_xll.YCP($B67,AK$2)} | AL67: {=_xll.YCP($B67,AL$2)} | AM67: {=_xll.YCP($B67,AM$2)} | AN67: {=_xll.YCP($B67,AN$2)} | AO67: {=_xll.YCP($B67,AO$2)} | ... CF67: {=_xll.YCP($B67,CF$2)}
... C100: {=_xll.YCI($B100,C$2)} | D100: {=_xll.YCI($B100,D$2)} | E100: {=_xll.YCI($B100,E$2)} | F100: {=_xll.YCI($B100,F$2)} | G100: {=_xll.YCI($B100,G$2)} | H100: {=_xll.YCI($B100,H$2)} | I100: {=_xll.YCI($B100,I$2)} | J100: {=_xll.YCI($B100,J$2)} | ... N100: {=_xll.YCI($B100,N$2)} | O100: {=_xll.YCP($B100,O$2)} | P100: {=_xll.YCP($B100,P$2)} | Q100: {=_xll.YCP($B100,Q$2)} | R100: {=_xll.YCP($B100,R$2)} | S100: {=_xll.YCP($B100,S$2)} | T100: {=_xll.YCP($B100,T$2)} | U100: {=_xll.YCP($B100,U$2)} | W100: {=_xll.YCP($B100,W$2)} | AA100: {=_xll.YCP($B100,AA$2)} | AB100: {=_xll.YCP($B100,AB$2)} | AC100: {=_xll.YCP($B100,AC$2)} | AE100: {=_xll.YCP($B100,AE$2)} | AH100: {=_xll.YCP($B100,AH$2)} | AI100: {=_xll.YCP($B100,AI$2)} | AJ100: {=_xll.YCP($B100,AJ$2)} | AK100: {=_xll.YCP($B100,AK$2)} | AL100: {=_xll.YCP($B100,AL$2)} | AM100: {=_xll.YCP($B100,AM$2)} | AN100: {=_xll.YCP($B100,AN$2)} | AO100: {=_xll.YCP($B100,AO$2)} | ... CF100: {=_xll.YCP($B100,CF$2)}

Sheet Related
B2: related_securities
A3: =Securities!B3 -> M:APDFX | C3: security_name | D3: detailed_security_type | E3: investment_strategy | F3: fund_family | G3: fund_company_name | H3: broad_category_group | I3: broad_asset_class | J3: category_name | K3: category_index | L3: peer_group_name | M3: ycharts_benchmark_category | N3: inception_date_generic | O3: assets_under_management | P3: expense_ratio_generic | Q3: expense_ratio_rank | R3: expense_ratio_peer_group_rank | S3: max_manager_tenure | T3: discount_or_premium_to_nav | U3: alpha_rank | V3: information_ratio_rank | W3: sharpe_rank | X3: alpha_3y_vs_category | Y3: information_ratio_3y_vs_category | Z3: historical_sharpe_3y | AA3: rsquared_3y_vs_category | AB3: upside_downside_5y_vs_category | AC3: alpha_peer_group_rank | AD3: information_ratio_peer_group_rank | AE3: sharpe_peer_group_rank | AF3: market_alpha_3y_vs_pg | AG3: information_ratio_3y_vs_pg | AH3: rsquared_3y_vs_pg | AI3: upside_downside_5y_vs_pg | AJ3: one_month_total_return_nav | AK3: three_month_total_return_nav | AL3: ytd_total_return_nav | AM3: one_year_total_return_nav | AN3: annualized_three_year_total_return_nav | AO3: annualized_five_year_total_return_nav | AP3: annualized_ten_year_total_return_nav | AQ3: category_one_month_total_return | AR3: category_three_month_total_return | AS3: category_ytd_total_return | AT3: category_one_year_total_return | AU3: category_three_year_total_return | AV3: category_five_year_total_return | AW3: category_ten_year_total_return | AX3: one_month_total_return_rank_nav | AY3: three_month_total_return_rank_nav | AZ3: ytd_total_return_rank_nav | BA3: one_year_total_return_rank_nav | BB3: three_year_total_return_rank_nav | BC3: five_year_total_return_rank_nav | BD3: ten_year_total_return_rank_nav | BE3: one_month_total_return_rank_category_size_nav | BF3: three_month_total_return_rank_category_size_nav | BG3: ytd_total_return_rank_category_size_nav | BH3: one_year_total_return_rank_category_size_nav | BI3: three_year_total_return_rank_category_size_nav | BJ3: five_year_total_return_rank_category_size_nav | BK3: ten_year_total_return_rank_category_size_nav | BL3: peer_group_one_month_total_return | BM3: peer_group_three_month_total_return | BN3: peer_group_ytd_total_return | BO3: peer_group_one_year_total_return | BP3: peer_group_three_year_total_return | BQ3: peer_group_five_year_total_return | BR3: peer_group_ten_year_total_return | BS3: one_month_total_return_peer_group_rank_nav | BT3: three_month_total_return_peer_group_rank_nav | BU3: ytd_total_return_peer_group_rank_nav | BV3: one_year_total_return_peer_group_rank_nav | BW3: three_year_total_return_peer_group_rank_nav | BX3: five_year_total_return_peer_group_rank_nav | BY3: ten_year_total_return_peer_group_rank_nav | BZ3: one_month_total_return_peer_group_size_nav | CA3: three_month_total_return_peer_group_size_nav | CB3: ytd_total_return_peer_group_size_nav | CC3: one_year_total_return_peer_group_size_nav | CD3: three_year_total_return_peer_group_size_nav | CE3: five_year_total_return_peer_group_size_nav | CF3: ten_year_total_return_peer_group_size_nav
B4: {=_xll.YCI(A3,B2)} -> M:IPYAX | C4: {=_xll.YCI($B4,C$3)} -> Voya High Yield Portfolio Adviser | D4: {=_xll.YCI($B4,D$3)} -> insurance_fund | E4: {=_xll.YCI($B4,E$3)} -> The investment seeks to provide investors with a high level of current income and total return. Under normal circumstances, the fund invests at least 80% of its net assets (plus the amount of any borrowings for investment purposes) in a diversified portfolio of high-yield bonds. For purposes of this 80% policy, high-yield bonds include, without limitation, bonds, debt instruments, and other fixed income and income-producing debt instruments, of any kind, issued or guaranteed by governmental or private-sector entities that are rated below investment grade by one or more NRSRO or, if unrated, determined by the fund to be of comparable quality. | F4: {=_xll.YCI($B4,F$3)} -> Voya | G4: {=_xll.YCI($B4,G$3)} -> Voya Investments, LLC | H4: {=_xll.YCI($B4,H$3)} -> Fixed Income | I4: {=_xll.YCI($B4,I$3)} -> Taxable Bond | J4: {=_xll.YCI($B4,J$3)} -> High Yield Bond | ... N4: {=_xll.YCI($B4,N$3)} -> ERR: NO DATA | O4: {=_xll.YCP($B4,O$3)} -> 53323513 | P4: {=_xll.YCP($B4,P$3)} -> 0.011 | Q4: {=_xll.YCP($B4,Q$3)} -> 72 | R4: {=_xll.YCP($B4,R$3)} -> 80 | S4: {=_xll.YCP($B4,S$3)} -> 1.09 | T4: {=_xll.YCP($B4,T$3)} -> ERR: INVALID CALC | U4: {=_xll.YCP($B4,U$3)} -> 78 | V4: {=_xll.YCP($B4,V$3)} -> 68 | ... CF4: {=_xll.YCP($B4,CF$3)} -> 467
B5: M:AGDYX | C5: {=_xll.YCI($B5,C$3)} -> AB High Income Fund Advisor | D5: {=_xll.YCI($B5,D$3)} -> mutual_fund | E5: {=_xll.YCI($B5,E$3)} -> The investment seeks to maximize total returns from price appreciation and income. The fund pursues income opportunities from government, corporate, emerging market and high-yield sources. It has the flexibility to invest in a broad range of fixed-income securities in both developed and emerging market countries. The fund's investments may include U.S. and non-U.S. corporate debt securities and sovereign debt securities. It may invest, without limitation, in either U.S. Dollar-denominated or non-U.S. Dollar-denominated fixed-income securities. | F5: {=_xll.YCI($B5,F$3)} -> AllianceBernstein | G5: {=_xll.YCI($B5,G$3)} -> AllianceBernstein L.P. | H5: {=_xll.YCI($B5,H$3)} -> Fixed Income | I5: {=_xll.YCI($B5,I$3)} -> Taxable Bond | J5: {=_xll.YCI($B5,J$3)} -> High Yield Bond | ... N5: {=_xll.YCI($B5,N$3)} -> 1994-02-25 | O5: {=_xll.YCP($B5,O$3)} -> 2020716292 | P5: {=_xll.YCP($B5,P$3)} -> 0.0061 | Q5: {=_xll.YCP($B5,Q$3)} -> 32 | R5: {=_xll.YCP($B5,R$3)} -> 22 | S5: {=_xll.YCP($B5,S$3)} -> 20.76 | T5: {=_xll.YCP($B5,T$3)} -> ERR: INVALID CALC | U5: {=_xll.YCP($B5,U$3)} -> 10 | V5: {=_xll.YCP($B5,V$3)} -> 9 | ... CF5: {=_xll.YCP($B5,CF$3)} -> 63
B6: M:PAOPX | C6: {=_xll.YCI($B6,C$3)} -> T Rowe Price Credit Opportunities Fund Adv | D6: {=_xll.YCI($B6,D$3)} -> mutual_fund | E6: {=_xll.YCI($B6,E$3)} -> The investment seeks a combination of long-term capital appreciation and high income. The fund normally invests at least 80% of its net assets (plus any borrowings for investment purposes) in credit instruments and derivative instruments that are linked to,or provide investment exposure to, credit instruments. The fund may invest without limit in bonds that are rated below investment grade (below BBB or an equivalent rating) or are not rated by credit rating agencies, as well as bank loans and other instruments that are rated below investment grade or are not rated by credit rating agencies. | F6: {=_xll.YCI($B6,F$3)} -> T. Rowe Price | G6: {=_xll.YCI($B6,G$3)} -> T. Rowe Price Associates, Inc. | H6: {=_xll.YCI($B6,H$3)} -> Fixed Income | I6: {=_xll.YCI($B6,I$3)} -> Taxable Bond | J6: {=_xll.YCI($B6,J$3)} -> High Yield Bond | ... N6: {=_xll.YCI($B6,N$3)} -> 2014-04-29 | O6: {=_xll.YCP($B6,O$3)} -> 142735 | P6: {=_xll.YCP($B6,P$3)} -> 0.0091 | Q6: {=_xll.YCP($B6,Q$3)} -> 61 | R6: {=_xll.YCP($B6,R$3)} -> 66 | S6: {=_xll.YCP($B6,S$3)} -> 11.07 | T6: {=_xll.YCP($B6,T$3)} -> ERR: INVALID CALC | U6: {=_xll.YCP($B6,U$3)} -> 37 | V6: {=_xll.YCP($B6,V$3)} -> 56 | ... CF6: {=_xll.YCP($B6,CF$3)} -> 467
B7: M:PAHIX | C7: {=_xll.YCI($B7,C$3)} -> T Rowe Price High Yield Fund Advisor | D7: {=_xll.YCI($B7,D$3)} -> mutual_fund | E7: {=_xll.YCI($B7,E$3)} -> The investment seeks high current income and, secondarily, capital appreciation. The fund will normally invest at least 80% of its net assets in a widely diversified portfolio of high yield corporate bonds, often called "junk" bonds, as well as income-producing convertible securities and preferred stocks that are rated below investment grade or not rated by any major credit rating agency but deemed to be below investment grade. High yield bonds are rated below investment grade (BB and lower, or an equivalent rating), and tend to provide high income in an effort to compensate investors for their higher risk of default. | F7: {=_xll.YCI($B7,F$3)} -> T. Rowe Price | G7: {=_xll.YCI($B7,G$3)} -> T. Rowe Price Associates, Inc. | H7: {=_xll.YCI($B7,H$3)} -> Fixed Income | I7: {=_xll.YCI($B7,I$3)} -> Taxable Bond | J7: {=_xll.YCI($B7,J$3)} -> High Yield Bond | ... N7: {=_xll.YCI($B7,N$3)} -> 1984-12-31 | O7: {=_xll.YCP($B7,O$3)} -> 12285679 | P7: {=_xll.YCP($B7,P$3)} -> 0.0104 | Q7: {=_xll.YCP($B7,Q$3)} -> 71 | R7: {=_xll.YCP($B7,R$3)} -> 78 | S7: {=_xll.YCP($B7,S$3)} -> 7.55 | T7: {=_xll.YCP($B7,T$3)} -> ERR: INVALID CALC | U7: {=_xll.YCP($B7,U$3)} -> 58 | V7: {=_xll.YCP($B7,V$3)} -> 62 | ... CF7: {=_xll.YCP($B7,CF$3)} -> 467
B8: M:TUHAX | C8: {=_xll.YCI($B8,C$3)} -> T Rowe Price US High Yield Fund Advisor | D8: {=_xll.YCI($B8,D$3)} -> mutual_fund | E8: {=_xll.YCI($B8,E$3)} -> The investment seeks total return, and secondarily, current income. The fund normally invests at least 80% of its net assets (plus any borrowings for investment purposes) in U.S. high yield instruments. U.S. high yield instruments, commonly referred to as “junk” bonds, are debt instruments that are, at the time of purchase, rated below investment grade by a credit rating agency, or, if not rated by any credit rating agency, deemed by T. Rowe Price to be below investment grade. | F8: {=_xll.YCI($B8,F$3)} -> T. Rowe Price | G8: {=_xll.YCI($B8,G$3)} -> T. Rowe Price Associates, Inc. | H8: {=_xll.YCI($B8,H$3)} -> Fixed Income | I8: {=_xll.YCI($B8,I$3)} -> Taxable Bond | J8: {=_xll.YCI($B8,J$3)} -> High Yield Bond | ... N8: {=_xll.YCI($B8,N$3)} -> 2013-04-30 | O8: {=_xll.YCP($B8,O$3)} -> 2276524 | P8: {=_xll.YCP($B8,P$3)} -> 0.009 | Q8: {=_xll.YCP($B8,Q$3)} -> 60 | R8: {=_xll.YCP($B8,R$3)} -> 65 | S8: {=_xll.YCP($B8,S$3)} -> 13.26 | T8: {=_xll.YCP($B8,T$3)} -> ERR: INVALID CALC | U8: {=_xll.YCP($B8,U$3)} -> 64 | V8: {=_xll.YCP($B8,V$3)} -> 77 | ... CF8: {=_xll.YCP($B8,CF$3)} -> 467
C9: {=_xll.YCI($B9,C$3)} | D9: {=_xll.YCI($B9,D$3)} | E9: {=_xll.YCI($B9,E$3)} | F9: {=_xll.YCI($B9,F$3)} | G9: {=_xll.YCI($B9,G$3)} | H9: {=_xll.YCI($B9,H$3)} | I9: {=_xll.YCI($B9,I$3)} | J9: {=_xll.YCI($B9,J$3)} | ... N9: {=_xll.YCI($B9,N$3)} | O9: {=_xll.YCP($B9,O$3)} | P9: {=_xll.YCP($B9,P$3)} | Q9: {=_xll.YCP($B9,Q$3)} | R9: {=_xll.YCP($B9,R$3)} | S9: {=_xll.YCP($B9,S$3)} | T9: {=_xll.YCP($B9,T$3)} | U9: {=_xll.YCP($B9,U$3)} | V9: {=_xll.YCP($B9,V$3)} | ... CF9: {=_xll.YCP($B9,CF$3)}
A10: =Securities!B4 -> AVDE | C10: {=_xll.YCI($B10,C$3)} | D10: {=_xll.YCI($B10,D$3)} | E10: {=_xll.YCI($B10,E$3)} | F10: {=_xll.YCI($B10,F$3)} | G10: {=_xll.YCI($B10,G$3)} | H10: {=_xll.YCI($B10,H$3)} | I10: {=_xll.YCI($B10,I$3)} | J10: {=_xll.YCI($B10,J$3)} | ... N10: {=_xll.YCI($B10,N$3)} | O10: {=_xll.YCP($B10,O$3)} | P10: {=_xll.YCP($B10,P$3)} | Q10: {=_xll.YCP($B10,Q$3)} | R10: {=_xll.YCP($B10,R$3)} | S10: {=_xll.YCP($B10,S$3)} | T10: {=_xll.YCP($B10,T$3)} | U10: {=_xll.YCP($B10,U$3)} | V10: {=_xll.YCP($B10,V$3)} | ... CF10: {=_xll.YCP($B10,CF$3)}
B11: {=_xll.YCI(A10,B2)} -> DFAI | C11: {=_xll.YCI($B11,C$3)} -> DFA Dimensional International Core Equity Market | D11: {=_xll.YCI($B11,D$3)} -> etf | E11: {=_xll.YCI($B11,E$3)} -> The investment seeks to achieve long-term capital appreciation. The fund will invest in companies of all sizes, with increased exposure to smaller capitalization, lower relative price, and higher profitability companies as compared to their representation in the International Universe. As a non-fundamental policy, under normal circumstances, it will invest at least 80% of its net assets in equity securities. The Advisor may also increase or reduce the fund's exposure to an eligible company, or exclude a company, based on shorter-term considerations, such as a company's price momentum, short-run reversals, and investment characteristics. | F11: {=_xll.YCI($B11,F$3)} -> Dimensional Fund Advisors | G11: {=_xll.YCI($B11,G$3)} -> Dimensional Fund Advisors LP | H11: {=_xll.YCI($B11,H$3)} -> Equity | I11: {=_xll.YCI($B11,I$3)} -> International Equity | J11: {=_xll.YCI($B11,J$3)} -> Foreign Large Blend | ... N11: {=_xll.YCI($B11,N$3)} -> 2020-11-17 | O11: {=_xll.YCP($B11,O$3)} -> 18086159708 | P11: {=_xll.YCP($B11,P$3)} -> 0.0018 | Q11: {=_xll.YCP($B11,Q$3)} -> 9 | R11: {=_xll.YCP($B11,R$3)} -> 11 | S11: {=_xll.YCP($B11,S$3)} -> 5.71 | T11: {=_xll.YCP($B11,T$3)} -> -0.00232666 | U11: {=_xll.YCP($B11,U$3)} -> 21 | V11: {=_xll.YCP($B11,V$3)} -> 29 | ... CF11: {=_xll.YCP($B11,CF$3)} -> 164
B12: DFAX | C12: {=_xll.YCI($B12,C$3)} -> DFA Dimensional World ex US Core Equity 2 ETF | D12: {=_xll.YCI($B12,D$3)} -> etf | E12: {=_xll.YCI($B12,E$3)} -> The investment seeks to achieve long-term capital appreciation while considering federal tax implications of investment decisions. Generally, the Advisor buys and sells securities for the Portfolio with the goals of: (i) delaying and minimizing the realization of net capital gains (e.g., selling stocks with capital losses to offset gains, realized or anticipated); and (ii) maximizing the extent to which any realized net capital gains are long-term in nature (i.e., taxable at lower capital gains tax rates). The Portfolio is designed to purchase a broad and diverse group of equity securities of non‑U.S. companies in countries with developed and emerging markets. | F12: {=_xll.YCI($B12,F$3)} -> Dimensional Fund Advisors | G12: {=_xll.YCI($B12,G$3)} -> Dimensional Fund Advisors LP | H12: {=_xll.YCI($B12,H$3)} -> Equity | I12: {=_xll.YCI($B12,I$3)} -> International Equity | J12: {=_xll.YCI($B12,J$3)} -> Foreign Large Blend | ... N12: {=_xll.YCI($B12,N$3)} -> 2008-03-06 | O12: {=_xll.YCP($B12,O$3)} -> 12446043005 | P12: {=_xll.YCP($B12,P$3)} -> 0.0028 | Q12: {=_xll.YCP($B12,Q$3)} -> 20 | R12: {=_xll.YCP($B12,R$3)} -> 18 | S12: {=_xll.YCP($B12,S$3)} -> 16.43 | T12: {=_xll.YCP($B12,T$3)} -> -0.0042328 | U12: {=_xll.YCP($B12,U$3)} -> 25 | V12: {=_xll.YCP($B12,V$3)} -> 16 | ... CF12: {=_xll.YCP($B12,CF$3)} -> 164
B13: DFIC | C13: {=_xll.YCI($B13,C$3)} -> DFA Dimensional International Core Equity 2 ETF | D13: {=_xll.YCI($B13,D$3)} -> etf | E13: {=_xll.YCI($B13,E$3)} -> The investment seeks to achieve long-term capital appreciation. The Portfolio is designed to purchase a broad and diverse group of equity securities of non‑U.S. companies in developed markets. The Portfolio invests in companies of all sizes, with increased exposure to smaller capitalization, lower relative price, and higher profitability companies as compared to their representation in the International Universe. | F13: {=_xll.YCI($B13,F$3)} -> Dimensional Fund Advisors | G13: {=_xll.YCI($B13,G$3)} -> Dimensional Fund Advisors LP | H13: {=_xll.YCI($B13,H$3)} -> Equity | I13: {=_xll.YCI($B13,I$3)} -> International Equity | J13: {=_xll.YCI($B13,J$3)} -> Foreign Large Blend | ... N13: {=_xll.YCI($B13,N$3)} -> 2022-03-23 | O13: {=_xll.YCP($B13,O$3)} -> 15264376556 | P13: {=_xll.YCP($B13,P$3)} -> 0.0022 | Q13: {=_xll.YCP($B13,Q$3)} -> 13 | R13: {=_xll.YCP($B13,R$3)} -> 12 | S13: {=_xll.YCP($B13,S$3)} -> 4.36 | T13: {=_xll.YCP($B13,T$3)} -> -0.00153925 | U13: {=_xll.YCP($B13,U$3)} -> 16 | V13: {=_xll.YCP($B13,V$3)} -> 21 | ... CF13: {=_xll.YCP($B13,CF$3)} -> 164
B14: DIHP | C14: {=_xll.YCI($B14,C$3)} -> DFA Dimensional Internatl High Profitability ETF | D14: {=_xll.YCI($B14,D$3)} -> etf | E14: {=_xll.YCI($B14,E$3)} -> The investment seeks to achieve long-term capital appreciation. The Portfolio is designed to purchase securities of large non‑U.S. companies that the Advisor determines to have high profitability relative to other large capitalization companies in the same country or region, at the time of purchase. The Portfolio may emphasize certain stocks, including smaller capitalization companies, lower relative price stocks, and/or higher profitability stocks as compared to their representation in the large‑cap high profitability segments of developed non‑U.S. markets. | F14: {=_xll.YCI($B14,F$3)} -> Dimensional Fund Advisors | G14: {=_xll.YCI($B14,G$3)} -> Dimensional Fund Advisors LP | H14: {=_xll.YCI($B14,H$3)} -> Equity | I14: {=_xll.YCI($B14,I$3)} -> International Equity | J14: {=_xll.YCI($B14,J$3)} -> Foreign Large Blend | ... N14: {=_xll.YCI($B14,N$3)} -> 2022-03-23 | O14: {=_xll.YCP($B14,O$3)} -> 6556735569 | P14: {=_xll.YCP($B14,P$3)} -> 0.0027 | Q14: {=_xll.YCP($B14,Q$3)} -> 19 | R14: {=_xll.YCP($B14,R$3)} -> 4 | S14: {=_xll.YCP($B14,S$3)} -> 4.36 | T14: {=_xll.YCP($B14,T$3)} -> -0.00255319 | U14: {=_xll.YCP($B14,U$3)} -> 77 | V14: {=_xll.YCP($B14,V$3)} -> 84 | ... CF14: {=_xll.YCP($B14,CF$3)} -> 325
B15: IDEV | C15: {=_xll.YCI($B15,C$3)} -> iShares Core MSCI International Developed Mkt ETF | D15: {=_xll.YCI($B15,D$3)} -> etf | E15: {=_xll.YCI($B15,E$3)} -> The investment seeks to track the investment results of the MSCI World ex USA Investable Market Index. The fund generally will invest at least 80% of its assets in the component securities of its underlying index and in investments that have economic characteristics that are substantially identical to the component securities of its underlying index. The underlying index is free float adjusted, market cap weighted, and is designed to measure large-, mid- and small-capitalization equity market performance and includes stocks from North America, Europe, Australasia and the Far East. | F15: {=_xll.YCI($B15,F$3)} -> iShares | G15: {=_xll.YCI($B15,G$3)} -> BlackRock Fund Advisors | H15: {=_xll.YCI($B15,H$3)} -> Equity | I15: {=_xll.YCI($B15,I$3)} -> International Equity | J15: {=_xll.YCI($B15,J$3)} -> Foreign Large Blend | ... N15: {=_xll.YCI($B15,N$3)} -> 2017-03-22 | O15: {=_xll.YCP($B15,O$3)} -> 32246741366 | P15: {=_xll.YCP($B15,P$3)} -> 0.0004 | Q15: {=_xll.YCP($B15,Q$3)} -> 4 | R15: {=_xll.YCP($B15,R$3)} -> 3 | S15: {=_xll.YCP($B15,S$3)} -> 9.37 | T15: {=_xll.YCP($B15,T$3)} -> 0.00188504 | U15: {=_xll.YCP($B15,U$3)} -> 35 | V15: {=_xll.YCP($B15,V$3)} -> 40 | ... CF15: {=_xll.YCP($B15,CF$3)} -> 164
C16: {=_xll.YCI($B16,C$3)} | D16: {=_xll.YCI($B16,D$3)} | E16: {=_xll.YCI($B16,E$3)} | F16: {=_xll.YCI($B16,F$3)} | G16: {=_xll.YCI($B16,G$3)} | H16: {=_xll.YCI($B16,H$3)} | I16: {=_xll.YCI($B16,I$3)} | J16: {=_xll.YCI($B16,J$3)} | ... N16: {=_xll.YCI($B16,N$3)} | O16: {=_xll.YCP($B16,O$3)} | P16: {=_xll.YCP($B16,P$3)} | Q16: {=_xll.YCP($B16,Q$3)} | R16: {=_xll.YCP($B16,R$3)} | S16: {=_xll.YCP($B16,S$3)} | T16: {=_xll.YCP($B16,T$3)} | U16: {=_xll.YCP($B16,U$3)} | V16: {=_xll.YCP($B16,V$3)} | ... CF16: {=_xll.YCP($B16,CF$3)}
A17: =Securities!B5 -> M:AVERX | C17: {=_xll.YCI($B17,C$3)} | D17: {=_xll.YCI($B17,D$3)} | E17: {=_xll.YCI($B17,E$3)} | F17: {=_xll.YCI($B17,F$3)} | G17: {=_xll.YCI($B17,G$3)} | H17: {=_xll.YCI($B17,H$3)} | I17: {=_xll.YCI($B17,I$3)} | J17: {=_xll.YCI($B17,J$3)} | ... N17: {=_xll.YCI($B17,N$3)} | O17: {=_xll.YCP($B17,O$3)} | P17: {=_xll.YCP($B17,P$3)} | Q17: {=_xll.YCP($B17,Q$3)} | R17: {=_xll.YCP($B17,R$3)} | S17: {=_xll.YCP($B17,S$3)} | T17: {=_xll.YCP($B17,T$3)} | U17: {=_xll.YCP($B17,U$3)} | V17: {=_xll.YCP($B17,V$3)} | ... CF17: {=_xll.YCP($B17,CF$3)}
B18: {=_xll.YCI(A17,B2)} -> M:BTMFX | C18: {=_xll.YCI($B18,C$3)} -> Boston Trust Midcap Fund | D18: {=_xll.YCI($B18,D$3)} -> mutual_fund | E18: {=_xll.YCI($B18,E$3)} -> The investment seeks long-term capital growth through an actively managed portfolio of stocks of middle capitalization ("midcap") companies. The fund invests, under normal circumstances, at least 80% of its assets in a diversified portfolio of domestic equity securities of mid cap companies. Equity securities include common stock and any rights to purchase common stock. For these purposes, the Adviser defines mid cap companies as those with market capitalizations within the range encompassed by the Russell Midcap® Index at the time of purchase. | F18: {=_xll.YCI($B18,F$3)} -> Boston Trust Walden Funds | G18: {=_xll.YCI($B18,G$3)} -> Boston Trust Walden Inc. | H18: {=_xll.YCI($B18,H$3)} -> Equity | I18: {=_xll.YCI($B18,I$3)} -> US Equity | J18: {=_xll.YCI($B18,J$3)} -> Mid-Cap Blend | ... N18: {=_xll.YCI($B18,N$3)} -> 2007-09-24 | O18: {=_xll.YCP($B18,O$3)} -> 167056103 | P18: {=_xll.YCP($B18,P$3)} -> 0.0098 | Q18: {=_xll.YCP($B18,Q$3)} -> 74 | R18: {=_xll.YCP($B18,R$3)} -> 61 | S18: {=_xll.YCP($B18,S$3)} -> 18.87 | T18: {=_xll.YCP($B18,T$3)} -> ERR: INVALID CALC | U18: {=_xll.YCP($B18,U$3)} -> 61 | V18: {=_xll.YCP($B18,V$3)} -> 90 | ... CF18: {=_xll.YCP($B18,CF$3)} -> 353
B19: M:WAMFX | C19: {=_xll.YCI($B19,C$3)} -> Boston Trust Walden Midcap Fund | D19: {=_xll.YCI($B19,D$3)} -> mutual_fund | E19: {=_xll.YCI($B19,E$3)} -> The investment seeks long-term capital growth through an actively managed portfolio of stocks of middle capitalization ("midcap") companies. The fund invests, under normal circumstances, at least 80% of its assets in a diversified portfolio of domestic equity securities of mid cap companies. For these purposes, the Adviser defines mid cap companies as those with market capitalizations within the range encompassed by the Russell Midcap® Index at the time of purchase. The Adviser evaluates how financially material environmental, social, and governance (ESG) factors may affect a company's revenues, expenses, assets, liabilities, and overall risk. | F19: {=_xll.YCI($B19,F$3)} -> Boston Trust Walden Funds | G19: {=_xll.YCI($B19,G$3)} -> Boston Trust Walden Inc. | H19: {=_xll.YCI($B19,H$3)} -> Equity | I19: {=_xll.YCI($B19,I$3)} -> US Equity | J19: {=_xll.YCI($B19,J$3)} -> Mid-Cap Blend | ... N19: {=_xll.YCI($B19,N$3)} -> 2011-08-01 | O19: {=_xll.YCP($B19,O$3)} -> 162735718 | P19: {=_xll.YCP($B19,P$3)} -> 0.01 | Q19: {=_xll.YCP($B19,Q$3)} -> 75 | R19: {=_xll.YCP($B19,R$3)} -> 63 | S19: {=_xll.YCP($B19,S$3)} -> 15.01 | T19: {=_xll.YCP($B19,T$3)} -> ERR: INVALID CALC | U19: {=_xll.YCP($B19,U$3)} -> 58 | V19: {=_xll.YCP($B19,V$3)} -> 88 | ... CF19: {=_xll.YCP($B19,CF$3)} -> 353
B20: M:AVEMX | C20: {=_xll.YCI($B20,C$3)} -> Ave Maria Value Fund | D20: {=_xll.YCI($B20,D$3)} -> mutual_fund | E20: {=_xll.YCI($B20,E$3)} -> The investment seeks long-term capital appreciation. The fund invests primarily in common stocks believed by the adviser to be priced at a discount to their true value according to the Adviser's criteria for value. Under normal circumstances, all of its equity investments (which include common stocks, preferred stocks and securities convertible into common stock) and at least 80% of its net assets will be invested in companies meeting its religious criteria. The fund invests in securities of established companies of various market capitalizations. | F20: {=_xll.YCI($B20,F$3)} -> Ave Maria Mutual Funds | G20: {=_xll.YCI($B20,G$3)} -> Schwartz Investment Counsel Inc | H20: {=_xll.YCI($B20,H$3)} -> Equity | I20: {=_xll.YCI($B20,I$3)} -> US Equity | J20: {=_xll.YCI($B20,J$3)} -> Mid-Cap Blend | ... N20: {=_xll.YCI($B20,N$3)} -> 2001-05-01 | O20: {=_xll.YCP($B20,O$3)} -> 538751192 | P20: {=_xll.YCP($B20,P$3)} -> 0.0092 | Q20: {=_xll.YCP($B20,Q$3)} -> 71 | R20: {=_xll.YCP($B20,R$3)} -> 50 | S20: {=_xll.YCP($B20,S$3)} -> 10.59 | T20: {=_xll.YCP($B20,T$3)} -> ERR: INVALID CALC | U20: {=_xll.YCP($B20,U$3)} -> 5 | V20: {=_xll.YCP($B20,V$3)} -> 24 | ... CF20: {=_xll.YCP($B20,CF$3)} -> 371
B21: M:BRMAX | C21: {=_xll.YCI($B21,C$3)} -> iShares Russell Mid-Cap Idx Fund Class A Shares | D21: {=_xll.YCI($B21,D$3)} -> mutual_fund | E21: {=_xll.YCI($B21,E$3)} -> The investment seeks to track the investment results of the Russell Midcap® Index (the "underlying index"), which measures the performance of the mid-capitalization sector of the U.S. equity market. The fund generally invests at least 90% of its assets, plus the amount of any borrowing for investment purposes, in securities of the underlying index. The underlying index is a float-adjusted, capitalization-weighted index of equity securities issued by approximately 800 of the smallest issuers in the Russell 1000® Index. | F21: {=_xll.YCI($B21,F$3)} -> BlackRock | G21: {=_xll.YCI($B21,G$3)} -> BlackRock Advisors, LLC | H21: {=_xll.YCI($B21,H$3)} -> Equity | I21: {=_xll.YCI($B21,I$3)} -> US Equity | J21: {=_xll.YCI($B21,J$3)} -> Mid-Cap Blend | ... N21: {=_xll.YCI($B21,N$3)} -> 2015-11-30 | O21: {=_xll.YCP($B21,O$3)} -> 202289375 | P21: {=_xll.YCP($B21,P$3)} -> 0.0036 | Q21: {=_xll.YCP($B21,Q$3)} -> 35 | R21: {=_xll.YCP($B21,R$3)} -> 8 | S21: {=_xll.YCP($B21,S$3)} -> 10.32 | T21: {=_xll.YCP($B21,T$3)} -> ERR: INVALID CALC | U21: {=_xll.YCP($B21,U$3)} -> 36 | V21: {=_xll.YCP($B21,V$3)} -> 45 | ... CF21: {=_xll.YCP($B21,CF$3)} -> 353
B22: M:GVMCX | C22: {=_xll.YCI($B22,C$3)} -> Government Street Opportunities Fund | D22: {=_xll.YCI($B22,D$3)} -> mutual_fund | E22: {=_xll.YCI($B22,E$3)} -> The investment seeks capital appreciation. The fund’s portfolio manager emphasizes investment in the common stocks of mid-cap companies and is typically broadly diversified among companies in a variety of industries and economic sectors. It is governed by an investment philosophy that seeks to reduce the variability of its returns (risk) and to increase its longer-term compounded returns through a diversified investment strategy. The manager will emphasize investments in common stocks of mid-cap companies and shares of ETFs that invest primarily in common stocks of mid-cap companies, but is not limited to any particular market capitalization. | F22: {=_xll.YCI($B22,F$3)} -> Leavell | G22: {=_xll.YCI($B22,G$3)} -> Leavell Investment Management Inc | H22: {=_xll.YCI($B22,H$3)} -> Equity | I22: {=_xll.YCI($B22,I$3)} -> US Equity | J22: {=_xll.YCI($B22,J$3)} -> Mid-Cap Blend | ... N22: {=_xll.YCI($B22,N$3)} -> 2003-11-17 | O22: {=_xll.YCP($B22,O$3)} -> 94299289 | P22: {=_xll.YCP($B22,P$3)} -> 0.0107 | Q22: {=_xll.YCP($B22,Q$3)} -> 78 | R22: {=_xll.YCP($B22,R$3)} -> 67 | S22: {=_xll.YCP($B22,S$3)} -> 22.72 | T22: {=_xll.YCP($B22,T$3)} -> ERR: INVALID CALC | U22: {=_xll.YCP($B22,U$3)} -> 24 | V22: {=_xll.YCP($B22,V$3)} -> 46 | ... CF22: {=_xll.YCP($B22,CF$3)} -> 277
C23: {=_xll.YCI($B23,C$3)} | D23: {=_xll.YCI($B23,D$3)} | E23: {=_xll.YCI($B23,E$3)} | F23: {=_xll.YCI($B23,F$3)} | G23: {=_xll.YCI($B23,G$3)} | H23: {=_xll.YCI($B23,H$3)} | I23: {=_xll.YCI($B23,I$3)} | J23: {=_xll.YCI($B23,J$3)} | ... N23: {=_xll.YCI($B23,N$3)} | O23: {=_xll.YCP($B23,O$3)} | P23: {=_xll.YCP($B23,P$3)} | Q23: {=_xll.YCP($B23,Q$3)} | R23: {=_xll.YCP($B23,R$3)} | S23: {=_xll.YCP($B23,S$3)} | T23: {=_xll.YCP($B23,T$3)} | U23: {=_xll.YCP($B23,U$3)} | V23: {=_xll.YCP($B23,V$3)} | ... CF23: {=_xll.YCP($B23,CF$3)}
A24: =Securities!B5 -> M:AVERX | C24: {=_xll.YCI($B24,C$3)} | D24: {=_xll.YCI($B24,D$3)} | E24: {=_xll.YCI($B24,E$3)} | F24: {=_xll.YCI($B24,F$3)} | G24: {=_xll.YCI($B24,G$3)} | H24: {=_xll.YCI($B24,H$3)} | I24: {=_xll.YCI($B24,I$3)} | J24: {=_xll.YCI($B24,J$3)} | ... N24: {=_xll.YCI($B24,N$3)} | O24: {=_xll.YCP($B24,O$3)} | P24: {=_xll.YCP($B24,P$3)} | Q24: {=_xll.YCP($B24,Q$3)} | R24: {=_xll.YCP($B24,R$3)} | S24: {=_xll.YCP($B24,S$3)} | T24: {=_xll.YCP($B24,T$3)} | U24: {=_xll.YCP($B24,U$3)} | V24: {=_xll.YCP($B24,V$3)} | ... CF24: {=_xll.YCP($B24,CF$3)}
B25: {=_xll.YCI(A24,B2)} -> M:BTMFX | C25: {=_xll.YCI($B25,C$3)} -> Boston Trust Midcap Fund | D25: {=_xll.YCI($B25,D$3)} -> mutual_fund | E25: {=_xll.YCI($B25,E$3)} -> The investment seeks long-term capital growth through an actively managed portfolio of stocks of middle capitalization ("midcap") companies. The fund invests, under normal circumstances, at least 80% of its assets in a diversified portfolio of domestic equity securities of mid cap companies. Equity securities include common stock and any rights to purchase common stock. For these purposes, the Adviser defines mid cap companies as those with market capitalizations within the range encompassed by the Russell Midcap® Index at the time of purchase. | F25: {=_xll.YCI($B25,F$3)} -> Boston Trust Walden Funds | G25: {=_xll.YCI($B25,G$3)} -> Boston Trust Walden Inc. | H25: {=_xll.YCI($B25,H$3)} -> Equity | I25: {=_xll.YCI($B25,I$3)} -> US Equity | J25: {=_xll.YCI($B25,J$3)} -> Mid-Cap Blend | ... N25: {=_xll.YCI($B25,N$3)} -> 2007-09-24 | O25: {=_xll.YCP($B25,O$3)} -> 167056103 | P25: {=_xll.YCP($B25,P$3)} -> 0.0098 | Q25: {=_xll.YCP($B25,Q$3)} -> 74 | R25: {=_xll.YCP($B25,R$3)} -> 61 | S25: {=_xll.YCP($B25,S$3)} -> 18.87 | T25: {=_xll.YCP($B25,T$3)} -> ERR: INVALID CALC | U25: {=_xll.YCP($B25,U$3)} -> 61 | V25: {=_xll.YCP($B25,V$3)} -> 90 | ... CF25: {=_xll.YCP($B25,CF$3)} -> 353
B26: M:WAMFX | C26: {=_xll.YCI($B26,C$3)} -> Boston Trust Walden Midcap Fund | D26: {=_xll.YCI($B26,D$3)} -> mutual_fund | E26: {=_xll.YCI($B26,E$3)} -> The investment seeks long-term capital growth through an actively managed portfolio of stocks of middle capitalization ("midcap") companies. The fund invests, under normal circumstances, at least 80% of its assets in a diversified portfolio of domestic equity securities of mid cap companies. For these purposes, the Adviser defines mid cap companies as those with market capitalizations within the range encompassed by the Russell Midcap® Index at the time of purchase. The Adviser evaluates how financially material environmental, social, and governance (ESG) factors may affect a company's revenues, expenses, assets, liabilities, and overall risk. | F26: {=_xll.YCI($B26,F$3)} -> Boston Trust Walden Funds | G26: {=_xll.YCI($B26,G$3)} -> Boston Trust Walden Inc. | H26: {=_xll.YCI($B26,H$3)} -> Equity | I26: {=_xll.YCI($B26,I$3)} -> US Equity | J26: {=_xll.YCI($B26,J$3)} -> Mid-Cap Blend | ... N26: {=_xll.YCI($B26,N$3)} -> 2011-08-01 | O26: {=_xll.YCP($B26,O$3)} -> 162735718 | P26: {=_xll.YCP($B26,P$3)} -> 0.01 | Q26: {=_xll.YCP($B26,Q$3)} -> 75 | R26: {=_xll.YCP($B26,R$3)} -> 63 | S26: {=_xll.YCP($B26,S$3)} -> 15.01 | T26: {=_xll.YCP($B26,T$3)} -> ERR: INVALID CALC | U26: {=_xll.YCP($B26,U$3)} -> 58 | V26: {=_xll.YCP($B26,V$3)} -> 88 | ... CF26: {=_xll.YCP($B26,CF$3)} -> 353
B27: M:AVEMX | C27: {=_xll.YCI($B27,C$3)} -> Ave Maria Value Fund | D27: {=_xll.YCI($B27,D$3)} -> mutual_fund | E27: {=_xll.YCI($B27,E$3)} -> The investment seeks long-term capital appreciation. The fund invests primarily in common stocks believed by the adviser to be priced at a discount to their true value according to the Adviser's criteria for value. Under normal circumstances, all of its equity investments (which include common stocks, preferred stocks and securities convertible into common stock) and at least 80% of its net assets will be invested in companies meeting its religious criteria. The fund invests in securities of established companies of various market capitalizations. | F27: {=_xll.YCI($B27,F$3)} -> Ave Maria Mutual Funds | G27: {=_xll.YCI($B27,G$3)} -> Schwartz Investment Counsel Inc | H27: {=_xll.YCI($B27,H$3)} -> Equity | I27: {=_xll.YCI($B27,I$3)} -> US Equity | J27: {=_xll.YCI($B27,J$3)} -> Mid-Cap Blend | ... N27: {=_xll.YCI($B27,N$3)} -> 2001-05-01 | O27: {=_xll.YCP($B27,O$3)} -> 538751192 | P27: {=_xll.YCP($B27,P$3)} -> 0.0092 | Q27: {=_xll.YCP($B27,Q$3)} -> 71 | R27: {=_xll.YCP($B27,R$3)} -> 50 | S27: {=_xll.YCP($B27,S$3)} -> 10.59 | T27: {=_xll.YCP($B27,T$3)} -> ERR: INVALID CALC | U27: {=_xll.YCP($B27,U$3)} -> 5 | V27: {=_xll.YCP($B27,V$3)} -> 24 | ... CF27: {=_xll.YCP($B27,CF$3)} -> 371
B28: M:BRMAX | C28: {=_xll.YCI($B28,C$3)} -> iShares Russell Mid-Cap Idx Fund Class A Shares | D28: {=_xll.YCI($B28,D$3)} -> mutual_fund | E28: {=_xll.YCI($B28,E$3)} -> The investment seeks to track the investment results of the Russell Midcap® Index (the "underlying index"), which measures the performance of the mid-capitalization sector of the U.S. equity market. The fund generally invests at least 90% of its assets, plus the amount of any borrowing for investment purposes, in securities of the underlying index. The underlying index is a float-adjusted, capitalization-weighted index of equity securities issued by approximately 800 of the smallest issuers in the Russell 1000® Index. | F28: {=_xll.YCI($B28,F$3)} -> BlackRock | G28: {=_xll.YCI($B28,G$3)} -> BlackRock Advisors, LLC | H28: {=_xll.YCI($B28,H$3)} -> Equity | I28: {=_xll.YCI($B28,I$3)} -> US Equity | J28: {=_xll.YCI($B28,J$3)} -> Mid-Cap Blend | ... N28: {=_xll.YCI($B28,N$3)} -> 2015-11-30 | O28: {=_xll.YCP($B28,O$3)} -> 202289375 | P28: {=_xll.YCP($B28,P$3)} -> 0.0036 | Q28: {=_xll.YCP($B28,Q$3)} -> 35 | R28: {=_xll.YCP($B28,R$3)} -> 8 | S28: {=_xll.YCP($B28,S$3)} -> 10.32 | T28: {=_xll.YCP($B28,T$3)} -> ERR: INVALID CALC | U28: {=_xll.YCP($B28,U$3)} -> 36 | V28: {=_xll.YCP($B28,V$3)} -> 45 | ... CF28: {=_xll.YCP($B28,CF$3)} -> 353
B29: M:GVMCX | C29: {=_xll.YCI($B29,C$3)} -> Government Street Opportunities Fund | D29: {=_xll.YCI($B29,D$3)} -> mutual_fund | E29: {=_xll.YCI($B29,E$3)} -> The investment seeks capital appreciation. The fund’s portfolio manager emphasizes investment in the common stocks of mid-cap companies and is typically broadly diversified among companies in a variety of industries and economic sectors. It is governed by an investment philosophy that seeks to reduce the variability of its returns (risk) and to increase its longer-term compounded returns through a diversified investment strategy. The manager will emphasize investments in common stocks of mid-cap companies and shares of ETFs that invest primarily in common stocks of mid-cap companies, but is not limited to any particular market capitalization. | F29: {=_xll.YCI($B29,F$3)} -> Leavell | G29: {=_xll.YCI($B29,G$3)} -> Leavell Investment Management Inc | H29: {=_xll.YCI($B29,H$3)} -> Equity | I29: {=_xll.YCI($B29,I$3)} -> US Equity | J29: {=_xll.YCI($B29,J$3)} -> Mid-Cap Blend | ... N29: {=_xll.YCI($B29,N$3)} -> 2003-11-17 | O29: {=_xll.YCP($B29,O$3)} -> 94299289 | P29: {=_xll.YCP($B29,P$3)} -> 0.0107 | Q29: {=_xll.YCP($B29,Q$3)} -> 78 | R29: {=_xll.YCP($B29,R$3)} -> 67 | S29: {=_xll.YCP($B29,S$3)} -> 22.72 | T29: {=_xll.YCP($B29,T$3)} -> ERR: INVALID CALC | U29: {=_xll.YCP($B29,U$3)} -> 24 | V29: {=_xll.YCP($B29,V$3)} -> 46 | ... CF29: {=_xll.YCP($B29,CF$3)} -> 277
C30: {=_xll.YCI($B30,C$3)} | D30: {=_xll.YCI($B30,D$3)} | E30: {=_xll.YCI($B30,E$3)} | F30: {=_xll.YCI($B30,F$3)} | G30: {=_xll.YCI($B30,G$3)} | H30: {=_xll.YCI($B30,H$3)} | I30: {=_xll.YCI($B30,I$3)} | J30: {=_xll.YCI($B30,J$3)} | ... N30: {=_xll.YCI($B30,N$3)} | O30: {=_xll.YCP($B30,O$3)} | P30: {=_xll.YCP($B30,P$3)} | Q30: {=_xll.YCP($B30,Q$3)} | R30: {=_xll.YCP($B30,R$3)} | S30: {=_xll.YCP($B30,S$3)} | T30: {=_xll.YCP($B30,T$3)} | U30: {=_xll.YCP($B30,U$3)} | V30: {=_xll.YCP($B30,V$3)} | ... CF30: {=_xll.YCP($B30,CF$3)}
A31: =Securities!B6 -> AVIG | C31: {=_xll.YCI($B31,C$3)} | D31: {=_xll.YCI($B31,D$3)} | E31: {=_xll.YCI($B31,E$3)} | F31: {=_xll.YCI($B31,F$3)} | G31: {=_xll.YCI($B31,G$3)} | H31: {=_xll.YCI($B31,H$3)} | I31: {=_xll.YCI($B31,I$3)} | J31: {=_xll.YCI($B31,J$3)} | ... N31: {=_xll.YCI($B31,N$3)} | O31: {=_xll.YCP($B31,O$3)} | P31: {=_xll.YCP($B31,P$3)} | Q31: {=_xll.YCP($B31,Q$3)} | R31: {=_xll.YCP($B31,R$3)} | S31: {=_xll.YCP($B31,S$3)} | T31: {=_xll.YCP($B31,T$3)} | U31: {=_xll.YCP($B31,U$3)} | V31: {=_xll.YCP($B31,V$3)} | ... CF31: {=_xll.YCP($B31,CF$3)}
B32: {=_xll.YCI(A31,B2)} -> UNIY | C32: {=_xll.YCI($B32,C$3)} -> WisdomTree Voya Yield Enhanced USD Unvrsl Bd Fund | D32: {=_xll.YCI($B32,D$3)} -> etf | E32: {=_xll.YCI($B32,E$3)} -> The investment seeks to track the price and yield performance, before fees and expenses, of the Bloomberg US Universal Enhanced Yield Index. Under normal circumstances, at least 80% of the fund’s net assets, plus the amount of any borrowings for investment purposes, will be invested in the component securities of the index. The index is comprised of USD-denominated bonds. The index deconstructs the USD-denominated bond market, as represented by USD-denominated, taxable bonds that are rated either investment grade or high yield, into one of the five categories of debt. The fund is non-diversified. | F32: {=_xll.YCI($B32,F$3)} -> WisdomTree | G32: {=_xll.YCI($B32,G$3)} -> WisdomTree Asset Management Inc | H32: {=_xll.YCI($B32,H$3)} -> Fixed Income | I32: {=_xll.YCI($B32,I$3)} -> Taxable Bond | J32: {=_xll.YCI($B32,J$3)} -> Intermediate Core Bond | ... N32: {=_xll.YCI($B32,N$3)} -> 2023-02-06 | O32: {=_xll.YCP($B32,O$3)} -> 1314346757 | P32: {=_xll.YCP($B32,P$3)} -> 0.0015 | Q32: {=_xll.YCP($B32,Q$3)} -> 13 | R32: {=_xll.YCP($B32,R$3)} -> 8 | S32: {=_xll.YCP($B32,S$3)} -> 3.49 | T32: {=_xll.YCP($B32,T$3)} -> -6.925e-05 | U32: {=_xll.YCP($B32,U$3)} -> 24 | V32: {=_xll.YCP($B32,V$3)} -> 12 | ... CF32: {=_xll.YCP($B32,CF$3)} -> 24
B33: FLCB | C33: {=_xll.YCI($B33,C$3)} -> Franklin US Core Bond ETF | D33: {=_xll.YCI($B33,D$3)} -> etf | E33: {=_xll.YCI($B33,E$3)} -> The investment seeks total return. Under normal market conditions, the fund invests at least 80% of its net assets in bonds of U.S. issuers, including government, corporate debt, mortgage-backed and asset-backed securities. It invests predominantly in investment grade debt securities and, under normal market conditions, is generally expected to have sector, credit and duration exposures comparable to the Bloomberg U.S. Aggregate Bond Index, the fund's benchmark index. | F33: {=_xll.YCI($B33,F$3)} -> Franklin Templeton Investments | G33: {=_xll.YCI($B33,G$3)} -> Franklin Advisers, Inc. | H33: {=_xll.YCI($B33,H$3)} -> Fixed Income | I33: {=_xll.YCI($B33,I$3)} -> Taxable Bond | J33: {=_xll.YCI($B33,J$3)} -> Intermediate Core Bond | ... N33: {=_xll.YCI($B33,N$3)} -> 2019-09-17 | O33: {=_xll.YCP($B33,O$3)} -> 3056184236 | P33: {=_xll.YCP($B33,P$3)} -> 0.0015 | Q33: {=_xll.YCP($B33,Q$3)} -> 13 | R33: {=_xll.YCP($B33,R$3)} -> 9 | S33: {=_xll.YCP($B33,S$3)} -> 6.88 | T33: {=_xll.YCP($B33,T$3)} -> 0.00042774 | U33: {=_xll.YCP($B33,U$3)} -> 50 | V33: {=_xll.YCP($B33,V$3)} -> 44 | ... CF33: {=_xll.YCP($B33,CF$3)} -> 488
B34: BND | C34: {=_xll.YCI($B34,C$3)} -> Vanguard Total Bond Market Index Fund ETF | D34: {=_xll.YCI($B34,D$3)} -> etf | E34: {=_xll.YCI($B34,E$3)} -> The investment seeks to track the performance of the Bloomberg U.S. Aggregate Float Adjusted Index. This index measures the performance of a wide spectrum of public, investment-grade, taxable, fixed income securities in the United States-including government, corporate, and international dollar-denominated bonds, as well as mortgage-backed and asset-backed securities-all with maturities of more than 1 year. All of the fund's investments will be selected through the sampling process, and at least 80% of its assets will be invested in bonds held in the index. | F34: {=_xll.YCI($B34,F$3)} -> Vanguard | G34: {=_xll.YCI($B34,G$3)} -> Vanguard Group, Inc. (via Vanguard Capital Mgmt) | H34: {=_xll.YCI($B34,H$3)} -> Fixed Income | I34: {=_xll.YCI($B34,I$3)} -> Taxable Bond | J34: {=_xll.YCI($B34,J$3)} -> Intermediate Core Bond | ... N34: {=_xll.YCI($B34,N$3)} -> 2007-04-03 | O34: {=_xll.YCP($B34,O$3)} -> 160932184250 | P34: {=_xll.YCP($B34,P$3)} -> 0.0003 | Q34: {=_xll.YCP($B34,Q$3)} -> 7 | R34: {=_xll.YCP($B34,R$3)} -> 4 | S34: {=_xll.YCP($B34,S$3)} -> 13.45 | T34: {=_xll.YCP($B34,T$3)} -> 0.00013848 | U34: {=_xll.YCP($B34,U$3)} -> 60 | V34: {=_xll.YCP($B34,V$3)} -> 55 | ... CF34: {=_xll.YCP($B34,CF$3)} -> 488
B35: AGG | C35: {=_xll.YCI($B35,C$3)} -> iShares Core US Aggregate Bond ETF | D35: {=_xll.YCI($B35,D$3)} -> etf | E35: {=_xll.YCI($B35,E$3)} -> The investment seeks to track the investment results of the Bloomberg U.S. Aggregate Bond Index. The index measures the performance of the total U.S. investment-grade bond market. The fund will invest at least 80% of its assets in the component securities of the underlying index and TBAs that have economic characteristics that are substantially identical to the economic characteristics of the component securities of the underlying index, and the fund will invest at least 90% of its assets in fixed income securities of the types included in the underlying index that the advisor believes will help the fund track the underlying index. | F35: {=_xll.YCI($B35,F$3)} -> iShares | G35: {=_xll.YCI($B35,G$3)} -> BlackRock Fund Advisors | H35: {=_xll.YCI($B35,H$3)} -> Fixed Income | I35: {=_xll.YCI($B35,I$3)} -> Taxable Bond | J35: {=_xll.YCI($B35,J$3)} -> Intermediate Core Bond | ... N35: {=_xll.YCI($B35,N$3)} -> 2003-09-22 | O35: {=_xll.YCP($B35,O$3)} -> 137955566986 | P35: {=_xll.YCP($B35,P$3)} -> 0.0003 | Q35: {=_xll.YCP($B35,Q$3)} -> 7 | R35: {=_xll.YCP($B35,R$3)} -> 4 | S35: {=_xll.YCP($B35,S$3)} -> 15.1 | T35: {=_xll.YCP($B35,T$3)} -> -6.39e-06 | U35: {=_xll.YCP($B35,U$3)} -> 54 | V35: {=_xll.YCP($B35,V$3)} -> 55 | ... CF35: {=_xll.YCP($B35,CF$3)} -> 488
B36: BIV | C36: {=_xll.YCI($B36,C$3)} -> Vanguard Intermediate-Term Bond Index Fund ETF | D36: {=_xll.YCI($B36,D$3)} -> etf | E36: {=_xll.YCI($B36,E$3)} -> The investment seeks to track the performance of the Bloomberg U.S. 5-10 Year Government/Credit Float Adjusted Index. This index includes all medium and larger issues of U.S. government, investment-grade corporate and investment-grade international dollar-denominated bonds that have maturities between 5 and 10 years and are publicly issued. All of the fund's investments will be selected through the sampling process, and at least 80% of its assets will be invested in bonds held in the index. | F36: {=_xll.YCI($B36,F$3)} -> Vanguard | G36: {=_xll.YCI($B36,G$3)} -> Vanguard Group, Inc. (via Vanguard Capital Mgmt) | H36: {=_xll.YCI($B36,H$3)} -> Fixed Income | I36: {=_xll.YCI($B36,I$3)} -> Taxable Bond | J36: {=_xll.YCI($B36,J$3)} -> Intermediate Core Bond | ... N36: {=_xll.YCI($B36,N$3)} -> 2007-04-03 | O36: {=_xll.YCP($B36,O$3)} -> 28797391268 | P36: {=_xll.YCP($B36,P$3)} -> 0.0003 | Q36: {=_xll.YCP($B36,Q$3)} -> 7 | R36: {=_xll.YCP($B36,R$3)} -> 4 | S36: {=_xll.YCP($B36,S$3)} -> 18.28 | T36: {=_xll.YCP($B36,T$3)} -> 0 | U36: {=_xll.YCP($B36,U$3)} -> 18 | V36: {=_xll.YCP($B36,V$3)} -> 16 | ... CF36: {=_xll.YCP($B36,CF$3)} -> 488
C37: {=_xll.YCI($B37,C$3)} | D37: {=_xll.YCI($B37,D$3)} | E37: {=_xll.YCI($B37,E$3)} | F37: {=_xll.YCI($B37,F$3)} | G37: {=_xll.YCI($B37,G$3)} | H37: {=_xll.YCI($B37,H$3)} | I37: {=_xll.YCI($B37,I$3)} | J37: {=_xll.YCI($B37,J$3)} | ... N37: {=_xll.YCI($B37,N$3)} | O37: {=_xll.YCP($B37,O$3)} | P37: {=_xll.YCP($B37,P$3)} | Q37: {=_xll.YCP($B37,Q$3)} | R37: {=_xll.YCP($B37,R$3)} | S37: {=_xll.YCP($B37,S$3)} | T37: {=_xll.YCP($B37,T$3)} | U37: {=_xll.YCP($B37,U$3)} | V37: {=_xll.YCP($B37,V$3)} | ... CF37: {=_xll.YCP($B37,CF$3)}
A38: =Securities!B7 -> M:BIMIX | C38: {=_xll.YCI($B38,C$3)} | D38: {=_xll.YCI($B38,D$3)} | E38: {=_xll.YCI($B38,E$3)} | F38: {=_xll.YCI($B38,F$3)} | G38: {=_xll.YCI($B38,G$3)} | H38: {=_xll.YCI($B38,H$3)} | I38: {=_xll.YCI($B38,I$3)} | J38: {=_xll.YCI($B38,J$3)} | ... N38: {=_xll.YCI($B38,N$3)} | O38: {=_xll.YCP($B38,O$3)} | P38: {=_xll.YCP($B38,P$3)} | Q38: {=_xll.YCP($B38,Q$3)} | R38: {=_xll.YCP($B38,R$3)} | S38: {=_xll.YCP($B38,S$3)} | T38: {=_xll.YCP($B38,T$3)} | U38: {=_xll.YCP($B38,U$3)} | V38: {=_xll.YCP($B38,V$3)} | ... CF38: {=_xll.YCP($B38,CF$3)}
B39: {=_xll.YCI(A38,B2)} -> M:BAGIX | C39: {=_xll.YCI($B39,C$3)} -> Baird Aggregate Bond Fund Institutional | D39: {=_xll.YCI($B39,D$3)} -> mutual_fund | E39: {=_xll.YCI($B39,E$3)} -> The investment seeks an annual rate of total return, before fund expenses, greater than the annual rate of total return of the Bloomberg U.S. Aggregate Index. The fund normally invests at least 80% of its net assets in the following types of U.S. dollar‑denominated debt obligations: U.S. government and other public‑sector entities; asset‑backed and mortgage‑backed obligations of U.S. and foreign issuers; corporate debt of U.S. and foreign issuers. | F39: {=_xll.YCI($B39,F$3)} -> Baird | G39: {=_xll.YCI($B39,G$3)} -> Robert W. Baird & Co. Incorporated | H39: {=_xll.YCI($B39,H$3)} -> Fixed Income | I39: {=_xll.YCI($B39,I$3)} -> Taxable Bond | J39: {=_xll.YCI($B39,J$3)} -> Intermediate Core Bond | ... N39: {=_xll.YCI($B39,N$3)} -> 2000-09-29 | O39: {=_xll.YCP($B39,O$3)} -> 56602334036 | P39: {=_xll.YCP($B39,P$3)} -> 0.003 | Q39: {=_xll.YCP($B39,Q$3)} -> 33 | R39: {=_xll.YCP($B39,R$3)} -> 18 | S39: {=_xll.YCP($B39,S$3)} -> 25.85 | T39: {=_xll.YCP($B39,T$3)} -> ERR: INVALID CALC | U39: {=_xll.YCP($B39,U$3)} -> 20 | V39: {=_xll.YCP($B39,V$3)} -> 3 | ... CF39: {=_xll.YCP($B39,CF$3)} -> 488
B40: M:VBMPX | C40: {=_xll.YCI($B40,C$3)} -> Vanguard Total Bond Market Index Fund Inst Plus | D40: {=_xll.YCI($B40,D$3)} -> mutual_fund | E40: {=_xll.YCI($B40,E$3)} -> The investment seeks to track the performance of the Bloomberg U.S. Aggregate Float Adjusted Index. This index measures the performance of a wide spectrum of public, investment-grade, taxable, fixed income securities in the United States-including government, corporate, and international dollar-denominated bonds, as well as mortgage-backed and asset-backed securities-all with maturities of more than 1 year. All of the fund's investments will be selected through the sampling process, and at least 80% of its assets will be invested in bonds held in the index. | F40: {=_xll.YCI($B40,F$3)} -> Vanguard | G40: {=_xll.YCI($B40,G$3)} -> Vanguard Group, Inc. (via Vanguard Capital Mgmt) | H40: {=_xll.YCI($B40,H$3)} -> Fixed Income | I40: {=_xll.YCI($B40,I$3)} -> Taxable Bond | J40: {=_xll.YCI($B40,J$3)} -> Intermediate Core Bond | ... N40: {=_xll.YCI($B40,N$3)} -> 1995-09-18 | O40: {=_xll.YCP($B40,O$3)} -> 35813762820 | P40: {=_xll.YCP($B40,P$3)} -> 0.0002 | Q40: {=_xll.YCP($B40,Q$3)} -> 5 | R40: {=_xll.YCP($B40,R$3)} -> 3 | S40: {=_xll.YCP($B40,S$3)} -> 13.45 | T40: {=_xll.YCP($B40,T$3)} -> ERR: INVALID CALC | U40: {=_xll.YCP($B40,U$3)} -> 54 | V40: {=_xll.YCP($B40,V$3)} -> 52 | ... CF40: {=_xll.YCP($B40,CF$3)} -> 488
B41: M:VBILX | C41: {=_xll.YCI($B41,C$3)} -> Vanguard Intermediate-Term Bond Index Fund Admiral | D41: {=_xll.YCI($B41,D$3)} -> mutual_fund | E41: {=_xll.YCI($B41,E$3)} -> The investment seeks to track the performance of the Bloomberg U.S. 5-10 Year Government/Credit Float Adjusted Index. This index includes all medium and larger issues of U.S. government, investment-grade corporate and investment-grade international dollar-denominated bonds that have maturities between 5 and 10 years and are publicly issued. All of the fund's investments will be selected through the sampling process, and at least 80% of its assets will be invested in bonds held in the index. | F41: {=_xll.YCI($B41,F$3)} -> Vanguard | G41: {=_xll.YCI($B41,G$3)} -> Vanguard Group, Inc. (via Vanguard Capital Mgmt) | H41: {=_xll.YCI($B41,H$3)} -> Fixed Income | I41: {=_xll.YCI($B41,I$3)} -> Taxable Bond | J41: {=_xll.YCI($B41,J$3)} -> Intermediate Core Bond | ... N41: {=_xll.YCI($B41,N$3)} -> 2001-11-12 | O41: {=_xll.YCP($B41,O$3)} -> 18726019274 | P41: {=_xll.YCP($B41,P$3)} -> 0.0006 | Q41: {=_xll.YCP($B41,Q$3)} -> 8 | R41: {=_xll.YCP($B41,R$3)} -> 6 | S41: {=_xll.YCP($B41,S$3)} -> 18.28 | T41: {=_xll.YCP($B41,T$3)} -> ERR: INVALID CALC | U41: {=_xll.YCP($B41,U$3)} -> 19 | V41: {=_xll.YCP($B41,V$3)} -> 20 | ... CF41: {=_xll.YCP($B41,CF$3)} -> 488
B42: M:JIBEX | C42: {=_xll.YCI($B42,C$3)} -> Johnson Institutional Intermediate Bond Fund I | D42: {=_xll.YCI($B42,D$3)} -> mutual_fund | E42: {=_xll.YCI($B42,E$3)} -> The investment seeks a high level of income over the long term consistent with preservation of capital. The fund invests at least 80% of its net assets, plus any amounts for borrowing, in a broad range of investment grade fixed income securities, including bonds, notes, domestic and foreign corporate and government securities, government agency securities, mortgage-backed securities, collateralized mortgage obligations, asset-backed securities, municipal securities and short-term obligations. It does not limit itself to securities of a particular maturity range but will normally seek to maintain a dollar weighted average duration between 3 and 5 years. | F42: {=_xll.YCI($B42,F$3)} -> Johnson Mutual Funds | G42: {=_xll.YCI($B42,G$3)} -> Johnson Investment Counsel Inc | H42: {=_xll.YCI($B42,H$3)} -> Fixed Income | I42: {=_xll.YCI($B42,I$3)} -> Taxable Bond | J42: {=_xll.YCI($B42,J$3)} -> Intermediate Core Bond | ... N42: {=_xll.YCI($B42,N$3)} -> 2000-08-31 | O42: {=_xll.YCP($B42,O$3)} -> 401469441 | P42: {=_xll.YCP($B42,P$3)} -> 0.0025 | Q42: {=_xll.YCP($B42,Q$3)} -> 29 | R42: {=_xll.YCP($B42,R$3)} -> 16 | S42: {=_xll.YCP($B42,S$3)} -> 25.93 | T42: {=_xll.YCP($B42,T$3)} -> ERR: INVALID CALC | U42: {=_xll.YCP($B42,U$3)} -> 14 | V42: {=_xll.YCP($B42,V$3)} -> 29 | ... CF42: {=_xll.YCP($B42,CF$3)} -> 154
B43: M:LP40232734 | C43: {=_xll.YCI($B43,C$3)} -> JNL Bond Index Fund I | D43: {=_xll.YCI($B43,D$3)} -> insurance_fund | E43: {=_xll.YCI($B43,E$3)} -> The investment seeks to track the performance of the Bloomberg U.S. Aggregate Bond Index to provide a moderate rate of income by investing in domestic fixed-income investments. The fund invests under normal circumstances at least 80% of its assets in fixed-income securities that seek to track the performance and characteristics of the index that Sub-Adviser believes to be important such as Option Adjusted Duration, Maturity, Average Quality Rating, Sector/Industries, and Yield to worst. The index includes Treasuries, government-related credit, mortgage-backed securities, asset-backed securities and commercial mortgage backed securities. | F43: {=_xll.YCI($B43,F$3)} -> Jackson National | G43: {=_xll.YCI($B43,G$3)} -> Jackson National Asset Management, LLC | H43: {=_xll.YCI($B43,H$3)} -> Fixed Income | I43: {=_xll.YCI($B43,I$3)} -> Taxable Bond | J43: {=_xll.YCI($B43,J$3)} -> Intermediate Core Bond | ... N43: {=_xll.YCI($B43,N$3)} -> ERR: NO DATA | O43: {=_xll.YCP($B43,O$3)} -> 1030585505 | P43: {=_xll.YCP($B43,P$3)} -> 0.0009 | Q43: {=_xll.YCP($B43,Q$3)} -> 9 | R43: {=_xll.YCP($B43,R$3)} -> 6 | S43: {=_xll.YCP($B43,S$3)} -> 1.09 | T43: {=_xll.YCP($B43,T$3)} -> ERR: INVALID CALC | U43: {=_xll.YCP($B43,U$3)} -> 53 | V43: {=_xll.YCP($B43,V$3)} -> 52 | ... CF43: {=_xll.YCP($B43,CF$3)} -> 24
C44: {=_xll.YCI($B44,C$3)} | D44: {=_xll.YCI($B44,D$3)} | E44: {=_xll.YCI($B44,E$3)} | F44: {=_xll.YCI($B44,F$3)} | G44: {=_xll.YCI($B44,G$3)} | H44: {=_xll.YCI($B44,H$3)} | I44: {=_xll.YCI($B44,I$3)} | J44: {=_xll.YCI($B44,J$3)} | ... N44: {=_xll.YCI($B44,N$3)} | O44: {=_xll.YCP($B44,O$3)} | P44: {=_xll.YCP($B44,P$3)} | Q44: {=_xll.YCP($B44,Q$3)} | R44: {=_xll.YCP($B44,R$3)} | S44: {=_xll.YCP($B44,S$3)} | T44: {=_xll.YCP($B44,T$3)} | U44: {=_xll.YCP($B44,U$3)} | V44: {=_xll.YCP($B44,V$3)} | ... CF44: {=_xll.YCP($B44,CF$3)}
A45: =Securities!B8 -> BIV | C45: {=_xll.YCI($B45,C$3)} | D45: {=_xll.YCI($B45,D$3)} | E45: {=_xll.YCI($B45,E$3)} | F45: {=_xll.YCI($B45,F$3)} | G45: {=_xll.YCI($B45,G$3)} | H45: {=_xll.YCI($B45,H$3)} | I45: {=_xll.YCI($B45,I$3)} | J45: {=_xll.YCI($B45,J$3)} | ... N45: {=_xll.YCI($B45,N$3)} | O45: {=_xll.YCP($B45,O$3)} | P45: {=_xll.YCP($B45,P$3)} | Q45: {=_xll.YCP($B45,Q$3)} | R45: {=_xll.YCP($B45,R$3)} | S45: {=_xll.YCP($B45,S$3)} | T45: {=_xll.YCP($B45,T$3)} | U45: {=_xll.YCP($B45,U$3)} | V45: {=_xll.YCP($B45,V$3)} | ... CF45: {=_xll.YCP($B45,CF$3)}
B46: {=_xll.YCI(A45,B2)} -> BND | C46: {=_xll.YCI($B46,C$3)} -> Vanguard Total Bond Market Index Fund ETF | D46: {=_xll.YCI($B46,D$3)} -> etf | E46: {=_xll.YCI($B46,E$3)} -> The investment seeks to track the performance of the Bloomberg U.S. Aggregate Float Adjusted Index. This index measures the performance of a wide spectrum of public, investment-grade, taxable, fixed income securities in the United States-including government, corporate, and international dollar-denominated bonds, as well as mortgage-backed and asset-backed securities-all with maturities of more than 1 year. All of the fund's investments will be selected through the sampling process, and at least 80% of its assets will be invested in bonds held in the index. | F46: {=_xll.YCI($B46,F$3)} -> Vanguard | G46: {=_xll.YCI($B46,G$3)} -> Vanguard Group, Inc. (via Vanguard Capital Mgmt) | H46: {=_xll.YCI($B46,H$3)} -> Fixed Income | I46: {=_xll.YCI($B46,I$3)} -> Taxable Bond | J46: {=_xll.YCI($B46,J$3)} -> Intermediate Core Bond | ... N46: {=_xll.YCI($B46,N$3)} -> 2007-04-03 | O46: {=_xll.YCP($B46,O$3)} -> 160932184250 | P46: {=_xll.YCP($B46,P$3)} -> 0.0003 | Q46: {=_xll.YCP($B46,Q$3)} -> 7 | R46: {=_xll.YCP($B46,R$3)} -> 4 | S46: {=_xll.YCP($B46,S$3)} -> 13.45 | T46: {=_xll.YCP($B46,T$3)} -> 0.00013848 | U46: {=_xll.YCP($B46,U$3)} -> 60 | V46: {=_xll.YCP($B46,V$3)} -> 55 | ... CF46: {=_xll.YCP($B46,CF$3)} -> 488
B47: VTC | C47: {=_xll.YCI($B47,C$3)} -> Vanguard Total Corporate Bond ETF | D47: {=_xll.YCI($B47,D$3)} -> etf | E47: {=_xll.YCI($B47,E$3)} -> The investment seeks to track the performance of the Bloomberg U.S. Corporate Bond Index. The fund is a fund of funds and employs an indexing investment approach designed to track the performance of the Bloomberg U.S. Corporate Bond Index, which measures the investment-grade, fixed-rate, taxable corporate bond market. The index includes U.S. dollar-denominated securities that are publicly issued by industrial, utility, and financial issuers. | F47: {=_xll.YCI($B47,F$3)} -> Vanguard | G47: {=_xll.YCI($B47,G$3)} -> Vanguard Group, Inc. (via Vanguard Capital Mgmt) | H47: {=_xll.YCI($B47,H$3)} -> Fixed Income | I47: {=_xll.YCI($B47,I$3)} -> Taxable Bond | J47: {=_xll.YCI($B47,J$3)} -> Corporate Bond | ... N47: {=_xll.YCI($B47,N$3)} -> 2017-11-07 | O47: {=_xll.YCP($B47,O$3)} -> 1710158952 | P47: {=_xll.YCP($B47,P$3)} -> 0.0003 | Q47: {=_xll.YCP($B47,Q$3)} -> 2 | R47: {=_xll.YCP($B47,R$3)} -> 4 | S47: {=_xll.YCP($B47,S$3)} -> 8.74 | T47: {=_xll.YCP($B47,T$3)} -> 7.998e-05 | U47: {=_xll.YCP($B47,U$3)} -> 50 | V47: {=_xll.YCP($B47,V$3)} -> 48 | ... CF47: {=_xll.YCP($B47,CF$3)} -> 488
B48: VCIT | C48: {=_xll.YCI($B48,C$3)} -> Vanguard Intermediate-Term Corp Bond Idx Fund ETF | D48: {=_xll.YCI($B48,D$3)} -> etf | E48: {=_xll.YCI($B48,E$3)} -> The investment seeks to track the performance of a market-weighted corporate bond index with an intermediate-term dollar-weighted average maturity. The fund employs an indexing investment approach designed to track the performance of the Bloomberg U.S. 5-10 Year Corporate Bond Index. This index includes U.S. dollar-denominated, investment-grade, fixed-rate, taxable securities issued by U.S. and non-U.S. industrial, utility, and financial companies, with maturities between 5 and 10 years. Under normal circumstances, at least 80% of the fund's assets will be invested in bonds included in the index. | F48: {=_xll.YCI($B48,F$3)} -> Vanguard | G48: {=_xll.YCI($B48,G$3)} -> Vanguard Group, Inc. (via Vanguard Capital Mgmt) | H48: {=_xll.YCI($B48,H$3)} -> Fixed Income | I48: {=_xll.YCI($B48,I$3)} -> Taxable Bond | J48: {=_xll.YCI($B48,J$3)} -> Corporate Bond | ... N48: {=_xll.YCI($B48,N$3)} -> 2009-11-19 | O48: {=_xll.YCP($B48,O$3)} -> 67652763868 | P48: {=_xll.YCP($B48,P$3)} -> 0.0003 | Q48: {=_xll.YCP($B48,Q$3)} -> 2 | R48: {=_xll.YCP($B48,R$3)} -> 7 | S48: {=_xll.YCP($B48,S$3)} -> 16.71 | T48: {=_xll.YCP($B48,T$3)} -> -0.00012333 | U48: {=_xll.YCP($B48,U$3)} -> 3 | V48: {=_xll.YCP($B48,V$3)} -> 3 | ... CF48: {=_xll.YCP($B48,CF$3)} -> 210
B49: BSV | C49: {=_xll.YCI($B49,C$3)} -> Vanguard Short-Term Bond Index Fund ETF | D49: {=_xll.YCI($B49,D$3)} -> etf | E49: {=_xll.YCI($B49,E$3)} -> The investment seeks to track the performance of the Bloomberg U.S. 1-5 Year Government/Credit Float Adjusted Index. This index includes all medium and larger issues of U.S. government, investment-grade corporate, and investment-grade international dollar-denominated bonds that have maturities between 1 and 5 years and are publicly issued. All of the fund's investments will be selected through the sampling process, and at least 80% of its assets will be invested in bonds held in the index. | F49: {=_xll.YCI($B49,F$3)} -> Vanguard | G49: {=_xll.YCI($B49,G$3)} -> Vanguard Group, Inc. (via Vanguard Capital Mgmt) | H49: {=_xll.YCI($B49,H$3)} -> Fixed Income | I49: {=_xll.YCI($B49,I$3)} -> Taxable Bond | J49: {=_xll.YCI($B49,J$3)} -> Short-Term Bond | ... N49: {=_xll.YCI($B49,N$3)} -> 2007-04-03 | O49: {=_xll.YCP($B49,O$3)} -> 45614532573 | P49: {=_xll.YCP($B49,P$3)} -> 0.0003 | Q49: {=_xll.YCP($B49,Q$3)} -> 3 | R49: {=_xll.YCP($B49,R$3)} -> 3 | S49: {=_xll.YCP($B49,S$3)} -> 13.45 | T49: {=_xll.YCP($B49,T$3)} -> 0.00012883 | U49: {=_xll.YCP($B49,U$3)} -> 77 | V49: {=_xll.YCP($B49,V$3)} -> 76 | ... CF49: {=_xll.YCP($B49,CF$3)} -> 336
B50: EDV | C50: {=_xll.YCI($B50,C$3)} -> Vanguard Extended Duration Treasury Index Fd ETF | D50: {=_xll.YCI($B50,D$3)} -> etf | E50: {=_xll.YCI($B50,E$3)} -> The investment seeks to track the performance of the Bloomberg U.S. Treasury STRIPS 20–30 Year Equal Par Bond Index of extended-duration zero-coupon U.S. Treasury securities. The advisor employs an indexing investment approach designed to track the performance of the Bloomberg U.S. Treasury STRIPS 20-30 Year Equal Par Bond Index. This index includes zero-coupon U.S. Treasury securities (Treasury STRIPS), which are backed by the full faith and credit of the U.S. government, with maturities ranging from 20 to 30 years. The fund invests by sampling the index. At least 80% of it's assets will be invested in U.S. Treasury securities held in the index. | F50: {=_xll.YCI($B50,F$3)} -> Vanguard | G50: {=_xll.YCI($B50,G$3)} -> Vanguard Group, Inc. (via Vanguard Capital Mgmt) | H50: {=_xll.YCI($B50,H$3)} -> Fixed Income | I50: {=_xll.YCI($B50,I$3)} -> Taxable Bond | J50: {=_xll.YCI($B50,J$3)} -> Long Government | ... N50: {=_xll.YCI($B50,N$3)} -> 2007-12-06 | O50: {=_xll.YCP($B50,O$3)} -> 3436938328 | P50: {=_xll.YCP($B50,P$3)} -> 0.0005 | Q50: {=_xll.YCP($B50,Q$3)} -> 11 | R50: {=_xll.YCP($B50,R$3)} -> 26 | S50: {=_xll.YCP($B50,S$3)} -> 13.45 | T50: {=_xll.YCP($B50,T$3)} -> 0.00615174 | U50: {=_xll.YCP($B50,U$3)} -> 92 | V50: {=_xll.YCP($B50,V$3)} -> 33 | ... CF50: {=_xll.YCP($B50,CF$3)} -> 40
C51: {=_xll.YCI($B51,C$3)} | D51: {=_xll.YCI($B51,D$3)} | E51: {=_xll.YCI($B51,E$3)} | F51: {=_xll.YCI($B51,F$3)} | G51: {=_xll.YCI($B51,G$3)} | H51: {=_xll.YCI($B51,H$3)} | I51: {=_xll.YCI($B51,I$3)} | J51: {=_xll.YCI($B51,J$3)} | ... N51: {=_xll.YCI($B51,N$3)} | O51: {=_xll.YCP($B51,O$3)} | P51: {=_xll.YCP($B51,P$3)} | Q51: {=_xll.YCP($B51,Q$3)} | R51: {=_xll.YCP($B51,R$3)} | S51: {=_xll.YCP($B51,S$3)} | T51: {=_xll.YCP($B51,T$3)} | U51: {=_xll.YCP($B51,U$3)} | V51: {=_xll.YCP($B51,V$3)} | ... CF51: {=_xll.YCP($B51,CF$3)}
A52: =Securities!B9 -> M:BRXIX | C52: {=_xll.YCI($B52,C$3)} | D52: {=_xll.YCI($B52,D$3)} | E52: {=_xll.YCI($B52,E$3)} | F52: {=_xll.YCI($B52,F$3)} | G52: {=_xll.YCI($B52,G$3)} | H52: {=_xll.YCI($B52,H$3)} | I52: {=_xll.YCI($B52,I$3)} | J52: {=_xll.YCI($B52,J$3)} | ... N52: {=_xll.YCI($B52,N$3)} | O52: {=_xll.YCP($B52,O$3)} | P52: {=_xll.YCP($B52,P$3)} | Q52: {=_xll.YCP($B52,Q$3)} | R52: {=_xll.YCP($B52,R$3)} | S52: {=_xll.YCP($B52,S$3)} | T52: {=_xll.YCP($B52,T$3)} | U52: {=_xll.YCP($B52,U$3)} | V52: {=_xll.YCP($B52,V$3)} | ... CF52: {=_xll.YCP($B52,CF$3)}
B53: {=_xll.YCI(A52,B2)} -> M:MRSIX | C53: {=_xll.YCI($B53,C$3)} -> MFS Research International Fund I | D53: {=_xll.YCI($B53,D$3)} -> mutual_fund | E53: {=_xll.YCI($B53,E$3)} -> The investment seeks capital appreciation. The fund normally invests its assets primarily in foreign equity securities, including emerging market equity securities. Equity securities include common stocks depositary receipts, and other securities that represent an ownership interest (or right to acquire an ownership interest) in a company or other issuer. MFS normally invests the fund's assets across different industries, sectors, countries, and regions, but MFS may invest a significant percentage of the fund's assets in issuers in a single industry, sector, country, or region. | F53: {=_xll.YCI($B53,F$3)} -> MFS | G53: {=_xll.YCI($B53,G$3)} -> Massachusetts Financial Services Company | H53: {=_xll.YCI($B53,H$3)} -> Equity | I53: {=_xll.YCI($B53,I$3)} -> International Equity | J53: {=_xll.YCI($B53,J$3)} -> Foreign Large Blend | ... N53: {=_xll.YCI($B53,N$3)} -> 1997-01-02 | O53: {=_xll.YCP($B53,O$3)} -> 1327874512 | P53: {=_xll.YCP($B53,P$3)} -> 0.0074 | Q53: {=_xll.YCP($B53,Q$3)} -> 51 | R53: {=_xll.YCP($B53,R$3)} -> 47 | S53: {=_xll.YCP($B53,S$3)} -> 3.59 | T53: {=_xll.YCP($B53,T$3)} -> ERR: INVALID CALC | U53: {=_xll.YCP($B53,U$3)} -> 83 | V53: {=_xll.YCP($B53,V$3)} -> 85 | ... CF53: {=_xll.YCP($B53,CF$3)} -> 310
B54: M:OIIEX | C54: {=_xll.YCI($B54,C$3)} -> Optimum International Fund Institutional | D54: {=_xll.YCI($B54,D$3)} -> mutual_fund | E54: {=_xll.YCI($B54,E$3)} -> The investment seeks long-term growth of capital and may also seek income. The fund invests primarily in non-U.S. securities; including securities of issuers located in emerging markets, but, in any event, will invest at least 65% of its net assets in non-U.S. securities. The Advisor intends to invest primarily in common stocks, but it may also invest in other securities that a sub-advisor believes provide opportunities for capital growth and income, such as preferred stocks, rights and warrants, depositary receipts, participatory notes and securities convertible into common stocks. | F54: {=_xll.YCI($B54,F$3)} -> Nomura | G54: {=_xll.YCI($B54,G$3)} -> Delaware Management Company | H54: {=_xll.YCI($B54,H$3)} -> Equity | I54: {=_xll.YCI($B54,I$3)} -> International Equity | J54: {=_xll.YCI($B54,J$3)} -> Foreign Large Blend | ... N54: {=_xll.YCI($B54,N$3)} -> 2003-08-01 | O54: {=_xll.YCP($B54,O$3)} -> 1178944004 | P54: {=_xll.YCP($B54,P$3)} -> 0.0107 | Q54: {=_xll.YCP($B54,Q$3)} -> 78 | R54: {=_xll.YCP($B54,R$3)} -> 66 | S54: {=_xll.YCP($B54,S$3)} -> 11.55 | T54: {=_xll.YCP($B54,T$3)} -> ERR: INVALID CALC | U54: {=_xll.YCP($B54,U$3)} -> 67 | V54: {=_xll.YCP($B54,V$3)} -> 37 | ... CF54: {=_xll.YCP($B54,CF$3)} -> 121
B55: M:CRLSX | C55: {=_xll.YCI($B55,C$3)} -> Catholic Responsible Investments Intl Eqty Fd Inst | D55: {=_xll.YCI($B55,D$3)} -> mutual_fund | E55: {=_xll.YCI($B55,E$3)} -> The investment seeks to achieve long-term capital appreciation. The fund seeks to achieve long-term capital appreciation by investing primarily in a broadly diversified portfolio of equity securities of well-established companies based in those countries included in the MSCI All Country World Ex-USA Index that are believed to have above-average market appreciation potential. Under normal circumstances, it invests at least 80% of the value of its net assets plus borrowings for investment purposes in equity securities of well-established companies that are located in countries throughout the world. | F55: {=_xll.YCI($B55,F$3)} -> Catholic Responsible Investments Funds | G55: {=_xll.YCI($B55,G$3)} -> Christian Brothers Inv Srvc Inc | H55: {=_xll.YCI($B55,H$3)} -> Equity | I55: {=_xll.YCI($B55,I$3)} -> International Equity | J55: {=_xll.YCI($B55,J$3)} -> Foreign Large Blend | ... N55: {=_xll.YCI($B55,N$3)} -> 2021-12-03 | O55: {=_xll.YCP($B55,O$3)} -> 2236623050 | P55: {=_xll.YCP($B55,P$3)} -> 0.008 | Q55: {=_xll.YCP($B55,Q$3)} -> 57 | R55: {=_xll.YCP($B55,R$3)} -> 54 | S55: {=_xll.YCP($B55,S$3)} -> 4.66 | T55: {=_xll.YCP($B55,T$3)} -> ERR: INVALID CALC | U55: {=_xll.YCP($B55,U$3)} -> 84 | V55: {=_xll.YCP($B55,V$3)} -> 71 | ... CF55: {=_xll.YCP($B55,CF$3)} -> 310
B56: M:MIEKX | C56: {=_xll.YCI($B56,C$3)} -> MFS International Equity Fund I | D56: {=_xll.YCI($B56,D$3)} -> mutual_fund | E56: {=_xll.YCI($B56,E$3)} -> The investment seeks capital appreciation. The fund normally invests at least 80% of the fund's net assets in equity securities. It normally invests the fund's assets primarily in foreign securities, including emerging market securities. The fund normally invests the fund's assets across different industries, sectors, countries, and regions, but it may invest a significant percentage of the fund's assets in issuers in a single industry, sector, country, or region. | F56: {=_xll.YCI($B56,F$3)} -> MFS | G56: {=_xll.YCI($B56,G$3)} -> Massachusetts Financial Services Company | H56: {=_xll.YCI($B56,H$3)} -> Equity | I56: {=_xll.YCI($B56,I$3)} -> International Equity | J56: {=_xll.YCI($B56,J$3)} -> Foreign Large Blend | ... N56: {=_xll.YCI($B56,N$3)} -> 2023-02-08 | O56: {=_xll.YCP($B56,O$3)} -> 6889942453 | P56: {=_xll.YCP($B56,P$3)} -> 0.0073 | Q56: {=_xll.YCP($B56,Q$3)} -> 50 | R56: {=_xll.YCP($B56,R$3)} -> 47 | S56: {=_xll.YCP($B56,S$3)} -> 10.26 | T56: {=_xll.YCP($B56,T$3)} -> ERR: INVALID CALC | U56: {=_xll.YCP($B56,U$3)} -> 83 | V56: {=_xll.YCP($B56,V$3)} -> 81 | ... CF56: {=_xll.YCP($B56,CF$3)} -> 310
B57: M:TGVIX | C57: {=_xll.YCI($B57,C$3)} -> Thornburg International Equity Fund I | D57: {=_xll.YCI($B57,D$3)} -> mutual_fund | E57: {=_xll.YCI($B57,E$3)} -> The investment seeks long-term capital appreciation; current income is the secondary objective. The fund invests primarily in common stocks of non-U.S. companies and in depositary receipts associated with such stocks. The fund may invest in developing countries. Under normal conditions, the fund will invest at least 80% of its net assets in common stocks or depositary receipts. | F57: {=_xll.YCI($B57,F$3)} -> Thornburg | G57: {=_xll.YCI($B57,G$3)} -> Thornburg Investment Management Inc | H57: {=_xll.YCI($B57,H$3)} -> Equity | I57: {=_xll.YCI($B57,I$3)} -> International Equity | J57: {=_xll.YCI($B57,J$3)} -> Foreign Large Blend | ... N57: {=_xll.YCI($B57,N$3)} -> 1998-05-28 | O57: {=_xll.YCP($B57,O$3)} -> 3836067167 | P57: {=_xll.YCP($B57,P$3)} -> 0.009 | Q57: {=_xll.YCP($B57,Q$3)} -> 66 | R57: {=_xll.YCP($B57,R$3)} -> 65 | S57: {=_xll.YCP($B57,S$3)} -> 20.51 | T57: {=_xll.YCP($B57,T$3)} -> ERR: INVALID CALC | U57: {=_xll.YCP($B57,U$3)} -> 6 | V57: {=_xll.YCP($B57,V$3)} -> 9 | ... CF57: {=_xll.YCP($B57,CF$3)} -> 310
C58: {=_xll.YCI($B58,C$3)} | D58: {=_xll.YCI($B58,D$3)} | E58: {=_xll.YCI($B58,E$3)} | F58: {=_xll.YCI($B58,F$3)} | G58: {=_xll.YCI($B58,G$3)} | H58: {=_xll.YCI($B58,H$3)} | I58: {=_xll.YCI($B58,I$3)} | J58: {=_xll.YCI($B58,J$3)} | ... N58: {=_xll.YCI($B58,N$3)} | O58: {=_xll.YCP($B58,O$3)} | P58: {=_xll.YCP($B58,P$3)} | Q58: {=_xll.YCP($B58,Q$3)} | R58: {=_xll.YCP($B58,R$3)} | S58: {=_xll.YCP($B58,S$3)} | T58: {=_xll.YCP($B58,T$3)} | U58: {=_xll.YCP($B58,U$3)} | V58: {=_xll.YCP($B58,V$3)} | ... CF58: {=_xll.YCP($B58,CF$3)}
A59: =Securities!B10 -> DFCF | C59: {=_xll.YCI($B59,C$3)} | D59: {=_xll.YCI($B59,D$3)} | E59: {=_xll.YCI($B59,E$3)} | F59: {=_xll.YCI($B59,F$3)} | G59: {=_xll.YCI($B59,G$3)} | H59: {=_xll.YCI($B59,H$3)} | I59: {=_xll.YCI($B59,I$3)} | J59: {=_xll.YCI($B59,J$3)} | ... N59: {=_xll.YCI($B59,N$3)} | O59: {=_xll.YCP($B59,O$3)} | P59: {=_xll.YCP($B59,P$3)} | Q59: {=_xll.YCP($B59,Q$3)} | R59: {=_xll.YCP($B59,R$3)} | S59: {=_xll.YCP($B59,S$3)} | T59: {=_xll.YCP($B59,T$3)} | U59: {=_xll.YCP($B59,U$3)} | V59: {=_xll.YCP($B59,V$3)} | ... CF59: {=_xll.YCP($B59,CF$3)}
B60: {=_xll.YCI(A59,B2)} -> BIV | C60: {=_xll.YCI($B60,C$3)} -> Vanguard Intermediate-Term Bond Index Fund ETF | D60: {=_xll.YCI($B60,D$3)} -> etf | E60: {=_xll.YCI($B60,E$3)} -> The investment seeks to track the performance of the Bloomberg U.S. 5-10 Year Government/Credit Float Adjusted Index. This index includes all medium and larger issues of U.S. government, investment-grade corporate and investment-grade international dollar-denominated bonds that have maturities between 5 and 10 years and are publicly issued. All of the fund's investments will be selected through the sampling process, and at least 80% of its assets will be invested in bonds held in the index. | F60: {=_xll.YCI($B60,F$3)} -> Vanguard | G60: {=_xll.YCI($B60,G$3)} -> Vanguard Group, Inc. (via Vanguard Capital Mgmt) | H60: {=_xll.YCI($B60,H$3)} -> Fixed Income | I60: {=_xll.YCI($B60,I$3)} -> Taxable Bond | J60: {=_xll.YCI($B60,J$3)} -> Intermediate Core Bond | ... N60: {=_xll.YCI($B60,N$3)} -> 2007-04-03 | O60: {=_xll.YCP($B60,O$3)} -> 28797391268 | P60: {=_xll.YCP($B60,P$3)} -> 0.0003 | Q60: {=_xll.YCP($B60,Q$3)} -> 7 | R60: {=_xll.YCP($B60,R$3)} -> 4 | S60: {=_xll.YCP($B60,S$3)} -> 18.28 | T60: {=_xll.YCP($B60,T$3)} -> 0 | U60: {=_xll.YCP($B60,U$3)} -> 18 | V60: {=_xll.YCP($B60,V$3)} -> 16 | ... CF60: {=_xll.YCP($B60,CF$3)} -> 488
B61: SCHZ | C61: {=_xll.YCI($B61,C$3)} -> Schwab US Aggregate Bond ETF | D61: {=_xll.YCI($B61,D$3)} -> etf | E61: {=_xll.YCI($B61,E$3)} -> The investment seeks to track as closely as possible, before fees and expenses, the total return of the Bloomberg U.S. Aggregate Bond Index. The fund will invest at least 90% of its net assets in securities included in the index. The index is a broad-based benchmark measuring the performance of the U.S. investment grade, taxable bond market, including U.S. Treasuries, government-related and corporate bonds, mortgage pass-through securities, commercial mortgage-backed securities, and asset-backed securities that are publicly available for sale in the United States. | F61: {=_xll.YCI($B61,F$3)} -> Schwab ETFs | G61: {=_xll.YCI($B61,G$3)} -> Charles Schwab Investment Management Inc | H61: {=_xll.YCI($B61,H$3)} -> Fixed Income | I61: {=_xll.YCI($B61,I$3)} -> Taxable Bond | J61: {=_xll.YCI($B61,J$3)} -> Intermediate Core Bond | ... N61: {=_xll.YCI($B61,N$3)} -> 2011-07-13 | O61: {=_xll.YCP($B61,O$3)} -> 10619485970 | P61: {=_xll.YCP($B61,P$3)} -> 0.0003 | Q61: {=_xll.YCP($B61,Q$3)} -> 7 | R61: {=_xll.YCP($B61,R$3)} -> 4 | S61: {=_xll.YCP($B61,S$3)} -> 15.06 | T61: {=_xll.YCP($B61,T$3)} -> 0.00045975 | U61: {=_xll.YCP($B61,U$3)} -> 57 | V61: {=_xll.YCP($B61,V$3)} -> 70 | ... CF61: {=_xll.YCP($B61,CF$3)} -> 488
B62: BND | C62: {=_xll.YCI($B62,C$3)} -> Vanguard Total Bond Market Index Fund ETF | D62: {=_xll.YCI($B62,D$3)} -> etf | E62: {=_xll.YCI($B62,E$3)} -> The investment seeks to track the performance of the Bloomberg U.S. Aggregate Float Adjusted Index. This index measures the performance of a wide spectrum of public, investment-grade, taxable, fixed income securities in the United States-including government, corporate, and international dollar-denominated bonds, as well as mortgage-backed and asset-backed securities-all with maturities of more than 1 year. All of the fund's investments will be selected through the sampling process, and at least 80% of its assets will be invested in bonds held in the index. | F62: {=_xll.YCI($B62,F$3)} -> Vanguard | G62: {=_xll.YCI($B62,G$3)} -> Vanguard Group, Inc. (via Vanguard Capital Mgmt) | H62: {=_xll.YCI($B62,H$3)} -> Fixed Income | I62: {=_xll.YCI($B62,I$3)} -> Taxable Bond | J62: {=_xll.YCI($B62,J$3)} -> Intermediate Core Bond | ... N62: {=_xll.YCI($B62,N$3)} -> 2007-04-03 | O62: {=_xll.YCP($B62,O$3)} -> 160932184250 | P62: {=_xll.YCP($B62,P$3)} -> 0.0003 | Q62: {=_xll.YCP($B62,Q$3)} -> 7 | R62: {=_xll.YCP($B62,R$3)} -> 4 | S62: {=_xll.YCP($B62,S$3)} -> 13.45 | T62: {=_xll.YCP($B62,T$3)} -> 0.00013848 | U62: {=_xll.YCP($B62,U$3)} -> 60 | V62: {=_xll.YCP($B62,V$3)} -> 55 | ... CF62: {=_xll.YCP($B62,CF$3)} -> 488
B63: BBAG | C63: {=_xll.YCI($B63,C$3)} -> JPMorgan BetaBuilders US Aggregate Bond ETF | D63: {=_xll.YCI($B63,D$3)} -> etf | E63: {=_xll.YCI($B63,E$3)} -> The investment seeks investment results that closely correspond, before fees and expenses, to the performance of the Bloomberg U.S. Aggregate Bond Index. The underlying index covers the U.S. investment grade fixed rate bond market, with index components for government and corporate securities, mortgage pass-through securities, and asset-backed securities. The fund will invest at least 80% of its assets in securities included in the underlying index. | F63: {=_xll.YCI($B63,F$3)} -> JPMorgan | G63: {=_xll.YCI($B63,G$3)} -> J.P. Morgan Investment Management, Inc. | H63: {=_xll.YCI($B63,H$3)} -> Fixed Income | I63: {=_xll.YCI($B63,I$3)} -> Taxable Bond | J63: {=_xll.YCI($B63,J$3)} -> Intermediate Core Bond | ... N63: {=_xll.YCI($B63,N$3)} -> 2018-12-12 | O63: {=_xll.YCP($B63,O$3)} -> 1047934978 | P63: {=_xll.YCP($B63,P$3)} -> 0.0003 | Q63: {=_xll.YCP($B63,Q$3)} -> 7 | R63: {=_xll.YCP($B63,R$3)} -> 4 | S63: {=_xll.YCP($B63,S$3)} -> 2.81 | T63: {=_xll.YCP($B63,T$3)} -> 0.00022163 | U63: {=_xll.YCP($B63,U$3)} -> 59 | V63: {=_xll.YCP($B63,V$3)} -> 71 | ... CF63: {=_xll.YCP($B63,CF$3)} -> 24
B64: BKAG | C64: {=_xll.YCI($B64,C$3)} -> BNY Mellon Core Bond ETF | D64: {=_xll.YCI($B64,D$3)} -> etf | E64: {=_xll.YCI($B64,E$3)} -> The investment seeks to track the performance of the Bloomberg US Aggregate Total Return Index. The fund will invest at least 80% of its net assets, plus any borrowings for investment purposes, in bonds, TBA transactions representing bonds and ETFs providing exposure to such securities. The Bloomberg US Aggregate Total Return Index is designed to measure the investment grade, U.S. dollar-denominated, fixed-rate taxable bond market. It is non-diversified. | F64: {=_xll.YCI($B64,F$3)} -> BNY Mellon | G64: {=_xll.YCI($B64,G$3)} -> BNY Mellon ETF Investment Adviser, LLC | H64: {=_xll.YCI($B64,H$3)} -> Fixed Income | I64: {=_xll.YCI($B64,I$3)} -> Taxable Bond | J64: {=_xll.YCI($B64,J$3)} -> Intermediate Core Bond | ... N64: {=_xll.YCI($B64,N$3)} -> 2020-04-22 | O64: {=_xll.YCP($B64,O$3)} -> 2250762252 | P64: {=_xll.YCP($B64,P$3)} -> 0 | Q64: {=_xll.YCP($B64,Q$3)} -> 2 | R64: {=_xll.YCP($B64,R$3)} -> 1 | S64: {=_xll.YCP($B64,S$3)} -> 1.09 | T64: {=_xll.YCP($B64,T$3)} -> 0.0007271 | U64: {=_xll.YCP($B64,U$3)} -> 53 | V64: {=_xll.YCP($B64,V$3)} -> 75 | ... CF64: {=_xll.YCP($B64,CF$3)} -> 488
C65: {=_xll.YCI($B65,C$3)} | D65: {=_xll.YCI($B65,D$3)} | E65: {=_xll.YCI($B65,E$3)} | F65: {=_xll.YCI($B65,F$3)} | G65: {=_xll.YCI($B65,G$3)} | H65: {=_xll.YCI($B65,H$3)} | I65: {=_xll.YCI($B65,I$3)} | J65: {=_xll.YCI($B65,J$3)} | ... N65: {=_xll.YCI($B65,N$3)} | O65: {=_xll.YCP($B65,O$3)} | P65: {=_xll.YCP($B65,P$3)} | Q65: {=_xll.YCP($B65,Q$3)} | R65: {=_xll.YCP($B65,R$3)} | S65: {=_xll.YCP($B65,S$3)} | T65: {=_xll.YCP($B65,T$3)} | U65: {=_xll.YCP($B65,U$3)} | V65: {=_xll.YCP($B65,V$3)} | ... CF65: {=_xll.YCP($B65,CF$3)}
A66: =Securities!B11 -> M:DHRIX | C66: {=_xll.YCI($B66,C$3)} | D66: {=_xll.YCI($B66,D$3)} | E66: {=_xll.YCI($B66,E$3)} | F66: {=_xll.YCI($B66,F$3)} | G66: {=_xll.YCI($B66,G$3)} | H66: {=_xll.YCI($B66,H$3)} | I66: {=_xll.YCI($B66,I$3)} | J66: {=_xll.YCI($B66,J$3)} | ... N66: {=_xll.YCI($B66,N$3)} | O66: {=_xll.YCP($B66,O$3)} | P66: {=_xll.YCP($B66,P$3)} | Q66: {=_xll.YCP($B66,Q$3)} | R66: {=_xll.YCP($B66,R$3)} | S66: {=_xll.YCP($B66,S$3)} | T66: {=_xll.YCP($B66,T$3)} | U66: {=_xll.YCP($B66,U$3)} | V66: {=_xll.YCP($B66,V$3)} | ... CF66: {=_xll.YCP($B66,CF$3)}
B67: {=_xll.YCI(A66,B2)} -> M:DFAPX | C67: {=_xll.YCI($B67,C$3)} -> DFA Investment Grade Portfolio | D67: {=_xll.YCI($B67,D$3)} -> mutual_fund | E67: {=_xll.YCI($B67,E$3)} -> The investment seeks to maximize total returns from the universe of eligible investments. The fund seeks to achieve its investment objective through exposure to a broad portfolio of investment grade debt securities of U.S. and non-U.S. corporate and government issuers. As a non-fundamental policy, under normal circumstances, at least 80% of the Portfolio's net assets will be invested in fixed income securities considered to be investment grade quality. | F67: {=_xll.YCI($B67,F$3)} -> Dimensional Fund Advisors | G67: {=_xll.YCI($B67,G$3)} -> Dimensional Fund Advisors LP | H67: {=_xll.YCI($B67,H$3)} -> Fixed Income | I67: {=_xll.YCI($B67,I$3)} -> Taxable Bond | J67: {=_xll.YCI($B67,J$3)} -> Intermediate Core Bond | ... N67: {=_xll.YCI($B67,N$3)} -> 2011-03-07 | O67: {=_xll.YCP($B67,O$3)} -> 12642964923 | P67: {=_xll.YCP($B67,P$3)} -> 0.0019 | Q67: {=_xll.YCP($B67,Q$3)} -> 15 | R67: {=_xll.YCP($B67,R$3)} -> 11 | S67: {=_xll.YCP($B67,S$3)} -> 15.41 | T67: {=_xll.YCP($B67,T$3)} -> ERR: INVALID CALC | U67: {=_xll.YCP($B67,U$3)} -> 28 | V67: {=_xll.YCP($B67,V$3)} -> 27 | ... CF67: {=_xll.YCP($B67,CF$3)} -> 488
B68: M:BAGIX | C68: {=_xll.YCI($B68,C$3)} -> Baird Aggregate Bond Fund Institutional | D68: {=_xll.YCI($B68,D$3)} -> mutual_fund | E68: {=_xll.YCI($B68,E$3)} -> The investment seeks an annual rate of total return, before fund expenses, greater than the annual rate of total return of the Bloomberg U.S. Aggregate Index. The fund normally invests at least 80% of its net assets in the following types of U.S. dollar‑denominated debt obligations: U.S. government and other public‑sector entities; asset‑backed and mortgage‑backed obligations of U.S. and foreign issuers; corporate debt of U.S. and foreign issuers. | F68: {=_xll.YCI($B68,F$3)} -> Baird | G68: {=_xll.YCI($B68,G$3)} -> Robert W. Baird & Co. Incorporated | H68: {=_xll.YCI($B68,H$3)} -> Fixed Income | I68: {=_xll.YCI($B68,I$3)} -> Taxable Bond | J68: {=_xll.YCI($B68,J$3)} -> Intermediate Core Bond | ... N68: {=_xll.YCI($B68,N$3)} -> 2000-09-29 | O68: {=_xll.YCP($B68,O$3)} -> 56602334036 | P68: {=_xll.YCP($B68,P$3)} -> 0.003 | Q68: {=_xll.YCP($B68,Q$3)} -> 33 | R68: {=_xll.YCP($B68,R$3)} -> 18 | S68: {=_xll.YCP($B68,S$3)} -> 25.85 | T68: {=_xll.YCP($B68,T$3)} -> ERR: INVALID CALC | U68: {=_xll.YCP($B68,U$3)} -> 20 | V68: {=_xll.YCP($B68,V$3)} -> 3 | ... CF68: {=_xll.YCP($B68,CF$3)} -> 488
B69: M:VBMPX | C69: {=_xll.YCI($B69,C$3)} -> Vanguard Total Bond Market Index Fund Inst Plus | D69: {=_xll.YCI($B69,D$3)} -> mutual_fund | E69: {=_xll.YCI($B69,E$3)} -> The investment seeks to track the performance of the Bloomberg U.S. Aggregate Float Adjusted Index. This index measures the performance of a wide spectrum of public, investment-grade, taxable, fixed income securities in the United States-including government, corporate, and international dollar-denominated bonds, as well as mortgage-backed and asset-backed securities-all with maturities of more than 1 year. All of the fund's investments will be selected through the sampling process, and at least 80% of its assets will be invested in bonds held in the index. | F69: {=_xll.YCI($B69,F$3)} -> Vanguard | G69: {=_xll.YCI($B69,G$3)} -> Vanguard Group, Inc. (via Vanguard Capital Mgmt) | H69: {=_xll.YCI($B69,H$3)} -> Fixed Income | I69: {=_xll.YCI($B69,I$3)} -> Taxable Bond | J69: {=_xll.YCI($B69,J$3)} -> Intermediate Core Bond | ... N69: {=_xll.YCI($B69,N$3)} -> 1995-09-18 | O69: {=_xll.YCP($B69,O$3)} -> 35813762820 | P69: {=_xll.YCP($B69,P$3)} -> 0.0002 | Q69: {=_xll.YCP($B69,Q$3)} -> 5 | R69: {=_xll.YCP($B69,R$3)} -> 3 | S69: {=_xll.YCP($B69,S$3)} -> 13.45 | T69: {=_xll.YCP($B69,T$3)} -> ERR: INVALID CALC | U69: {=_xll.YCP($B69,U$3)} -> 54 | V69: {=_xll.YCP($B69,V$3)} -> 52 | ... CF69: {=_xll.YCP($B69,CF$3)} -> 488
B70: M:TIUSX | C70: {=_xll.YCI($B70,C$3)} -> John Hancock Investment Grade Bond Fund I | D70: {=_xll.YCI($B70,D$3)} -> mutual_fund | E70: {=_xll.YCI($B70,E$3)} -> The investment seeks a high level of current income consistent with preservation of capital and maintenance of liquidity. Under normal market conditions, the fund invests at least 80% of its net assets (plus any borrowings for investment purposes) in investment-grade bonds (securities rated from AAA to BBB). These may include, but are not limited to, corporate bonds and debentures, mortgage-backed and asset-backed securities, U.S. government and agency securities, and U.S. dollar-denominated securities of foreign governments and corporations. | F70: {=_xll.YCI($B70,F$3)} -> John Hancock | G70: {=_xll.YCI($B70,G$3)} -> John Hancock Investment Management LLC | H70: {=_xll.YCI($B70,H$3)} -> Fixed Income | I70: {=_xll.YCI($B70,I$3)} -> Taxable Bond | J70: {=_xll.YCI($B70,J$3)} -> Intermediate Core Bond | ... N70: {=_xll.YCI($B70,N$3)} -> 1991-12-31 | O70: {=_xll.YCP($B70,O$3)} -> 2487648411 | P70: {=_xll.YCP($B70,P$3)} -> 0.0049 | Q70: {=_xll.YCP($B70,Q$3)} -> 61 | R70: {=_xll.YCP($B70,R$3)} -> 50 | S70: {=_xll.YCP($B70,S$3)} -> 28.6 | T70: {=_xll.YCP($B70,T$3)} -> ERR: INVALID CALC | U70: {=_xll.YCP($B70,U$3)} -> 30 | V70: {=_xll.YCP($B70,V$3)} -> 30 | ... CF70: {=_xll.YCP($B70,CF$3)} -> 488
B71: M:VTBNX | C71: {=_xll.YCI($B71,C$3)} -> Vanguard Total Bond Market II Index Fund Inst | D71: {=_xll.YCI($B71,D$3)} -> mutual_fund | E71: {=_xll.YCI($B71,E$3)} -> The investment seeks to track the performance of the Bloomberg U.S. Aggregate Float Adjusted Index. The index measures the performance of a wide spectrum of public, investment-grade, taxable bonds in the U.S. including government, corporate, and international dollar-denominated bonds, as well as mortgage-backed and asset-backed securities all with maturities of more than 1 year. It invests at least 80% of its net assets, plus the amount of any borrowings for investment purposes, in the bonds that make up the index and in securities that the advisor determines have substantially identical economic characteristics to the securities that make up the index. | F71: {=_xll.YCI($B71,F$3)} -> Vanguard | G71: {=_xll.YCI($B71,G$3)} -> Vanguard Group, Inc. (via Vanguard Capital Mgmt) | H71: {=_xll.YCI($B71,H$3)} -> Fixed Income | I71: {=_xll.YCI($B71,I$3)} -> Taxable Bond | J71: {=_xll.YCI($B71,J$3)} -> Intermediate Core Bond | ... N71: {=_xll.YCI($B71,N$3)} -> 2009-02-17 | O71: {=_xll.YCP($B71,O$3)} -> 207251115142 | P71: {=_xll.YCP($B71,P$3)} -> 0.0002 | Q71: {=_xll.YCP($B71,Q$3)} -> 5 | R71: {=_xll.YCP($B71,R$3)} -> 3 | S71: {=_xll.YCP($B71,S$3)} -> 16.51 | T71: {=_xll.YCP($B71,T$3)} -> ERR: INVALID CALC | U71: {=_xll.YCP($B71,U$3)} -> 62 | V71: {=_xll.YCP($B71,V$3)} -> 65 | ... CF71: {=_xll.YCP($B71,CF$3)} -> 488
C72: {=_xll.YCI($B72,C$3)} | D72: {=_xll.YCI($B72,D$3)} | E72: {=_xll.YCI($B72,E$3)} | F72: {=_xll.YCI($B72,F$3)} | G72: {=_xll.YCI($B72,G$3)} | H72: {=_xll.YCI($B72,H$3)} | I72: {=_xll.YCI($B72,I$3)} | J72: {=_xll.YCI($B72,J$3)} | ... N72: {=_xll.YCI($B72,N$3)} | O72: {=_xll.YCP($B72,O$3)} | P72: {=_xll.YCP($B72,P$3)} | Q72: {=_xll.YCP($B72,Q$3)} | R72: {=_xll.YCP($B72,R$3)} | S72: {=_xll.YCP($B72,S$3)} | T72: {=_xll.YCP($B72,T$3)} | U72: {=_xll.YCP($B72,U$3)} | V72: {=_xll.YCP($B72,V$3)} | ... CF72: {=_xll.YCP($B72,CF$3)}
A73: =Securities!B12 -> M:EICOX | C73: {=_xll.YCI($B73,C$3)} | D73: {=_xll.YCI($B73,D$3)} | E73: {=_xll.YCI($B73,E$3)} | F73: {=_xll.YCI($B73,F$3)} | G73: {=_xll.YCI($B73,G$3)} | H73: {=_xll.YCI($B73,H$3)} | I73: {=_xll.YCI($B73,I$3)} | J73: {=_xll.YCI($B73,J$3)} | ... N73: {=_xll.YCI($B73,N$3)} | O73: {=_xll.YCP($B73,O$3)} | P73: {=_xll.YCP($B73,P$3)} | Q73: {=_xll.YCP($B73,Q$3)} | R73: {=_xll.YCP($B73,R$3)} | S73: {=_xll.YCP($B73,S$3)} | T73: {=_xll.YCP($B73,T$3)} | U73: {=_xll.YCP($B73,U$3)} | V73: {=_xll.YCP($B73,V$3)} | ... CF73: {=_xll.YCP($B73,CF$3)}
B74: {=_xll.YCI(A73,B2)} -> M:FZAEX | C74: {=_xll.YCI($B74,C$3)} -> Fidelity Advisor Focused Emerging Markets Fund Z | D74: {=_xll.YCI($B74,D$3)} -> mutual_fund | E74: {=_xll.YCI($B74,E$3)} -> The investment seeks capital appreciation. The fund normally invests at least 80% of assets in securities of issuers in emerging markets and other investments that are tied economically to emerging markets. It invests primarily in common stocks. The fund invests in 30 to 70 stocks. The advisor allocates investments across different emerging markets countries. | F74: {=_xll.YCI($B74,F$3)} -> Fidelity Investments | G74: {=_xll.YCI($B74,G$3)} -> Fidelity Management & Research Company LLC | H74: {=_xll.YCI($B74,H$3)} -> Equity | I74: {=_xll.YCI($B74,I$3)} -> International Equity | J74: {=_xll.YCI($B74,J$3)} -> Diversified Emerging Mkts | ... N74: {=_xll.YCI($B74,N$3)} -> 2013-08-13 | O74: {=_xll.YCP($B74,O$3)} -> 5983981234 | P74: {=_xll.YCP($B74,P$3)} -> 0.008 | Q74: {=_xll.YCP($B74,Q$3)} -> 33 | R74: {=_xll.YCP($B74,R$3)} -> 26 | S74: {=_xll.YCP($B74,S$3)} -> 7.44 | T74: {=_xll.YCP($B74,T$3)} -> ERR: INVALID CALC | U74: {=_xll.YCP($B74,U$3)} -> 15 | V74: {=_xll.YCP($B74,V$3)} -> 15 | ... CF74: {=_xll.YCP($B74,CF$3)} -> 597
B75: M:CEFIX | C75: {=_xll.YCI($B75,C$3)} -> Calvert Emerging Markets Advancement Fund I | D75: {=_xll.YCI($B75,D$3)} -> mutual_fund | E75: {=_xll.YCI($B75,E$3)} -> The investment seeks total return. Under normal market conditions, the fund will invest at least 80% of its net assets (plus any borrowings for investment purposes) in equity securities issued by companies located in emerging market countries. Companies located in emerging market countries are defined as those companies tied economically to countries included in the Calvert Emerging Markets Responsible Index. | F75: {=_xll.YCI($B75,F$3)} -> Calvert Research and Management | G75: {=_xll.YCI($B75,G$3)} -> Calvert Research and Management | H75: {=_xll.YCI($B75,H$3)} -> Equity | I75: {=_xll.YCI($B75,I$3)} -> International Equity | J75: {=_xll.YCI($B75,J$3)} -> Diversified Emerging Mkts | ... N75: {=_xll.YCI($B75,N$3)} -> 2019-10-01 | O75: {=_xll.YCP($B75,O$3)} -> 247346372 | P75: {=_xll.YCP($B75,P$3)} -> 0.0095 | Q75: {=_xll.YCP($B75,Q$3)} -> 45 | R75: {=_xll.YCP($B75,R$3)} -> 40 | S75: {=_xll.YCP($B75,S$3)} -> 3.42 | T75: {=_xll.YCP($B75,T$3)} -> ERR: INVALID CALC | U75: {=_xll.YCP($B75,U$3)} -> 15 | V75: {=_xll.YCP($B75,V$3)} -> 15 | ... CF75: {=_xll.YCP($B75,CF$3)} -> 597
B76: M:CEMFX | C76: {=_xll.YCI($B76,C$3)} -> Cullen Emerging Markets High Dividend Fund I | D76: {=_xll.YCI($B76,D$3)} -> mutual_fund | E76: {=_xll.YCI($B76,E$3)} -> The investment seeks current income and long-term capital appreciation. The fund invests at least 80% of its net assets, plus borrowings for investment purposes, in high-dividend paying securities of companies across all capitalizations that are organized in, maintain at least 50% of their assets in, or derive at least 50% of their revenues from, emerging market countries. As a point of comparison, a high dividend paying common stock that the fund would invest in would generally have a dividend yield greater than the average dividend yield of the equity securities in the MSCI Emerging Markets Index. | F76: {=_xll.YCI($B76,F$3)} -> Cullen Funds Trust | G76: {=_xll.YCI($B76,G$3)} -> Cullen Capital Management, LLC | H76: {=_xll.YCI($B76,H$3)} -> Equity | I76: {=_xll.YCI($B76,I$3)} -> International Equity | J76: {=_xll.YCI($B76,J$3)} -> Diversified Emerging Mkts | ... N76: {=_xll.YCI($B76,N$3)} -> 2012-08-31 | O76: {=_xll.YCP($B76,O$3)} -> 2212833211 | P76: {=_xll.YCP($B76,P$3)} -> 0.01 | Q76: {=_xll.YCP($B76,Q$3)} -> 53 | R76: {=_xll.YCP($B76,R$3)} -> 75 | S76: {=_xll.YCP($B76,S$3)} -> 13.93 | T76: {=_xll.YCP($B76,T$3)} -> ERR: INVALID CALC | U76: {=_xll.YCP($B76,U$3)} -> 12 | V76: {=_xll.YCP($B76,V$3)} -> 12 | ... CF76: {=_xll.YCP($B76,CF$3)} -> 96
B77: M:AEMZX | C77: {=_xll.YCI($B77,C$3)} -> Acadian Emerging Markets Portfolio I | D77: {=_xll.YCI($B77,D$3)} -> mutual_fund | E77: {=_xll.YCI($B77,E$3)} -> The investment seeks long-term capital appreciation by investing primarily in common stocks of emerging market country issuers. The fund will invest primarily in common stocks but also may invest in other types of equity securities, including preferred stock. Under normal circumstances, it invests at least 80% of its net assets, plus any borrowings for investment purposes, in equity securities of issuers. The fund may also invest in securities of issuers located in industrialized countries. | F77: {=_xll.YCI($B77,F$3)} -> Acadian Funds | G77: {=_xll.YCI($B77,G$3)} -> Acadian Asset Management LLC | H77: {=_xll.YCI($B77,H$3)} -> Equity | I77: {=_xll.YCI($B77,I$3)} -> International Equity | J77: {=_xll.YCI($B77,J$3)} -> Diversified Emerging Mkts | ... N77: {=_xll.YCI($B77,N$3)} -> 2016-10-31 | O77: {=_xll.YCP($B77,O$3)} -> 1137464988 | P77: {=_xll.YCP($B77,P$3)} -> 0.011 | Q77: {=_xll.YCP($B77,Q$3)} -> 62 | R77: {=_xll.YCP($B77,R$3)} -> 58 | S77: {=_xll.YCP($B77,S$3)} -> 12.59 | T77: {=_xll.YCP($B77,T$3)} -> ERR: INVALID CALC | U77: {=_xll.YCP($B77,U$3)} -> 7 | V77: {=_xll.YCP($B77,V$3)} -> 6 | ... CF77: {=_xll.YCP($B77,CF$3)} -> 597
B78: M:TRFZX | C78: {=_xll.YCI($B78,C$3)} -> T Rowe Price Emerging Markets Discv Stock Fund Z | D78: {=_xll.YCI($B78,D$3)} -> mutual_fund | E78: {=_xll.YCI($B78,E$3)} -> The investment seeks long-term growth of capital. The fund normally invests at least 80% of its net assets (plus any borrowings for investment purposes) in stocks issued by companies in emerging markets. The fund relies on MSCI Inc., a third-party provider of benchmark indexes and data services, or another unaffiliated data provider to determine the country assigned to a security and whether the country is considered an emerging market. The Advisor expects to primarily invest in common stocks of companies located (or with primary operations) in emerging markets (which may include frontier markets) in Asia, Latin America, Europe, Africa, and the Middle East. | F78: {=_xll.YCI($B78,F$3)} -> T. Rowe Price | G78: {=_xll.YCI($B78,G$3)} -> T. Rowe Price Associates, Inc. | H78: {=_xll.YCI($B78,H$3)} -> Equity | I78: {=_xll.YCI($B78,I$3)} -> International Equity | J78: {=_xll.YCI($B78,J$3)} -> Diversified Emerging Mkts | ... N78: {=_xll.YCI($B78,N$3)} -> 2020-03-16 | O78: {=_xll.YCP($B78,O$3)} -> 4864631310 | P78: {=_xll.YCP($B78,P$3)} -> 0 | Q78: {=_xll.YCP($B78,Q$3)} -> 1 | R78: {=_xll.YCP($B78,R$3)} -> 1 | S78: {=_xll.YCP($B78,S$3)} -> 10.89 | T78: {=_xll.YCP($B78,T$3)} -> ERR: INVALID CALC | U78: {=_xll.YCP($B78,U$3)} -> 15 | V78: {=_xll.YCP($B78,V$3)} -> 11 | ... CF78: {=_xll.YCP($B78,CF$3)} -> 597
C79: {=_xll.YCI($B79,C$3)} | D79: {=_xll.YCI($B79,D$3)} | E79: {=_xll.YCI($B79,E$3)} | F79: {=_xll.YCI($B79,F$3)} | G79: {=_xll.YCI($B79,G$3)} | H79: {=_xll.YCI($B79,H$3)} | I79: {=_xll.YCI($B79,I$3)} | J79: {=_xll.YCI($B79,J$3)} | ... N79: {=_xll.YCI($B79,N$3)} | O79: {=_xll.YCP($B79,O$3)} | P79: {=_xll.YCP($B79,P$3)} | Q79: {=_xll.YCP($B79,Q$3)} | R79: {=_xll.YCP($B79,R$3)} | S79: {=_xll.YCP($B79,S$3)} | T79: {=_xll.YCP($B79,T$3)} | U79: {=_xll.YCP($B79,U$3)} | V79: {=_xll.YCP($B79,V$3)} | ... CF79: {=_xll.YCP($B79,CF$3)}
A80: =Securities!B13 -> EMMF | C80: {=_xll.YCI($B80,C$3)} | D80: {=_xll.YCI($B80,D$3)} | E80: {=_xll.YCI($B80,E$3)} | F80: {=_xll.YCI($B80,F$3)} | G80: {=_xll.YCI($B80,G$3)} | H80: {=_xll.YCI($B80,H$3)} | I80: {=_xll.YCI($B80,I$3)} | J80: {=_xll.YCI($B80,J$3)} | ... N80: {=_xll.YCI($B80,N$3)} | O80: {=_xll.YCP($B80,O$3)} | P80: {=_xll.YCP($B80,P$3)} | Q80: {=_xll.YCP($B80,Q$3)} | R80: {=_xll.YCP($B80,R$3)} | S80: {=_xll.YCP($B80,S$3)} | T80: {=_xll.YCP($B80,T$3)} | U80: {=_xll.YCP($B80,U$3)} | V80: {=_xll.YCP($B80,V$3)} | ... CF80: {=_xll.YCP($B80,CF$3)}
B81: {=_xll.YCI(A80,B2)} -> DGRE | C81: {=_xll.YCI($B81,C$3)} -> WisdomTree Emerging Markets Quality Dividend Gro | D81: {=_xll.YCI($B81,D$3)} -> etf | E81: {=_xll.YCI($B81,E$3)} -> The investment seeks income and capital appreciation. The fund seeks to achieve its investment objective by investing primarily in emerging market dividend-paying common stocks with growth characteristics. The adviser, using a disciplined model-based process focused on a long-term approach to investing, seeks to identify dividend-paying companies with strong corporate profitability and sustainable growth characteristics. The fund is non-diversified. | F81: {=_xll.YCI($B81,F$3)} -> WisdomTree | G81: {=_xll.YCI($B81,G$3)} -> WisdomTree Asset Management Inc | H81: {=_xll.YCI($B81,H$3)} -> Equity | I81: {=_xll.YCI($B81,I$3)} -> International Equity | J81: {=_xll.YCI($B81,J$3)} -> Diversified Emerging Mkts | ... N81: {=_xll.YCI($B81,N$3)} -> 2013-08-01 | O81: {=_xll.YCP($B81,O$3)} -> 148172153 | P81: {=_xll.YCP($B81,P$3)} -> 0.0032 | Q81: {=_xll.YCP($B81,Q$3)} -> 16 | R81: {=_xll.YCP($B81,R$3)} -> 12 | S81: {=_xll.YCP($B81,S$3)} -> 5.77 | T81: {=_xll.YCP($B81,T$3)} -> -0.01356157 | U81: {=_xll.YCP($B81,U$3)} -> 37 | V81: {=_xll.YCP($B81,V$3)} -> 27 | ... CF81: {=_xll.YCP($B81,CF$3)} -> 96
B82: NUEM | C82: {=_xll.YCI($B82,C$3)} -> Nuveen ESG Emerging Markets Equity ETF | D82: {=_xll.YCI($B82,D$3)} -> etf | E82: {=_xll.YCI($B82,E$3)} -> The investment seeks to track the investment results, before fees and expenses, of the TIAA ESG Emerging Markets Equity Index (the "index"). In seeking to track the investment results of the index, the advisor attempts to replicate the index by investing all, or substantially all, of its assets in the securities represented in the index in approximately the same proportions as the index. The index identifies equity securities from the base index that satisfy certain ESG criteria, based on ESG performance data collected by MSCI ESG Research, Inc. | F82: {=_xll.YCI($B82,F$3)} -> Nuveen | G82: {=_xll.YCI($B82,G$3)} -> Nuveen Fund Advisors, LLC. | H82: {=_xll.YCI($B82,H$3)} -> Equity | I82: {=_xll.YCI($B82,I$3)} -> International Equity | J82: {=_xll.YCI($B82,J$3)} -> Diversified Emerging Mkts | ... N82: {=_xll.YCI($B82,N$3)} -> 2017-06-06 | O82: {=_xll.YCP($B82,O$3)} -> 411643491 | P82: {=_xll.YCP($B82,P$3)} -> 0.0036 | Q82: {=_xll.YCP($B82,Q$3)} -> 18 | R82: {=_xll.YCP($B82,R$3)} -> 10 | S82: {=_xll.YCP($B82,S$3)} -> 9.16 | T82: {=_xll.YCP($B82,T$3)} -> -0.01688333 | U82: {=_xll.YCP($B82,U$3)} -> 72 | V82: {=_xll.YCP($B82,V$3)} -> 73 | ... CF82: {=_xll.YCP($B82,CF$3)} -> 597
B83: DEHP | C83: {=_xll.YCI($B83,C$3)} -> DFA Dimensional Emerging Mkts High Proftblty ETF | D83: {=_xll.YCI($B83,D$3)} -> etf | E83: {=_xll.YCI($B83,E$3)} -> The investment seeks to achieve long-term capital appreciation. The Portfolio is designed to purchase securities of large companies associated with emerging markets that the Advisor determines to have high profitability relative to other large companies in the same country or region at the time of purchase. The Advisor intends to purchase securities of large companies that are associated with emerging markets, which may include frontier markets (emerging market countries in an earlier stage of development). | F83: {=_xll.YCI($B83,F$3)} -> Dimensional Fund Advisors | G83: {=_xll.YCI($B83,G$3)} -> Dimensional Fund Advisors LP | H83: {=_xll.YCI($B83,H$3)} -> Equity | I83: {=_xll.YCI($B83,I$3)} -> International Equity | J83: {=_xll.YCI($B83,J$3)} -> Diversified Emerging Mkts | ... N83: {=_xll.YCI($B83,N$3)} -> 2022-04-26 | O83: {=_xll.YCP($B83,O$3)} -> 446353354 | P83: {=_xll.YCP($B83,P$3)} -> 0.0041 | Q83: {=_xll.YCP($B83,Q$3)} -> 20 | R83: {=_xll.YCP($B83,R$3)} -> 12 | S83: {=_xll.YCP($B83,S$3)} -> 4.27 | T83: {=_xll.YCP($B83,T$3)} -> -0.01741904 | U83: {=_xll.YCP($B83,U$3)} -> 47 | V83: {=_xll.YCP($B83,V$3)} -> 38 | ... CF83: {=_xll.YCP($B83,CF$3)} -> 597
B84: TLTE | C84: {=_xll.YCI($B84,C$3)} -> Northern Trust Morningstar Emg Mkts Fctr Tilt ETF | D84: {=_xll.YCI($B84,D$3)} -> etf | E84: {=_xll.YCI($B84,E$3)} -> The investment seeks investment results that correspond generally to the price and yield performance, before fees and expenses, of the Morningstar® Emerging Markets Factor Tilt IndexSM. The underlying index is designed to reflect the performance of emerging equity markets with increased exposure to size and value factors relative to the parent index, a float-adjusted market-capitalization weighted index of companies incorporated in emerging-market countries. Under normal circumstances, the fund will invest at least 80% of its total assets in the securities of the underlying index and in ADRs and GDRs based on the securities in the underlying index. | F84: {=_xll.YCI($B84,F$3)} -> Flexshares Trust | G84: {=_xll.YCI($B84,G$3)} -> Northern Trust Investments Inc | H84: {=_xll.YCI($B84,H$3)} -> Equity | I84: {=_xll.YCI($B84,I$3)} -> International Equity | J84: {=_xll.YCI($B84,J$3)} -> Diversified Emerging Mkts | ... N84: {=_xll.YCI($B84,N$3)} -> 2012-09-25 | O84: {=_xll.YCP($B84,O$3)} -> 350455972 | P84: {=_xll.YCP($B84,P$3)} -> 0.0057 | Q84: {=_xll.YCP($B84,Q$3)} -> 23 | R84: {=_xll.YCP($B84,R$3)} -> 16 | S84: {=_xll.YCP($B84,S$3)} -> 12.76 | T84: {=_xll.YCP($B84,T$3)} -> -0.01385484 | U84: {=_xll.YCP($B84,U$3)} -> 66 | V84: {=_xll.YCP($B84,V$3)} -> 63 | ... CF84: {=_xll.YCP($B84,CF$3)} -> 597
B85: PIE | C85: {=_xll.YCI($B85,C$3)} -> Invesco Dorsey Wright Emerging Markets Mo ETF | D85: {=_xll.YCI($B85,D$3)} -> etf | E85: {=_xll.YCI($B85,E$3)} -> The investment seeks to track the investment results (before fees and expenses) of the Dorsey Wright® Emerging Markets Technical Leaders Index (the "underlying index"). The fund will invest at least 90% of its total assets in the securities that comprise the underlying index. The underlying index is comprised of equity securities of large capitalization companies based in countries classified as emerging markets. | F85: {=_xll.YCI($B85,F$3)} -> Invesco | G85: {=_xll.YCI($B85,G$3)} -> Invesco Capital Management LLC | H85: {=_xll.YCI($B85,H$3)} -> Equity | I85: {=_xll.YCI($B85,I$3)} -> International Equity | J85: {=_xll.YCI($B85,J$3)} -> Diversified Emerging Mkts | ... N85: {=_xll.YCI($B85,N$3)} -> 2007-12-27 | O85: {=_xll.YCP($B85,O$3)} -> 246632994 | P85: {=_xll.YCP($B85,P$3)} -> 0.009 | Q85: {=_xll.YCP($B85,Q$3)} -> 41 | R85: {=_xll.YCP($B85,R$3)} -> 35 | S85: {=_xll.YCP($B85,S$3)} -> 18.6 | T85: {=_xll.YCP($B85,T$3)} -> 0.0006174 | U85: {=_xll.YCP($B85,U$3)} -> 75 | V85: {=_xll.YCP($B85,V$3)} -> 63 | ... CF85: {=_xll.YCP($B85,CF$3)} -> 597
C86: {=_xll.YCI($B86,C$3)} | D86: {=_xll.YCI($B86,D$3)} | E86: {=_xll.YCI($B86,E$3)} | F86: {=_xll.YCI($B86,F$3)} | G86: {=_xll.YCI($B86,G$3)} | H86: {=_xll.YCI($B86,H$3)} | I86: {=_xll.YCI($B86,I$3)} | J86: {=_xll.YCI($B86,J$3)} | ... N86: {=_xll.YCI($B86,N$3)} | O86: {=_xll.YCP($B86,O$3)} | P86: {=_xll.YCP($B86,P$3)} | Q86: {=_xll.YCP($B86,Q$3)} | R86: {=_xll.YCP($B86,R$3)} | S86: {=_xll.YCP($B86,S$3)} | T86: {=_xll.YCP($B86,T$3)} | U86: {=_xll.YCP($B86,U$3)} | V86: {=_xll.YCP($B86,V$3)} | ... CF86: {=_xll.YCP($B86,CF$3)}
A87: =Securities!B14 -> EYLD | C87: {=_xll.YCI($B87,C$3)} | D87: {=_xll.YCI($B87,D$3)} | E87: {=_xll.YCI($B87,E$3)} | F87: {=_xll.YCI($B87,F$3)} | G87: {=_xll.YCI($B87,G$3)} | H87: {=_xll.YCI($B87,H$3)} | I87: {=_xll.YCI($B87,I$3)} | J87: {=_xll.YCI($B87,J$3)} | ... N87: {=_xll.YCI($B87,N$3)} | O87: {=_xll.YCP($B87,O$3)} | P87: {=_xll.YCP($B87,P$3)} | Q87: {=_xll.YCP($B87,Q$3)} | R87: {=_xll.YCP($B87,R$3)} | S87: {=_xll.YCP($B87,S$3)} | T87: {=_xll.YCP($B87,T$3)} | U87: {=_xll.YCP($B87,U$3)} | V87: {=_xll.YCP($B87,V$3)} | ... CF87: {=_xll.YCP($B87,CF$3)}
B88: {=_xll.YCI(A87,B2)} -> FEM | C88: {=_xll.YCI($B88,C$3)} -> First Trust Emerging Markets AlphaDEX Fund | D88: {=_xll.YCI($B88,D$3)} -> etf | E88: {=_xll.YCI($B88,E$3)} -> The investment seeks investment results that correspond generally to the price and yield (before the fund's fees and expenses) of an equity index called the NASDAQ AlphaDEX® Emerging Markets Index. The fund will normally invest at least 90% of its net assets (including investment borrowings) in the securities that comprise the index. The index is designed to select stocks from the NASDAQ Emerging Markets Index (the "base index") that may generate positive alpha, or risk-adjusted returns, relative to traditional indices through the use of the AlphaDEX® selection methodology. | F88: {=_xll.YCI($B88,F$3)} -> First Trust | G88: {=_xll.YCI($B88,G$3)} -> First Trust Advisors L.P. | H88: {=_xll.YCI($B88,H$3)} -> Equity | I88: {=_xll.YCI($B88,I$3)} -> International Equity | J88: {=_xll.YCI($B88,J$3)} -> Diversified Emerging Mkts | ... N88: {=_xll.YCI($B88,N$3)} -> 2011-04-18 | O88: {=_xll.YCP($B88,O$3)} -> 798032826 | P88: {=_xll.YCP($B88,P$3)} -> 0.008 | Q88: {=_xll.YCP($B88,Q$3)} -> 33 | R88: {=_xll.YCP($B88,R$3)} -> 26 | S88: {=_xll.YCP($B88,S$3)} -> 15.3 | T88: {=_xll.YCP($B88,T$3)} -> -0.00356043 | U88: {=_xll.YCP($B88,U$3)} -> 67 | V88: {=_xll.YCP($B88,V$3)} -> 79 | ... CF88: {=_xll.YCP($B88,CF$3)} -> 597
B89: EDIV | C89: {=_xll.YCI($B89,C$3)} -> State Street SPDR S&P Emerging Markets Div ETF | D89: {=_xll.YCI($B89,D$3)} -> etf | E89: {=_xll.YCI($B89,E$3)} -> The investment seeks investment results that, before fees and expenses, correspond generally to the total return performance of the S&P Emerging Markets Dividend Opportunities Index. The fund generally invests substantially all, but at least 80%, of its total assets in the securities comprising the index and in depositary receipts based on securities comprising the index. The index is designed to measure the performance of 100 high-yielding emerging market common stocks. | F89: {=_xll.YCI($B89,F$3)} -> State Street Investment Management | G89: {=_xll.YCI($B89,G$3)} -> SSIM Funds Management Inc | H89: {=_xll.YCI($B89,H$3)} -> Equity | I89: {=_xll.YCI($B89,I$3)} -> International Equity | J89: {=_xll.YCI($B89,J$3)} -> Diversified Emerging Mkts | ... N89: {=_xll.YCI($B89,N$3)} -> 2011-02-23 | O89: {=_xll.YCP($B89,O$3)} -> 1225473045 | P89: {=_xll.YCP($B89,P$3)} -> 0.0049 | Q89: {=_xll.YCP($B89,Q$3)} -> 22 | R89: {=_xll.YCP($B89,R$3)} -> 25 | S89: {=_xll.YCP($B89,S$3)} -> 11.51 | T89: {=_xll.YCP($B89,T$3)} -> -0.00224569 | U89: {=_xll.YCP($B89,U$3)} -> 24 | V89: {=_xll.YCP($B89,V$3)} -> 77 | ... CF89: {=_xll.YCP($B89,CF$3)} -> 96
B90: DGS | C90: {=_xll.YCI($B90,C$3)} -> WisdomTree Emerging Markets SmallCap Dividend Fund | D90: {=_xll.YCI($B90,D$3)} -> etf | E90: {=_xll.YCI($B90,E$3)} -> The investment seeks to track the price and yield performance, before fees and expenses, of the WisdomTree Emerging Markets SmallCap Dividend Index. Under normal circumstances, at least 95% of the fund's total assets (exclusive of collateral held from securities lending) will be invested in constituent securities of the index and investments that have economic characteristics that are substantially identical to the economic characteristics of such constituent securities. The index is a fundamentally weighted index that is comprised of small cap common stocks selected from the WisdomTree Emerging Markets Dividend Index. The fund is non-diversified. | F90: {=_xll.YCI($B90,F$3)} -> WisdomTree | G90: {=_xll.YCI($B90,G$3)} -> WisdomTree Asset Management Inc | H90: {=_xll.YCI($B90,H$3)} -> Equity | I90: {=_xll.YCI($B90,I$3)} -> International Equity | J90: {=_xll.YCI($B90,J$3)} -> Diversified Emerging Mkts | ... N90: {=_xll.YCI($B90,N$3)} -> 2007-10-30 | O90: {=_xll.YCP($B90,O$3)} -> 1730112377 | P90: {=_xll.YCP($B90,P$3)} -> 0.0058 | Q90: {=_xll.YCP($B90,Q$3)} -> 24 | R90: {=_xll.YCP($B90,R$3)} -> 35 | S90: {=_xll.YCP($B90,S$3)} -> 5.77 | T90: {=_xll.YCP($B90,T$3)} -> -0.01031969 | U90: {=_xll.YCP($B90,U$3)} -> 87 | V90: {=_xll.YCP($B90,V$3)} -> 97 | ... CF90: {=_xll.YCP($B90,CF$3)} -> 96
B91: EMEQ | C91: {=_xll.YCI($B91,C$3)} -> Nomura Focused Emerging Markets Equity ETF | D91: {=_xll.YCI($B91,D$3)} -> etf | E91: {=_xll.YCI($B91,E$3)} -> The investment seeks to long-term capital appreciation. Under normal circumstances, the fund will invest at least 80% of its net assets, plus the amount of any borrowings for investment purposes, in equity securities of emerging markets issuers. The fund invests primarily in a broad range of equity securities of companies located in emerging market countries and may invest in companies of any size. The fund is non-diversified. | F91: {=_xll.YCI($B91,F$3)} -> Nomura | G91: {=_xll.YCI($B91,G$3)} -> Delaware Management Company | H91: {=_xll.YCI($B91,H$3)} -> Equity | I91: {=_xll.YCI($B91,I$3)} -> International Equity | J91: {=_xll.YCI($B91,J$3)} -> Diversified Emerging Mkts | ... N91: {=_xll.YCI($B91,N$3)} -> 2024-09-04 | O91: {=_xll.YCP($B91,O$3)} -> 608505690 | P91: {=_xll.YCP($B91,P$3)} -> 0.0085 | Q91: {=_xll.YCP($B91,Q$3)} -> 35 | R91: {=_xll.YCP($B91,R$3)} -> 29 | S91: {=_xll.YCP($B91,S$3)} -> 1.91 | T91: {=_xll.YCP($B91,T$3)} -> -0.02471806 | U91: {=_xll.YCP($B91,U$3)} -> ERR: NO DATA | V91: {=_xll.YCP($B91,V$3)} -> ERR: NO DATA | ... CF91: {=_xll.YCP($B91,CF$3)} -> 597
B92: SEEM | C92: {=_xll.YCI($B92,C$3)} -> SEI Select Emerging Markets Equity ETF | D92: {=_xll.YCI($B92,D$3)} -> etf | E92: {=_xll.YCI($B92,E$3)} -> The investment seeks long-term capital appreciation. Under normal circumstances, the fund will invest at least 80% of its net assets (plus the amount of any borrowings for investment purposes) in equity securities of emerging market issuers. The fund normally maintains investments in at least six emerging market countries, however, it may invest a substantial amount of its assets in issuers located in a single country or a limited number of countries. | F92: {=_xll.YCI($B92,F$3)} -> SEI Investments Co | G92: {=_xll.YCI($B92,G$3)} -> SEI Investments Management Corp | H92: {=_xll.YCI($B92,H$3)} -> Equity | I92: {=_xll.YCI($B92,I$3)} -> International Equity | J92: {=_xll.YCI($B92,J$3)} -> Diversified Emerging Mkts | ... N92: {=_xll.YCI($B92,N$3)} -> 2024-10-08 | O92: {=_xll.YCP($B92,O$3)} -> 646279085 | P92: {=_xll.YCP($B92,P$3)} -> 0.006 | Q92: {=_xll.YCP($B92,Q$3)} -> 24 | R92: {=_xll.YCP($B92,R$3)} -> 17 | S92: {=_xll.YCP($B92,S$3)} -> 1.81 | T92: {=_xll.YCP($B92,T$3)} -> -0.00889406 | U92: {=_xll.YCP($B92,U$3)} -> ERR: NO DATA | V92: {=_xll.YCP($B92,V$3)} -> ERR: NO DATA | ... CF92: {=_xll.YCP($B92,CF$3)} -> 597
C93: {=_xll.YCI($B93,C$3)} | D93: {=_xll.YCI($B93,D$3)} | E93: {=_xll.YCI($B93,E$3)} | F93: {=_xll.YCI($B93,F$3)} | G93: {=_xll.YCI($B93,G$3)} | H93: {=_xll.YCI($B93,H$3)} | I93: {=_xll.YCI($B93,I$3)} | J93: {=_xll.YCI($B93,J$3)} | ... N93: {=_xll.YCI($B93,N$3)} | O93: {=_xll.YCP($B93,O$3)} | P93: {=_xll.YCP($B93,P$3)} | Q93: {=_xll.YCP($B93,Q$3)} | R93: {=_xll.YCP($B93,R$3)} | S93: {=_xll.YCP($B93,S$3)} | T93: {=_xll.YCP($B93,T$3)} | U93: {=_xll.YCP($B93,U$3)} | V93: {=_xll.YCP($B93,V$3)} | ... CF93: {=_xll.YCP($B93,CF$3)}
A94: =Securities!B15 -> M:FAGIX | C94: {=_xll.YCI($B94,C$3)} | D94: {=_xll.YCI($B94,D$3)} | E94: {=_xll.YCI($B94,E$3)} | F94: {=_xll.YCI($B94,F$3)} | G94: {=_xll.YCI($B94,G$3)} | H94: {=_xll.YCI($B94,H$3)} | I94: {=_xll.YCI($B94,I$3)} | J94: {=_xll.YCI($B94,J$3)} | ... N94: {=_xll.YCI($B94,N$3)} | O94: {=_xll.YCP($B94,O$3)} | P94: {=_xll.YCP($B94,P$3)} | Q94: {=_xll.YCP($B94,Q$3)} | R94: {=_xll.YCP($B94,R$3)} | S94: {=_xll.YCP($B94,S$3)} | T94: {=_xll.YCP($B94,T$3)} | U94: {=_xll.YCP($B94,U$3)} | V94: {=_xll.YCP($B94,V$3)} | ... CF94: {=_xll.YCP($B94,CF$3)}
B95: {=_xll.YCI(A94,B2)} -> M:FAHCX | C95: {=_xll.YCI($B95,C$3)} -> Fidelity Advisor Capital & Income Fund I | D95: {=_xll.YCI($B95,D$3)} -> mutual_fund | E95: {=_xll.YCI($B95,E$3)} -> The investment seeks a combination of a high level of income and the potential for capital gains. The fund invests primarily in income-producing debt securities, preferred stocks, and convertible securities, with an emphasis on lower-quality debt securities. It invests in non-income producing securities, including defaulted securities and common stocks. The fund invests up to 20% of total assets in common stocks. It invests in companies in troubled or uncertain financial condition. The advisor uses fundamental analysis of each issuer's financial condition and industry position and market and economic conditions to select investments. | F95: {=_xll.YCI($B95,F$3)} -> Fidelity Investments | G95: {=_xll.YCI($B95,G$3)} -> Fidelity Management & Research Company LLC | H95: {=_xll.YCI($B95,H$3)} -> Fixed Income | I95: {=_xll.YCI($B95,I$3)} -> Taxable Bond | J95: {=_xll.YCI($B95,J$3)} -> High Yield Bond | ... N95: {=_xll.YCI($B95,N$3)} -> 1987-01-05 | O95: {=_xll.YCP($B95,O$3)} -> 1482627674 | P95: {=_xll.YCP($B95,P$3)} -> 0.0093 | Q95: {=_xll.YCP($B95,Q$3)} -> 62 | R95: {=_xll.YCP($B95,R$3)} -> 68 | S95: {=_xll.YCP($B95,S$3)} -> 6.84 | T95: {=_xll.YCP($B95,T$3)} -> ERR: INVALID CALC | U95: {=_xll.YCP($B95,U$3)} -> 2 | V95: {=_xll.YCP($B95,V$3)} -> 17 | ... CF95: {=_xll.YCP($B95,CF$3)} -> 467
B96: M:NHFIX | C96: {=_xll.YCI($B96,C$3)} -> Northern High Yield Fixed Income Fund | D96: {=_xll.YCI($B96,D$3)} -> mutual_fund | E96: {=_xll.YCI($B96,E$3)} -> The investment seeks a high level of current income. The fund will invest at least 80% of its net assets in lower quality bonds and other fixed-income securities (commonly referred to as "junk bonds"). Lower quality or below-investment grade securities are rated BB, Ba or lower by a Nationally Recognized Statistical Rating Organization (“NRSRO”), or unrated securities determined to be of comparable quality by the fund’s investment adviser. | F96: {=_xll.YCI($B96,F$3)} -> Northern Funds | G96: {=_xll.YCI($B96,G$3)} -> Shânti Asset Management | H96: {=_xll.YCI($B96,H$3)} -> Fixed Income | I96: {=_xll.YCI($B96,I$3)} -> Taxable Bond | J96: {=_xll.YCI($B96,J$3)} -> High Yield Bond | ... N96: {=_xll.YCI($B96,N$3)} -> 1998-12-31 | O96: {=_xll.YCP($B96,O$3)} -> 2090147499 | P96: {=_xll.YCP($B96,P$3)} -> 0.0061 | Q96: {=_xll.YCP($B96,Q$3)} -> 32 | R96: {=_xll.YCP($B96,R$3)} -> 31 | S96: {=_xll.YCP($B96,S$3)} -> 2 | T96: {=_xll.YCP($B96,T$3)} -> ERR: INVALID CALC | U96: {=_xll.YCP($B96,U$3)} -> 17 | V96: {=_xll.YCP($B96,V$3)} -> 11 | ... CF96: {=_xll.YCP($B96,CF$3)} -> 467
B97: M:SGYAX | C97: {=_xll.YCI($B97,C$3)} -> SEI Inst Inv High Yield Bond Fund A | D97: {=_xll.YCI($B97,D$3)} -> mutual_fund | E97: {=_xll.YCI($B97,E$3)} -> The investment seeks total return. The fund will invest at least 80% of its net assets (plus the amount of any borrowings for investment purposes) in high yield fixed income securities. It invests primarily in fixed income securities rated below investment grade, including corporate bonds and debentures, convertible and preferred securities, zero coupon obligations and tranches of collateralized debt obligations (CDOs) and collateralized loan obligations (CLOs). The fund uses a multi-manager approach, relying upon a number of Sub-Advisers with differing investment philosophies to manage portions of the fund's portfolio under the general supervision of SIMC. | F97: {=_xll.YCI($B97,F$3)} -> SEI | G97: {=_xll.YCI($B97,G$3)} -> SEI Investments Management Corp | H97: {=_xll.YCI($B97,H$3)} -> Fixed Income | I97: {=_xll.YCI($B97,I$3)} -> Taxable Bond | J97: {=_xll.YCI($B97,J$3)} -> High Yield Bond | ... N97: {=_xll.YCI($B97,N$3)} -> 2005-12-05 | O97: {=_xll.YCP($B97,O$3)} -> 2146274241 | P97: {=_xll.YCP($B97,P$3)} -> 0.0057 | Q97: {=_xll.YCP($B97,Q$3)} -> 6 | R97: {=_xll.YCP($B97,R$3)} -> 26 | S97: {=_xll.YCP($B97,S$3)} -> 20.67 | T97: {=_xll.YCP($B97,T$3)} -> ERR: INVALID CALC | U97: {=_xll.YCP($B97,U$3)} -> 24 | V97: {=_xll.YCP($B97,V$3)} -> 40 | ... CF97: {=_xll.YCP($B97,CF$3)} -> 467
B98: M:SPHIX | C98: {=_xll.YCI($B98,C$3)} -> Fidelity High Income Fund | D98: {=_xll.YCI($B98,D$3)} -> mutual_fund | E98: {=_xll.YCI($B98,E$3)} -> The investment seeks a high level of current income; growth of capital may also be considered. The fund normally invests primarily in income producing debt securities, preferred stocks, and convertible securities, with an emphasis on lower-quality debt securities. It potentially invests in non-income producing securities, including defaulted securities and common stocks. The fund invests in companies in troubled or uncertain financial condition. | F98: {=_xll.YCI($B98,F$3)} -> Fidelity Investments | G98: {=_xll.YCI($B98,G$3)} -> Fidelity Management & Research Company LLC | H98: {=_xll.YCI($B98,H$3)} -> Fixed Income | I98: {=_xll.YCI($B98,I$3)} -> Taxable Bond | J98: {=_xll.YCI($B98,J$3)} -> High Yield Bond | ... N98: {=_xll.YCI($B98,N$3)} -> 1990-08-29 | O98: {=_xll.YCP($B98,O$3)} -> 2638085729 | P98: {=_xll.YCP($B98,P$3)} -> 0.0069 | Q98: {=_xll.YCP($B98,Q$3)} -> 41 | R98: {=_xll.YCP($B98,R$3)} -> 41 | S98: {=_xll.YCP($B98,S$3)} -> 4.58 | T98: {=_xll.YCP($B98,T$3)} -> ERR: INVALID CALC | U98: {=_xll.YCP($B98,U$3)} -> 5 | V98: {=_xll.YCP($B98,V$3)} -> 3 | ... CF98: {=_xll.YCP($B98,CF$3)} -> 467
B99: M:LP40034659 | C99: {=_xll.YCI($B99,C$3)} -> JNL/PPM America High Yield Bond Fund A | D99: {=_xll.YCI($B99,D$3)} -> insurance_fund | E99: {=_xll.YCI($B99,E$3)} -> The investment seeks to maximize current income; capital appreciation is a secondary objective. The fund invests under normal circumstances at least 80% of its assets (net assets plus the amount of any borrowings made for investment purposes) in high-yield, high-risk debt securities (“junk bonds”) and related investments that are rated below investment grade (i.e., rated below BBB- or Baa3) by at least one major credit rating agency, or, if not rated by any credit rating agency, determined to be below investment-grade quality by PPM America, Inc. (“Sub-Adviser”). | F99: {=_xll.YCI($B99,F$3)} -> Jackson National | G99: {=_xll.YCI($B99,G$3)} -> Jackson National Asset Management, LLC | H99: {=_xll.YCI($B99,H$3)} -> Fixed Income | I99: {=_xll.YCI($B99,I$3)} -> Taxable Bond | J99: {=_xll.YCI($B99,J$3)} -> High Yield Bond | ... N99: {=_xll.YCI($B99,N$3)} -> ERR: NO DATA | O99: {=_xll.YCP($B99,O$3)} -> 1269580515 | P99: {=_xll.YCP($B99,P$3)} -> 0.0076 | Q99: {=_xll.YCP($B99,Q$3)} -> 51 | R99: {=_xll.YCP($B99,R$3)} -> 53 | S99: {=_xll.YCP($B99,S$3)} -> 8.26 | T99: {=_xll.YCP($B99,T$3)} -> ERR: INVALID CALC | U99: {=_xll.YCP($B99,U$3)} -> 33 | V99: {=_xll.YCP($B99,V$3)} -> 35 | ... CF99: {=_xll.YCP($B99,CF$3)} -> 467
C100: {=_xll.YCI($B100,C$3)} | D100: {=_xll.YCI($B100,D$3)} | E100: {=_xll.YCI($B100,E$3)} | F100: {=_xll.YCI($B100,F$3)} | G100: {=_xll.YCI($B100,G$3)} | H100: {=_xll.YCI($B100,H$3)} | I100: {=_xll.YCI($B100,I$3)} | J100: {=_xll.YCI($B100,J$3)} | ... N100: {=_xll.YCI($B100,N$3)} | O100: {=_xll.YCP($B100,O$3)} | P100: {=_xll.YCP($B100,P$3)} | Q100: {=_xll.YCP($B100,Q$3)} | R100: {=_xll.YCP($B100,R$3)} | S100: {=_xll.YCP($B100,S$3)} | T100: {=_xll.YCP($B100,T$3)} | U100: {=_xll.YCP($B100,U$3)} | V100: {=_xll.YCP($B100,V$3)} | ... CF100: {=_xll.YCP($B100,CF$3)}
A101: =Securities!B16 -> M:FLCSX | C101: {=_xll.YCI($B101,C$3)} | D101: {=_xll.YCI($B101,D$3)} | E101: {=_xll.YCI($B101,E$3)} | F101: {=_xll.YCI($B101,F$3)} | G101: {=_xll.YCI($B101,G$3)} | H101: {=_xll.YCI($B101,H$3)} | I101: {=_xll.YCI($B101,I$3)} | J101: {=_xll.YCI($B101,J$3)} | ... N101: {=_xll.YCI($B101,N$3)} | O101: {=_xll.YCP($B101,O$3)} | P101: {=_xll.YCP($B101,P$3)} | Q101: {=_xll.YCP($B101,Q$3)} | R101: {=_xll.YCP($B101,R$3)} | S101: {=_xll.YCP($B101,S$3)} | T101: {=_xll.YCP($B101,T$3)} | U101: {=_xll.YCP($B101,U$3)} | V101: {=_xll.YCP($B101,V$3)} | ... CF101: {=_xll.YCP($B101,CF$3)}
...
